Workbook

Sheet Table_Complete_CGNC_PCG
A1: TABLE DE CORRESPONDANCE COMPLÈTE PLAN COMPTABLE MAROCAIN (CGNC) → PCG FRANCE (ANC 2026)
A2: Sources : CGNC Maroc (9 classes) + PCG France ANC v.2026 | ✓ correspondance directe | ≈ approchée | ⚠ différence notable | ✗ sans équivalent PCG
A3: Cl. CGNC | B3: N° Cpt Maroc | C3: Intitulé Compte Marocain (CGNC) | D3: Statut | E3: N° Cpt France | F3: Intitulé Compte Français (PCG) | G3: Cl. PCG | H3: Observations / Divergences | I3: Clé recherche (sans zéros fin)
A4: CLASSE 1 — COMPTES DE FINANCEMENT PERMANENT (CGNC) → CLASSE 1 — COMPTES DE CAPITAUX (PCG)
A5: 1 | B5: 111 | C5: Capital social ou personnel | D5: ✓ | E5: 101 | F5: Capital | G5: 1 | H5: Identique | I5: 111
A6: 1 | B6: 1111 | C6: Capital social | D6: ✓ | E6: 1013 | F6: Capital souscrit - appelé, versé | G6: 1 | H6: Correspondance directe | I6: 1111
A7: 1 | B7: 1112 | C7: Fonds de dotation | D7: ≈ | E7: 108 | F7: Compte de l'exploitant | G7: 1 | H7: Spécifique associations marocaines | I7: 1112
A8: 1 | B8: 1117 | C8: Capital personnel | D8: ≈ | E8: 108 | F8: Compte de l'exploitant | G8: 1 | H8: EI/profession libérale | I8: 1117
A9: 1 | B9: 1119 | C9: Actionnaires, capital souscrit non appelé | D9: ✓ | E9: 109 | F9: Actionnaires : capital souscrit - non appelé | G9: 1 | H9: Identique - solde déducteur | I9: 1119
A10: 1 | B10: 112 | C10: Primes d'émission, de fusion et d'apport | D10: ✓ | E10: 104 | F10: Primes liées au capital | G10: 1 | H10: Même nature | I10: 112
A11: 1 | B11: 1121 | C11: Primes d'émission | D11: ✓ | E11: 1041 | F11: Primes d'émission | G11: 1 | H11: Identique | I11: 1121
A12: 1 | B12: 1122 | C12: Primes de fusion | D12: ✓ | E12: 1042 | F12: Primes de fusion | G12: 1 | H12: Identique | I12: 1122
A13: 1 | B13: 1123 | C13: Primes d'apport | D13: ✓ | E13: 1043 | F13: Primes d'apport | G13: 1 | H13: Identique | I13: 1123
A14: 1 | B14: 113 | C14: Ecarts de réévaluation | D14: ✓ | E14: 105 | F14: Écarts de réévaluation | G14: 1 | H14: Identique | I14: 113
A15: 1 | B15: 114 | C15: Réserve légale | D15: ✓ | E15: 1061 | F15: Réserve légale | G15: 1 | H15: Identique | I15: 114
A16: 1 | B16: 115 | C16: Autres réserves | D16: ✓ | E16: 106 | F16: Réserves | G16: 1 | H16: Regroupement en 106 France | I16: 115
... A58: 1 | B58: 172 | C58: Diminution des dettes de financement (écart conv.) | D58: ⚠ | E58: 4772 | F58: Diminution des dettes | G58: 4 | H58: ⚠ Maroc : cl.1 - France : cl.4 - reclassement nécessaire | I58: 172
A59: CLASSE 2 — COMPTES D'ACTIF IMMOBILISÉ (CGNC) → CLASSE 2 — COMPTES D'IMMOBILISATIONS (PCG)
A60: 2 | B60: 2111 | C60: Frais de constitution | D60: ⚠ | E60: 2011 | F60: Frais de constitution | G60: 2 | H60: ⚠ France : activation possible mais PCG préconise passage en charges - choix de méthode à documenter | I60: 2111
A61: 2 | B61: 2112 | C61: Frais préalables au démarrage | D61: ⚠ | E61: 2012 | F61: Frais de premier établissement | G61: 2 | H61: France : 20121 prospection ou 20122 publicité selon nature | I61: 2112
A62: 2 | B62: 2113 | C62: Frais d'augmentation du capital | D62: ✓ | E62: 2013 | F62: Frais d'augmentation de capital et opérations diverses | G62: 2 | H62: Identique | I62: 2113
A63: 2 | B63: 2114 | C63: Frais sur fusions, scissions, transformations | D63: ✓ | E63: 2013 | F63: Frais d'augmentation de capital et opérations diverses | G63: 2 | H63: Identique | I63: 2114
A64: 2 | B64: 2116 | C64: Frais de prospection | D64: ✓ | E64: 20121 | F64: Frais de prospection | G64: 2 | H64: Identique | I64: 2116
A65: 2 | B65: 2117 | C65: Frais de publicité | D65: ✓ | E65: 20122 | F65: Frais de publicité | G65: 2 | H65: Identique | I65: 2117
A66: 2 | B66: 2118 | C66: Autres frais préliminaires | D66: ≈ | E66: 2012 | F66: Frais de premier établissement | G66: 2 | H66: À ventiler selon nature | I66: 2118
A67: 2 | B67: 212 | C67: Charges à répartir sur plusieurs exercices | D67: ⚠ | E67: 486 | F67: Charges constatées d'avance | G67: 4 | H67: ⚠ France : pas d'actif distinct - CCA en 486 (cl.4) ou frais émission en 481 | I67: 212
A68: 2 | B68: 2121 | C68: Frais d'acquisition des immobilisations | D68: ⚠ | E68: 2xxx | F68: Inclus dans le coût d'acquisition de l'immobilisation | G68: 2 | H68: ⚠ PCG Art.213-8 : frais accessoires incorporés au coût - pas de compte séparé | I68: 2121
A69: 2 | B69: 2125 | C69: Frais d'émission des emprunts | D69: ✓ | E69: 481 | F69: Frais d'émission des emprunts | G69: 4 | H69: France : compte de régularisation actif (cl.4) - Maroc : actif immobilisé (cl.2) | I69: 2125
A70: 2 | B70: 213 | C70: Primes de remboursement des obligations | D70: ⚠ | E70: 169 | F70: Primes de remboursement des emprunts | G70: 1 | H70: ⚠ Maroc : actif immobilisé cl.2 - France : déducteur du passif cl.1 (169) | I70: 213
A71: 2 | B71: 221 | C71: Immobilisation en recherche et développement | D71: ✓ | E71: 203 | F71: Frais de développement | G71: 2 | H71: ⚠ France Art.212-3 : critères IAS 38 stricts - Maroc : critères moins détaillés | I71: 221
... A124: 2 | B124: 2958 | C124: Provisions pour dépréciation des autres titres | D124: ✓ | E124: 2971 | F124: Titres immobilisés | G124: 2 | H124: Identique | I124: 2958
A125: CLASSE 3 — ACTIF CIRCULANT HORS TRÉSORERIE (CGNC) → CLASSES 3 ET 4 (PCG) — DIFFÉRENCE ARCHITECTURALE MAJEURE
A126: 3 | B126: 311 | C126: Marchandises | D126: ✓ | E126: 37 | F126: Stocks de marchandises | G126: 3 | H126: Identique | I126: 311
A127: 3 | B127: 3121 | C127: Matières premières | D127: ✓ | E127: 31 | F127: Matières premières et fournitures | G127: 3 | H127: Identique | I127: 3121
A128: 3 | B128: 3122 | C128: Matières et fournitures consommables | D128: ✓ | E128: 321 | F128: Matières consommables | G128: 3 | H128: Identique | I128: 3122
A129: 3 | B129: 31223 | C129: Combustibles | D129: ✓ | E129: 3221 | F129: Combustibles | G129: 3 | H129: Identique | I129: 31223
A130: 3 | B130: 31224 | C130: Produits d'entretien | D130: ✓ | E130: 3222 | F130: Produits d'entretien | G130: 3 | H130: Identique | I130: 31224
A131: 3 | B131: 31225 | C131: Fournitures d'atelier et d'usine | D131: ✓ | E131: 3223 | F131: Fournitures d'atelier et d'usine | G131: 3 | H131: Identique | I131: 31225
A132: 3 | B132: 3123 | C132: Emballages | D132: ✓ | E132: 326 | F132: Emballages | G132: 3 | H132: Identique | I132: 3123
A133: 3 | B133: 313 | C133: Produits en cours | D133: ✓ | E133: 33 | F133: En-cours de production de biens | G133: 3 | H133: Identique | I133: 313
A134: 3 | B134: 3134 | C134: Services en cours | D134: ✓ | E134: 34 | F134: En-cours de production de services | G134: 3 | H134: Identique | I134: 3134
A135: 3 | B135: 314 | C135: Produits intermédiaires et produits résiduels | D135: ✓ | E135: 35 | F135: Stocks de produits | G135: 3 | H135: Identique | I135: 314
A136: 3 | B136: 315 | C136: Produits finis | D136: ✓ | E136: 355 | F136: Produits finis | G136: 3 | H136: Identique | I136: 315
A137: 3 | B137: 3411 | C137: Fournisseurs - avances et acomptes versés sur commandes | D137: ⚠ | E137: 4091 | F137: Fournisseurs - Avances et acomptes versés sur commandes | G137: 4 | H137: ⚠ Maroc : cl.3 - France : cl.4 - reclassement systématique | I137: 3411
... A164: 3 | B164: 395 | C164: Provisions pour dépréciation des TVP | D164: ⚠ | E164: 590 | F164: Dépréciations des valeurs mobilières de placement | G164: 5 | H164: ⚠ Reclassement cl.3 → cl.5 | I164: 395
A165: CLASSE 4 — PASSIF CIRCULANT HORS TRÉSORERIE (CGNC) → CLASSE 4 — COMPTES DE TIERS (PCG)
A166: 4 | B166: 4411 | C166: Fournisseurs | D166: ⚠ | E166: 401 | F166: Fournisseurs | G166: 4 | H166: ⚠ Maroc : 441x - France : 401x - numérotation différente | I166: 4411
A167: 4 | B167: 4413 | C167: Fournisseurs - retenues de garantie | D167: ✓ | E167: 4017 | F167: Fournisseurs - Retenues de garantie | G167: 4 | H167: Identique - numérotation différente | I167: 4413
A168: 4 | B168: 4415 | C168: Fournisseurs - effets à payer | D168: ✓ | E168: 403 | F168: Fournisseurs - Effets à payer | G168: 4 | H168: Identique | I168: 4415
A169: 4 | B169: 4417 | C169: Fournisseurs - factures non parvenues | D169: ✓ | E169: 408 | F169: Fournisseurs - Factures non parvenues | G169: 4 | H169: Identique | I169: 4417
A170: 4 | B170: 4418 | C170: Autres fournisseurs et comptes rattachés | D170: ✓ | E170: 401 | F170: Fournisseurs | G170: 4 | H170: À regrouper | I170: 4418
A171: 4 | B171: 4421 | C171: Clients - avances et acomptes reçus | D171: ⚠ | E171: 4191 | F171: Clients - Avances et acomptes reçus sur commandes | G171: 4 | H171: ⚠ Maroc : 442x - France : 419x | I171: 4421
A172: 4 | B172: 4425 | C172: Clients - dettes pour emballages consignés | D172: ✓ | E172: 4196 | F172: Clients - Dettes sur emballages et matériels consignés | G172: 4 | H172: Identique | I172: 4425
A173: 4 | B173: 4427 | C173: Rabais, remises et ristournes à accorder | D173: ✓ | E173: 4198 | F173: Rabais, remises, ristournes à accorder et autres avoirs à établir | G173: 4 | H173: Identique | I173: 4427
A174: 4 | B174: 4432 | C174: Rémunérations dues au personnel | D174: ⚠ | E174: 421 | F174: Personnel - Rémunérations dues | G174: 4 | H174: ⚠ Maroc : 443x - France : 42x | I174: 4432
A175: 4 | B175: 4433 | C175: Dépôts du personnel créditeurs | D175: ✓ | E175: 426 | F175: Personnel - Dépôts | G175: 4 | H175: Identique | I175: 4433
A176: 4 | B176: 4434 | C176: Oppositions sur salaires | D176: ✓ | E176: 427 | F176: Personnel - Oppositions | G176: 4 | H176: Identique | I176: 4434
A177: 4 | B177: 4437 | C177: Charges du personnel à payer | D177: ✓ | E177: 428 | F177: Personnel - Charges à payer | G177: 4 | H177: Identique | I177: 4437
... A205: 4 | B205: 4702 | C205: Diminution des dettes circulantes (écart conv.) | D205: ✓ | E205: 4772 | F205: Diminution des dettes | G205: 4 | H205: Identique | I205: 4702
A206: CLASSE 5 — COMPTES DE TRÉSORERIE (CGNC) → CLASSE 5 — COMPTES FINANCIERS (PCG)
A207: 5 | B207: 511 | C207: Chèques et valeurs à encaisser | D207: ✓ | E207: 511 | F207: Valeurs à l'encaissement | G207: 5 | H207: Identique | I207: 511
A208: 5 | B208: 5111 | C208: Chèques à encaisser | D208: ✓ | E208: 5112 | F208: Chèques à encaisser | G208: 5 | H208: Identique | I208: 5111
A209: 5 | B209: 5113 | C209: Effets à encaisser ou à l'encaissement | D209: ✓ | E209: 5113 | F209: Effets à l'encaissement | G209: 5 | H209: Identique | I209: 5113
A210: 5 | B210: 5141 | C210: Banques (solde débiteur) | D210: ✓ | E210: 5121 / 5124 | F210: Comptes en euros / Comptes en devises | G210: 5 | H210: ⚠ France distingue EUR et devises | I210: 5141
A211: 5 | B211: 5143 | C211: Trésorerie Générale | D211: ✓ | E211: 517 | F211: Autres organismes financiers | G211: 5 | H211: Correspondance directe | I211: 5143
A212: 5 | B212: 5146 | C212: Chèques postaux | D212: ≈ | E212: 512 | F212: Banques | G212: 5 | H212: France : CCP assimilés à banques | I212: 5146
A213: 5 | B213: 5161 | C213: Caisses | D213: ⚠ | E213: 530 | F213: Caisse | G213: 5 | H213: ⚠ Maroc : 516x - France : 530 - numérotation différente | I213: 5161
A214: 5 | B214: 5165 | C214: Régies d'avances et accréditifs | D214: ✓ | E214: 517 | F214: Autres organismes financiers | G214: 5 | H214: Correspondance directe | I214: 5165
A215: 5 | B215: 552 | C215: Crédits d'escompte | D215: ✓ | E215: 5191 | F215: Crédit de mobilisation de créances commerciales | G215: 5 | H215: Identique | I215: 552
A216: 5 | B216: 553 | C216: Crédits de trésorerie | D216: ✓ | E216: 519 | F216: Concours bancaires courants | G216: 5 | H216: Identique | I216: 553
A217: 5 | B217: 554 | C217: Banques (solde créditeur) | D217: ⚠ | E217: 519 | F217: Concours bancaires courants | G217: 5 | H217: ⚠ France : découvert en 519 - pas de compte séparé 554 | I217: 554
A218: 5 | B218: 59 | C218: Provisions pour dépréciation des comptes de trésorerie | D218: ✓ | E218: 59 | F218: Dépréciations des comptes financiers | G218: 5 | H218: Identique | I218: 59
A219: CLASSE 6 — COMPTES DE CHARGES (CGNC) → CLASSE 6 — COMPTES DE CHARGES (PCG)
A220: 6 | B220: 611 | C220: Achats revendus de marchandises | D220: ✓ | E220: 607 | F220: Achats de marchandises | G220: 6 | H220: Identique | I220: 611
A221: 6 | B221: 6114 | C221: Variation de stocks de marchandises | D221: ✓ | E221: 6037 | F221: Variation des stocks de marchandises | G221: 6 | H221: Identique | I221: 6114
A222: 6 | B222: 6121 | C222: Achats de matières premières | D222: ✓ | E222: 601 | F222: Achats stockés - Matières premières et fournitures | G222: 6 | H222: Identique | I222: 6121
A223: 6 | B223: 6122 | C223: Achats de matières et fournitures consommables | D223: ✓ | E223: 602 | F223: Achats stockés - Autres approvisionnements | G223: 6 | H223: Identique | I223: 6122
A224: 6 | B224: 61223 | C224: Achats de combustibles | D224: ✓ | E224: 60221 | F224: Combustibles | G224: 6 | H224: Identique | I224: 61223
A225: 6 | B225: 61224 | C225: Achats de produits d'entretien | D225: ✓ | E225: 60222 | F225: Produits d'entretien | G225: 6 | H225: Identique | I225: 61224
A226: 6 | B226: 61225 | C226: Achats de fournitures d'atelier et d'usine | D226: ✓ | E226: 60223 | F226: Fournitures d'atelier et d'usine | G226: 6 | H226: Identique | I226: 61225
A227: 6 | B227: 6124 | C227: Variation des stocks de matières et fournitures | D227: ✓ | E227: 603 | F227: Variation des stocks d'approvisionnements | G227: 6 | H227: Identique | I227: 6124
A228: 6 | B228: 61251 | C228: Achats de fournitures non stockables (eau, électricité) | D228: ✓ | E228: 6061 | F228: Fournitures non stockables (eau, énergie) | G228: 6 | H228: Identique | I228: 61251
A229: 6 | B229: 61252 | C229: Achats de fournitures d'entretien | D229: ✓ | E229: 6063 | F229: Fournitures d'entretien et de petit équipement | G229: 6 | H229: Identique | I229: 61252
A230: 6 | B230: 61253 | C230: Achats de petit outillage et petit équipement | D230: ✓ | E230: 6063 | F230: Fournitures d'entretien et de petit équipement | G230: 6 | H230: Ou 6064 selon nature | I230: 61253
A231: 6 | B231: 61254 | C231: Achats de fournitures de bureau | D231: ✓ | E231: 6064 | F231: Fournitures administratives | G231: 6 | H231: Identique | I231: 61254
... A308: 6 | B308: 6705 | C308: Imposition minimale annuelle des sociétés | D308: ⚠ | E308: 695 | F308: Impôts sur les bénéfices | G308: 6 | H308: ⚠ Spécifique Maroc (cotisation minimale) - pas d'équivalent exact France | I308: 6705
A309: CLASSE 7 — COMPTES DE PRODUITS (CGNC) → CLASSE 7 — COMPTES DE PRODUITS (PCG)
A310: 7 | B310: 711 | C310: Ventes de marchandises | D310: ✓ | E310: 707 | F310: Ventes de marchandises | G310: 7 | H310: Identique | I310: 711
A311: 7 | B311: 7121 | C311: Ventes de biens produits au Maroc | D311: ✓ | E311: 701 | F311: Ventes de produits finis | G311: 7 | H311: Identique | I311: 7121
A312: 7 | B312: 71241 | C312: Travaux | D312: ✓ | E312: 704 | F312: Travaux | G312: 7 | H312: Identique | I312: 71241
A313: 7 | B313: 71242 | C313: Etudes | D313: ✓ | E313: 705 | F313: Études | G313: 7 | H313: Identique | I313: 71242
A314: 7 | B314: 71243 | C314: Prestations de services | D314: ✓ | E314: 706 | F314: Prestations de services | G314: 7 | H314: Identique | I314: 71243
A315: 7 | B315: 7126 | C315: Redevances pour brevets, marques, droits | D315: ⚠ | E315: 751 | F315: Redevances pour concessions, brevets, licences | G315: 7 | H315: ⚠ Maroc : cl.71 produits exploitation - France : cl.751 autres produits gestion courante | I315: 7126
A316: 7 | B316: 71271 | C316: Locations diverses reçues | D316: ✓ | E316: 7083 | F316: Locations diverses | G316: 7 | H316: Identique | I316: 71271
A317: 7 | B317: 71272 | C317: Commissions et courtages reçus | D317: ✓ | E317: 7082 | F317: Commissions et courtages | G317: 7 | H317: Identique | I317: 71272
A318: 7 | B318: 71275 | C318: Bonis sur reprises d'emballages consignés | D318: ✓ | E318: 7086 | F318: Bonis sur reprises d'emballages consignés | G318: 7 | H318: Identique | I318: 71275
A319: 7 | B319: 713 | C319: Variation des stocks de produits | D319: ✓ | E319: 71 | F319: Production stockée (ou déstockage) | G319: 7 | H319: Identique | I319: 713
A320: 7 | B320: 714 | C320: Immobilisations produites par l'entreprise pour elle-même | D320: ✓ | E320: 72 | F320: Production immobilisée | G320: 7 | H320: Identique | I320: 714
A321: 7 | B321: 716 | C321: Subventions d'exploitation | D321: ✓ | E321: 741 | F321: Subventions d'exploitation | G321: 7 | H321: Identique | I321: 716
... A349: 7 | B349: 7596 | C349: Reprises non courantes sur provisions pour dépréciation | D349: ✓ | E349: 7876 | F349: Reprises sur dépréciations exceptionnelles | G349: 7 | H349: Identique | I349: 7596
...

Sheet Conversion_Balance retravail ba
A1: OUTIL DE CONVERSION AUTOMATIQUE BALANCE MAROCAINE (CGNC / MAD) → BALANCE FRANÇAISE (PCG / EUR)
A2: PARAMÈTRE TAUX DE CHANGE | C2: 10.8 | D2: Source : Bank Al-Maghrib Cours moyen | G2: ⚠ Modifiez uniquement la cellule E2 pour actualiser tous les montants en euros. Tous les calculs EUR sont dynamiques.
A3: ▼ COLLER votre balance ici (colonnes A à F) : N° compte | Intitulé | Mvt Débit | Mvt Crédit | Solde Débiteur | Solde Créditeur | F3: ▼ RÉSULTAT AUTOMATIQUE (Ne pas modifier ces colonnes)
A4: N° Compte Maroc (CGNC) | B4: Intitulé Compte Marocain | C4: Solde Débiteur (MAD) | D4: Solde Créditeur (MAD) | F4: N° Compte France (PCG) | G4: Intitulé Compte Français (PCG) | H4: Solde Débiteur (EUR) | I4: Solde Créditeur (EUR) | K4: Alertes / Points de vigilance | L4: Clé_norm
A5: 111100 | B5: Capital social | D5: 100000 | F5: =IF(A5="","",IFERROR(INDEX(Table_Complete_CGNC_PCG!$E:$E,MATCH(L5,Table_Complete_CGNC_PCG!$I:$I,0)),"? Non trouvé")) -> 1013 | G5: =IF(A5="","",IFERROR(INDEX(Table_Complete_CGNC_PCG!$F:$F,MATCH(L5,Table_Complete_CGNC_PCG!$I:$I,0)),"Non trouve — ajouter dans la table")) -> Capital souscrit - appelé, versé | H5: =IF(OR(A5="",C5="",C5=0),"",ROUND(C5/$C$2,2)) | I5: =IF(OR(A5="",D5="",D5=0),"",ROUND(D5/$C$2,2)) -> 9259.26 | K5: =IF(A5="","",IFERROR(IF(F5="? Non mappe","Compte non trouve - mapper manuellement",IF(AND(ISNUMBER(SEARCH("516",L5)),D5>0),"CAISSE CREDITRICE - anomalie a corriger",IF(IFERROR(INDEX(Table_Complete_CGNC_PCG!$D:$D,MATCH(L5,Table_Complete_CGNC_PCG!$I:$I,0)),"")="?","Retraitement requis - voir table","OK"))),"Erreur")) -> OK | L5: =LEFT(TEXT(A5,"0"),4) -> 1111
A6: 116100 | B6: Résultat net de l'exercice | D6: 861409.18 | F6: =IF(A6="","",IFERROR(INDEX(Table_Complete_CGNC_PCG!$E:$E,MATCH(L6,Table_Complete_CGNC_PCG!$I:$I,0)),"? Non trouvé")) -> 110 | G6: =IF(A6="","",IFERROR(INDEX(Table_Complete_CGNC_PCG!$F:$F,MATCH(L6,Table_Complete_CGNC_PCG!$I:$I,0)),"Non trouve — ajouter dans la table")) -> Report à nouveau - solde créditeur | H6: =IF(OR(A6="",C6="",C6=0),"",ROUND(C6/$C$2,2)) | I6: =IF(OR(A6="",D6="",D6=0),"",ROUND(D6/$C$2,2)) -> 79760.11 | K6: =IF(A6="","",IFERROR(IF(F6="? Non mappe","Compte non trouve - mapper manuellement",IF(AND(ISNUMBER(SEARCH("516",L6)),D6>0),"CAISSE CREDITRICE - anomalie a corriger",IF(IFERROR(INDEX(Table_Complete_CGNC_PCG!$D:$D,MATCH(L6,Table_Complete_CGNC_PCG!$I:$I,0)),"")="?","Retraitement requis - voir table","OK"))),"Erreur")) -> OK | L6: =LEFT(TEXT(A6,"0"),4) -> 1161
A7: 114100 | B7: Reserve légale | D7: 20000 | F7: =IF(A7="","",IFERROR(INDEX(Table_Complete_CGNC_PCG!$E:$E,MATCH(L7,Table_Complete_CGNC_PCG!$I:$I,0)),"? Non trouvé")) -> 1061 | G7: =IF(A7="","",IFERROR(INDEX(Table_Complete_CGNC_PCG!$F:$F,MATCH(L7,Table_Complete_CGNC_PCG!$I:$I,0)),"Non trouve — ajouter dans la table")) -> Réserve légale | H7: =IF(OR(A7="",C7="",C7=0),"",ROUND(C7/$C$2,2)) | I7: =IF(OR(A7="",D7="",D7=0),"",ROUND(D7/$C$2,2)) -> 1851.85 | K7: =IF(A7="","",IFERROR(IF(F7="? Non mappe","Compte non trouve - mapper manuellement",IF(AND(ISNUMBER(SEARCH("516",L7)),D7>0),"CAISSE CREDITRICE - anomalie a corriger",IF(IFERROR(INDEX(Table_Complete_CGNC_PCG!$D:$D,MATCH(L7,Table_Complete_CGNC_PCG!$I:$I,0)),"")="?","Retraitement requis - voir table","OK"))),"Erreur")) -> OK | L7: =LEFT(TEXT(A7,"0"),3) -> 114
A8: 211100 | B8: Frais de constitution | C8: 8200 | F8: =IF(A8="","",IFERROR(INDEX(Table_Complete_CGNC_PCG!$E:$E,MATCH(L8,Table_Complete_CGNC_PCG!$I:$I,0)),"? Non trouvé")) -> 2011 | G8: =IF(A8="","",IFERROR(INDEX(Table_Complete_CGNC_PCG!$F:$F,MATCH(L8,Table_Complete_CGNC_PCG!$I:$I,0)),"Non trouve — ajouter dans la table")) -> Frais de constitution | H8: =IF(OR(A8="",C8="",C8=0),"",ROUND(C8/$C$2,2)) -> 759.26 | I8: =IF(OR(A8="",D8="",D8=0),"",ROUND(D8/$C$2,2)) | K8: =IF(A8="","",IFERROR(IF(F8="? Non mappe","Compte non trouve - mapper manuellement",IF(AND(ISNUMBER(SEARCH("516",L8)),D8>0),"CAISSE CREDITRICE - anomalie a corriger",IF(IFERROR(INDEX(Table_Complete_CGNC_PCG!$D:$D,MATCH(L8,Table_Complete_CGNC_PCG!$I:$I,0)),"")="?","Retraitement requis - voir table","OK"))),"Erreur")) -> OK | L8: =LEFT(TEXT(A8,"0"),4) -> 2111
A9: 235600 | B9: Agencement, installation et aménagements divers | C9: 89830.33 | F9: =IF(A9="","",IFERROR(INDEX(Table_Complete_CGNC_PCG!$E:$E,MATCH(L9,Table_Complete_CGNC_PCG!$I:$I,0)),"? Non trouvé")) -> 2181 | G9: =IF(A9="","",IFERROR(INDEX(Table_Complete_CGNC_PCG!$F:$F,MATCH(L9,Table_Complete_CGNC_PCG!$I:$I,0)),"Non trouve — ajouter dans la table")) -> Installations générales, agencements, aménagements divers | H9: =IF(OR(A9="",C9="",C9=0),"",ROUND(C9/$C$2,2)) -> 8317.62 | I9: =IF(OR(A9="",D9="",D9=0),"",ROUND(D9/$C$2,2)) | K9: =IF(A9="","",IFERROR(IF(F9="? Non mappe","Compte non trouve - mapper manuellement",IF(AND(ISNUMBER(SEARCH("516",L9)),D9>0),"CAISSE CREDITRICE - anomalie a corriger",IF(IFERROR(INDEX(Table_Complete_CGNC_PCG!$D:$D,MATCH(L9,Table_Complete_CGNC_PCG!$I:$I,0)),"")="?","Retraitement requis - voir table","OK"))),"Erreur")) -> OK | L9: =LEFT(TEXT(A9,"0"),4) -> 2356
A10: 283500 | B10: Amortissements agencement - instalation | D10: 4045.36 | F10: =IF(A10="","",IFERROR(INDEX(Table_Complete_CGNC_PCG!$E:$E,MATCH(L10,Table_Complete_CGNC_PCG!$I:$I,0)),"? Non trouvé")) -> 2818 | G10: =IF(A10="","",IFERROR(INDEX(Table_Complete_CGNC_PCG!$F:$F,MATCH(L10,Table_Complete_CGNC_PCG!$I:$I,0)),"Non trouve — ajouter dans la table")) -> Autres immobilisations corporelles | H10: =IF(OR(A10="",C10="",C10=0),"",ROUND(C10/$C$2,2)) | I10: =IF(OR(A10="",D10="",D10=0),"",ROUND(D10/$C$2,2)) -> 374.57 | K10: =IF(A10="","",IFERROR(IF(F10="? Non mappe","Compte non trouve - mapper manuellement",IF(AND(ISNUMBER(SEARCH("516",L10)),D10>0),"CAISSE CREDITRICE - anomalie a corriger",IF(IFERROR(INDEX(Table_Complete_CGNC_PCG!$D:$D,MATCH(L10,Table_Complete_CGNC_PCG!$I:$I,0)),"")="?","Retraitement requis - voir table","OK"))),"Erreur")) -> OK | L10: =LEFT(TEXT(A10,"0"),4) -> 2835
A11: 281110 | B11: Amortissements des frais de constitution | D11: 3462.22 | F11: =IF(A11="","",IFERROR(INDEX(Table_Complete_CGNC_PCG!$E:$E,MATCH(L11,Table_Complete_CGNC_PCG!$I:$I,0)),"? Non trouvé")) -> 2801 | G11: =IF(A11="","",IFERROR(INDEX(Table_Complete_CGNC_PCG!$F:$F,MATCH(L11,Table_Complete_CGNC_PCG!$I:$I,0)),"Non trouve — ajouter dans la table")) -> Frais d'établissement (amortissements) | H11: =IF(OR(A11="",C11="",C11=0),"",ROUND(C11/$C$2,2)) | I11: =IF(OR(A11="",D11="",D11=0),"",ROUND(D11/$C$2,2)) -> 320.58 | K11: =IF(A11="","",IFERROR(IF(F11="? Non mappe","Compte non trouve - mapper manuellement",IF(AND(ISNUMBER(SEARCH("516",L11)),D11>0),"CAISSE CREDITRICE - anomalie a corriger",IF(IFERROR(INDEX(Table_Complete_CGNC_PCG!$D:$D,MATCH(L11,Table_Complete_CGNC_PCG!$I:$I,0)),"")="?","Retraitement requis - voir table","OK"))),"Erreur")) -> OK | L11: =LEFT(TEXT(A11,"0"),5) -> 28111
A12: 342100 | B12: Clients | C12: 202876.35 | F12: =IF(A12="","",IFERROR(INDEX(Table_Complete_CGNC_PCG!$E:$E,MATCH(L12,Table_Complete_CGNC_PCG!$I:$I,0)),"? Non trouvé")) -> 411 | G12: =IF(A12="","",IFERROR(INDEX(Table_Complete_CGNC_PCG!$F:$F,MATCH(L12,Table_Complete_CGNC_PCG!$I:$I,0)),"Non trouve — ajouter dans la table")) -> Clients | H12: =IF(OR(A12="",C12="",C12=0),"",ROUND(C12/$C$2,2)) -> 18784.85 | I12: =IF(OR(A12="",D12="",D12=0),"",ROUND(D12/$C$2,2)) | K12: =IF(A12="","",IFERROR(IF(F12="? Non mappe","Compte non trouve - mapper manuellement",IF(AND(ISNUMBER(SEARCH("516",L12)),D12>0),"CAISSE CREDITRICE - anomalie a corriger",IF(IFERROR(INDEX(Table_Complete_CGNC_PCG!$D:$D,MATCH(L12,Table_Complete_CGNC_PCG!$I:$I,0)),"")="?","Retraitement requis - voir table","OK"))),"Erreur")) -> OK | L12: =LEFT(TEXT(A12,"0"),4) -> 3421
A13: 3455200 | B13: ETAT - TVA récupérable sur les charges | C13: 2461.72 | F13: =IF(A13="","",IFERROR(INDEX(Table_Complete_CGNC_PCG!$E:$E,MATCH(L13,Table_Complete_CGNC_PCG!$I:$I,0)),"? Non trouvé")) -> 44566 | G13: =IF(A13="","",IFERROR(INDEX(Table_Complete_CGNC_PCG!$F:$F,MATCH(L13,Table_Complete_CGNC_PCG!$I:$I,0)),"Non trouve — ajouter dans la table")) -> TVA sur autres biens et services | H13: =IF(OR(A13="",C13="",C13=0),"",ROUND(C13/$C$2,2)) -> 227.94 | I13: =IF(OR(A13="",D13="",D13=0),"",ROUND(D13/$C$2,2)) | K13: =IF(A13="","",IFERROR(IF(F13="? Non mappe","Compte non trouve - mapper manuellement",IF(AND(ISNUMBER(SEARCH("516",L13)),D13>0),"CAISSE CREDITRICE - anomalie a corriger",IF(IFERROR(INDEX(Table_Complete_CGNC_PCG!$D:$D,MATCH(L13,Table_Complete_CGNC_PCG!$I:$I,0)),"")="?","Retraitement requis - voir table","OK"))),"Erreur")) -> OK | L13: =LEFT(TEXT(A13,"0"),5) -> 34552
A14: 441100 | B14: Fournisseurs A | D14: 9856 | F14: =IF(A14="","",IFERROR(INDEX(Table_Complete_CGNC_PCG!$E:$E,MATCH(L14,Table_Complete_CGNC_PCG!$I:$I,0)),"? Non trouvé")) -> 401 | G14: =IF(A14="","",IFERROR(INDEX(Table_Complete_CGNC_PCG!$F:$F,MATCH(L14,Table_Complete_CGNC_PCG!$I:$I,0)),"Non trouve — ajouter dans la table")) -> Fournisseurs | H14: =IF(OR(A14="",C14="",C14=0),"",ROUND(C14/$C$2,2)) | I14: =IF(OR(A14="",D14="",D14=0),"",ROUND(D14/$C$2,2)) -> 912.59 | K14: =IF(A14="","",IFERROR(IF(F14="? Non mappe","Compte non trouve - mapper manuellement",IF(AND(ISNUMBER(SEARCH("516",L14)),D14>0),"CAISSE CREDITRICE - anomalie a corriger",IF(IFERROR(INDEX(Table_Complete_CGNC_PCG!$D:$D,MATCH(L14,Table_Complete_CGNC_PCG!$I:$I,0)),"")="?","Retraitement requis - voir table","OK"))),"Erreur")) -> OK | L14: =LEFT(TEXT(A14,"0"),4) -> 4411
A15: 4411010 | B15: Fournisseurs B | D15: 4484.9 | F15: =IF(A15="","",IFERROR(INDEX(Table_Complete_CGNC_PCG!$E:$E,MATCH(L15,Table_Complete_CGNC_PCG!$I:$I,0)),"? Non trouvé")) -> 401 | G15: =IF(A15="","",IFERROR(INDEX(Table_Complete_CGNC_PCG!$F:$F,MATCH(L15,Table_Complete_CGNC_PCG!$I:$I,0)),"Non trouve — ajouter dans la table")) -> Fournisseurs | H15: =IF(OR(A15="",C15="",C15=0),"",ROUND(C15/$C$2,2)) | I15: =IF(OR(A15="",D15="",D15=0),"",ROUND(D15/$C$2,2)) -> 415.27 | K15: =IF(A15="","",IFERROR(IF(F15="? Non mappe","Compte non trouve - mapper manuellement",IF(AND(ISNUMBER(SEARCH("516",L15)),D15>0),"CAISSE CREDITRICE - anomalie a corriger",IF(IFERROR(INDEX(Table_Complete_CGNC_PCG!$D:$D,MATCH(L15,Table_Complete_CGNC_PCG!$I:$I,0)),"")="?","Retraitement requis - voir table","OK"))),"Erreur")) -> OK | L15: =LEFT(TEXT(A15,"0"),4) -> 4411
A16: 4411020 | B16: Fournisseurs C | D16: 3306.48 | F16: =IF(A16="","",IFERROR(INDEX(Table_Complete_CGNC_PCG!$E:$E,MATCH(L16,Table_Complete_CGNC_PCG!$I:$I,0)),"? Non trouvé")) -> 401 | G16: =IF(A16="","",IFERROR(INDEX(Table_Complete_CGNC_PCG!$F:$F,MATCH(L16,Table_Complete_CGNC_PCG!$I:$I,0)),"Non trouve — ajouter dans la table")) -> Fournisseurs | H16: =IF(OR(A16="",C16="",C16=0),"",ROUND(C16/$C$2,2)) | I16: =IF(OR(A16="",D16="",D16=0),"",ROUND(D16/$C$2,2)) -> 306.16 | K16: =IF(A16="","",IFERROR(IF(F16="? Non mappe","Compte non trouve - mapper manuellement",IF(AND(ISNUMBER(SEARCH("516",L16)),D16>0),"CAISSE CREDITRICE - anomalie a corriger",IF(IFERROR(INDEX(Table_Complete_CGNC_PCG!$D:$D,MATCH(L16,Table_Complete_CGNC_PCG!$I:$I,0)),"")="?","Retraitement requis - voir table","OK"))),"Erreur")) -> OK | L16: =LEFT(TEXT(A16,"0"),4) -> 4411
A17: 4411030 | B17: Fournisseurs D | D17: 997.93 | F17: =IF(A17="","",IFERROR(INDEX(Table_Complete_CGNC_PCG!$E:$E,MATCH(L17,Table_Complete_CGNC_PCG!$I:$I,0)),"? Non trouvé")) -> 401 | G17: =IF(A17="","",IFERROR(INDEX(Table_Complete_CGNC_PCG!$F:$F,MATCH(L17,Table_Complete_CGNC_PCG!$I:$I,0)),"Non trouve — ajouter dans la table")) -> Fournisseurs | H17: =IF(OR(A17="",C17="",C17=0),"",ROUND(C17/$C$2,2)) | I17: =IF(OR(A17="",D17="",D17=0),"",ROUND(D17/$C$2,2)) -> 92.4 | K17: =IF(A17="","",IFERROR(IF(F17="? Non mappe","Compte non trouve - mapper manuellement",IF(AND(ISNUMBER(SEARCH("516",L17)),D17>0),"CAISSE CREDITRICE - anomalie a corriger",IF(IFERROR(INDEX(Table_Complete_CGNC_PCG!$D:$D,MATCH(L17,Table_Complete_CGNC_PCG!$I:$I,0)),"")="?","Retraitement requis - voir table","OK"))),"Erreur")) -> OK | L17: =LEFT(TEXT(A17,"0"),4) -> 4411
A18: 4411040 | B18: Fournisseurs E | D18: 1116.34 | F18: =IF(A18="","",IFERROR(INDEX(Table_Complete_CGNC_PCG!$E:$E,MATCH(L18,Table_Complete_CGNC_PCG!$I:$I,0)),"? Non trouvé")) -> 401 | G18: =IF(A18="","",IFERROR(INDEX(Table_Complete_CGNC_PCG!$F:$F,MATCH(L18,Table_Complete_CGNC_PCG!$I:$I,0)),"Non trouve — ajouter dans la table")) -> Fournisseurs | H18: =IF(OR(A18="",C18="",C18=0),"",ROUND(C18/$C$2,2)) | I18: =IF(OR(A18="",D18="",D18=0),"",ROUND(D18/$C$2,2)) -> 103.36 | K18: =IF(A18="","",IFERROR(IF(F18="? Non mappe","Compte non trouve - mapper manuellement",IF(AND(ISNUMBER(SEARCH("516",L18)),D18>0),"CAISSE CREDITRICE - anomalie a corriger",IF(IFERROR(INDEX(Table_Complete_CGNC_PCG!$D:$D,MATCH(L18,Table_Complete_CGNC_PCG!$I:$I,0)),"")="?","Retraitement requis - voir table","OK"))),"Erreur")) -> OK | L18: =LEFT(TEXT(A18,"0"),4) -> 4411
A19: 4411050 | B19: Fournisseurs F | D19: 1925.77 | F19: =IF(A19="","",IFERROR(INDEX(Table_Complete_CGNC_PCG!$E:$E,MATCH(L19,Table_Complete_CGNC_PCG!$I:$I,0)),"? Non trouvé")) -> 401 | G19: =IF(A19="","",IFERROR(INDEX(Table_Complete_CGNC_PCG!$F:$F,MATCH(L19,Table_Complete_CGNC_PCG!$I:$I,0)),"Non trouve — ajouter dans la table")) -> Fournisseurs | H19: =IF(OR(A19="",C19="",C19=0),"",ROUND(C19/$C$2,2)) | I19: =IF(OR(A19="",D19="",D19=0),"",ROUND(D19/$C$2,2)) -> 178.31 | K19: =IF(A19="","",IFERROR(IF(F19="? Non mappe","Compte non trouve - mapper manuellement",IF(AND(ISNUMBER(SEARCH("516",L19)),D19>0),"CAISSE CREDITRICE - anomalie a corriger",IF(IFERROR(INDEX(Table_Complete_CGNC_PCG!$D:$D,MATCH(L19,Table_Complete_CGNC_PCG!$I:$I,0)),"")="?","Retraitement requis - voir table","OK"))),"Erreur")) -> OK | L19: =LEFT(TEXT(A19,"0"),4) -> 4411
A20: 4411060 | B20: Fournisseurs G | D20: 1443.51 | F20: =IF(A20="","",IFERROR(INDEX(Table_Complete_CGNC_PCG!$E:$E,MATCH(L20,Table_Complete_CGNC_PCG!$I:$I,0)),"? Non trouvé")) -> 401 | G20: =IF(A20="","",IFERROR(INDEX(Table_Complete_CGNC_PCG!$F:$F,MATCH(L20,Table_Complete_CGNC_PCG!$I:$I,0)),"Non trouve — ajouter dans la table")) -> Fournisseurs | H20: =IF(OR(A20="",C20="",C20=0),"",ROUND(C20/$C$2,2)) | I20: =IF(OR(A20="",D20="",D20=0),"",ROUND(D20/$C$2,2)) -> 133.66 | K20: =IF(A20="","",IFERROR(IF(F20="? Non mappe","Compte non trouve - mapper manuellement",IF(AND(ISNUMBER(SEARCH("516",L20)),D20>0),"CAISSE CREDITRICE - anomalie a corriger",IF(IFERROR(INDEX(Table_Complete_CGNC_PCG!$D:$D,MATCH(L20,Table_Complete_CGNC_PCG!$I:$I,0)),"")="?","Retraitement requis - voir table","OK"))),"Erreur")) -> OK | L20: =LEFT(TEXT(A20,"0"),4) -> 4411
A21: 4411070 | B21: Fournisseurs H | D21: 3950 | F21: =IF(A21="","",IFERROR(INDEX(Table_Complete_CGNC_PCG!$E:$E,MATCH(L21,Table_Complete_CGNC_PCG!$I:$I,0)),"? Non trouvé")) -> 401 | G21: =IF(A21="","",IFERROR(INDEX(Table_Complete_CGNC_PCG!$F:$F,MATCH(L21,Table_Complete_CGNC_PCG!$I:$I,0)),"Non trouve — ajouter dans la table")) -> Fournisseurs | H21: =IF(OR(A21="",C21="",C21=0),"",ROUND(C21/$C$2,2)) | I21: =IF(OR(A21="",D21="",D21=0),"",ROUND(D21/$C$2,2)) -> 365.74 | K21: =IF(A21="","",IFERROR(IF(F21="? Non mappe","Compte non trouve - mapper manuellement",IF(AND(ISNUMBER(SEARCH("516",L21)),D21>0),"CAISSE CREDITRICE - anomalie a corriger",IF(IFERROR(INDEX(Table_Complete_CGNC_PCG!$D:$D,MATCH(L21,Table_Complete_CGNC_PCG!$I:$I,0)),"")="?","Retraitement requis - voir table","OK"))),"Erreur")) -> OK | L21: =LEFT(TEXT(A21,"0"),4) -> 4411
A22: 4417000 | B22: Fournisseurs - factures non parvenues | D22: 1450.67 | F22: =IF(A22="","",IFERROR(INDEX(Table_Complete_CGNC_PCG!$E:$E,MATCH(L22,Table_Complete_CGNC_PCG!$I:$I,0)),"? Non trouvé")) -> 408 | G22: =IF(A22="","",IFERROR(INDEX(Table_Complete_CGNC_PCG!$F:$F,MATCH(L22,Table_Complete_CGNC_PCG!$I:$I,0)),"Non trouve — ajouter dans la table")) -> Fournisseurs - Factures non parvenues | H22: =IF(OR(A22="",C22="",C22=0),"",ROUND(C22/$C$2,2)) | I22: =IF(OR(A22="",D22="",D22=0),"",ROUND(D22/$C$2,2)) -> 134.32 | K22: =IF(A22="","",IFERROR(IF(F22="? Non mappe","Compte non trouve - mapper manuellement",IF(AND(ISNUMBER(SEARCH("516",L22)),D22>0),"CAISSE CREDITRICE - anomalie a corriger",IF(IFERROR(INDEX(Table_Complete_CGNC_PCG!$D:$D,MATCH(L22,Table_Complete_CGNC_PCG!$I:$I,0)),"")="?","Retraitement requis - voir table","OK"))),"Erreur")) -> OK | L22: =LEFT(TEXT(A22,"0"),4) -> 4417
A23: 4432000 | B23: Rémunérations dues au personnel | D23: 17321.28 | F23: =IF(A23="","",IFERROR(INDEX(Table_Complete_CGNC_PCG!$E:$E,MATCH(L23,Table_Complete_CGNC_PCG!$I:$I,0)),"? Non trouvé")) -> 421 | G23: =IF(A23="","",IFERROR(INDEX(Table_Complete_CGNC_PCG!$F:$F,MATCH(L23,Table_Complete_CGNC_PCG!$I:$I,0)),"Non trouve — ajouter dans la table")) -> Personnel - Rémunérations dues | H23: =IF(OR(A23="",C23="",C23=0),"",ROUND(C23/$C$2,2)) | I23: =IF(OR(A23="",D23="",D23=0),"",ROUND(D23/$C$2,2)) -> 1603.82 | K23: =IF(A23="","",IFERROR(IF(F23="? Non mappe","Compte non trouve - mapper manuellement",IF(AND(ISNUMBER(SEARCH("516",L23)),D23>0),"CAISSE CREDITRICE - anomalie a corriger",IF(IFERROR(INDEX(Table_Complete_CGNC_PCG!$D:$D,MATCH(L23,Table_Complete_CGNC_PCG!$I:$I,0)),"")="?","Retraitement requis - voir table","OK"))),"Erreur")) -> OK | L23: =LEFT(TEXT(A23,"0"),4) -> 4432
A24: 4455000 | B24: Etat, TVA facturée | C24: 33723.85 | F24: =IF(A24="","",IFERROR(INDEX(Table_Complete_CGNC_PCG!$E:$E,MATCH(L24,Table_Complete_CGNC_PCG!$I:$I,0)),"? Non trouvé")) -> 44571 | G24: =IF(A24="","",IFERROR(INDEX(Table_Complete_CGNC_PCG!$F:$F,MATCH(L24,Table_Complete_CGNC_PCG!$I:$I,0)),"Non trouve — ajouter dans la table")) -> TVA collectée | H24: =IF(OR(A24="",C24="",C24=0),"",ROUND(C24/$C$2,2)) -> 3122.58 | I24: =IF(OR(A24="",D24="",D24=0),"",ROUND(D24/$C$2,2)) | K24: =IF(A24="","",IFERROR(IF(F24="? Non mappe","Compte non trouve - mapper manuellement",IF(AND(ISNUMBER(SEARCH("516",L24)),D24>0),"CAISSE CREDITRICE - anomalie a corriger",IF(IFERROR(INDEX(Table_Complete_CGNC_PCG!$D:$D,MATCH(L24,Table_Complete_CGNC_PCG!$I:$I,0)),"")="?","Retraitement requis - voir table","OK"))),"Erreur")) -> OK | L24: =LEFT(TEXT(A24,"0"),4) -> 4455
A25: 4457000 | B25: Etat taxe de séjour | D25: 19598.65 | F25: =IF(A25="","",IFERROR(INDEX(Table_Complete_CGNC_PCG!$E:$E,MATCH(L25,Table_Complete_CGNC_PCG!$I:$I,0)),"? Non trouvé")) -> 447 | G25: =IF(A25="","",IFERROR(INDEX(Table_Complete_CGNC_PCG!$F:$F,MATCH(L25,Table_Complete_CGNC_PCG!$I:$I,0)),"Non trouve — ajouter dans la table")) -> Autres impôts, taxes et versements assimilés | H25: =IF(OR(A25="",C25="",C25=0),"",ROUND(C25/$C$2,2)) | I25: =IF(OR(A25="",D25="",D25=0),"",ROUND(D25/$C$2,2)) -> 1814.69 | K25: =IF(A25="","",IFERROR(IF(F25="? Non mappe","Compte non trouve - mapper manuellement",IF(AND(ISNUMBER(SEARCH("516",L25)),D25>0),"CAISSE CREDITRICE - anomalie a corriger",IF(IFERROR(INDEX(Table_Complete_CGNC_PCG!$D:$D,MATCH(L25,Table_Complete_CGNC_PCG!$I:$I,0)),"")="?","Retraitement requis - voir table","OK"))),"Erreur")) -> OK | L25: =LEFT(TEXT(A25,"0"),4) -> 4457
A26: 4456000 | B26: Etat, TVA due | D26: 48500 | F26: =IF(A26="","",IFERROR(INDEX(Table_Complete_CGNC_PCG!$E:$E,MATCH(L26,Table_Complete_CGNC_PCG!$I:$I,0)),"? Non trouvé")) -> 44551 | G26: =IF(A26="","",IFERROR(INDEX(Table_Complete_CGNC_PCG!$F:$F,MATCH(L26,Table_Complete_CGNC_PCG!$I:$I,0)),"Non trouve — ajouter dans la table")) -> TVA à décaisser | H26: =IF(OR(A26="",C26="",C26=0),"",ROUND(C26/$C$2,2)) | I26: =IF(OR(A26="",D26="",D26=0),"",ROUND(D26/$C$2,2)) -> 4490.74 | K26: =IF(A26="","",IFERROR(IF(F26="? Non mappe","Compte non trouve - mapper manuellement",IF(AND(ISNUMBER(SEARCH("516",L26)),D26>0),"CAISSE CREDITRICE - anomalie a corriger",IF(IFERROR(INDEX(Table_Complete_CGNC_PCG!$D:$D,MATCH(L26,Table_Complete_CGNC_PCG!$I:$I,0)),"")="?","Retraitement requis - voir table","OK"))),"Erreur")) -> OK | L26: =LEFT(TEXT(A26,"0"),4) -> 4456
A27: 4463000 | B27: Comptes courants des associés créditeurs | D27: 98270.5 | F27: =IF(A27="","",IFERROR(INDEX(Table_Complete_CGNC_PCG!$E:$E,MATCH(L27,Table_Complete_CGNC_PCG!$I:$I,0)),"? Non trouvé")) -> 455 | G27: =IF(A27="","",IFERROR(INDEX(Table_Complete_CGNC_PCG!$F:$F,MATCH(L27,Table_Complete_CGNC_PCG!$I:$I,0)),"Non trouve — ajouter dans la table")) -> Associés - Comptes courants | H27: =IF(OR(A27="",C27="",C27=0),"",ROUND(C27/$C$2,2)) | I27: =IF(OR(A27="",D27="",D27=0),"",ROUND(D27/$C$2,2)) -> 9099.12 | K27: =IF(A27="","",IFERROR(IF(F27="? Non mappe","Compte non trouve - mapper manuellement",IF(AND(ISNUMBER(SEARCH("516",L27)),D27>0),"CAISSE CREDITRICE - anomalie a corriger",IF(IFERROR(INDEX(Table_Complete_CGNC_PCG!$D:$D,MATCH(L27,Table_Complete_CGNC_PCG!$I:$I,0)),"")="?","Retraitement requis - voir table","OK"))),"Erreur")) -> OK | L27: =LEFT(TEXT(A27,"0"),4) -> 4463
A28: 5141000 | B28: Banques (ATIJARI WAFABANK) | C28: 951383.74 | F28: =IF(A28="","",IFERROR(INDEX(Table_Complete_CGNC_PCG!$E:$E,MATCH(L28,Table_Complete_CGNC_PCG!$I:$I,0)),"? Non mappe")) -> 5121 / 5124 | G28: =IF(A28="","",IFERROR(INDEX(Table_Complete_CGNC_PCG!$F:$F,MATCH(L28,Table_Complete_CGNC_PCG!$I:$I,0)),"Non trouve — ajouter dans la table")) -> Comptes en euros / Comptes en devises | H28: =IF(OR(A28="",C28="",C28=0),"",ROUND(C28/$C$2,2)) -> 88091.09 | I28: =IF(OR(A28="",D28="",D28=0),"",ROUND(D28/$C$2,2)) | K28: =IF(A28="","",IFERROR(IF(F28="? Non mappe","Compte non trouve - mapper manuellement",IF(AND(ISNUMBER(SEARCH("516",L28)),D28>0),"CAISSE CREDITRICE - anomalie a corriger",IF(IFERROR(INDEX(Table_Complete_CGNC_PCG!$D:$D,MATCH(L28,Table_Complete_CGNC_PCG!$I:$I,0)),"")="?","Retraitement requis - voir table","OK"))),"Erreur")) -> OK | L28: =LEFT(TEXT(A28,"0"),4) -> 5141
A29: 5161000 | B29: Caisses | C29: 60015.39 | F29: =IF(A29="","",IFERROR(INDEX(Table_Complete_CGNC_PCG!$E:$E,MATCH(L29,Table_Complete_CGNC_PCG!$I:$I,0)),"? Non mappe")) -> 530 | G29: =IF(A29="","",IFERROR(INDEX(Table_Complete_CGNC_PCG!$F:$F,MATCH(L29,Table_Complete_CGNC_PCG!$I:$I,0)),"Non trouve — ajouter dans la table")) -> Caisse | H29: =IF(OR(A29="",C29="",C29=0),"",ROUND(C29/$C$2,2)) -> 5556.98 | I29: =IF(OR(A29="",D29="",D29=0),"",ROUND(D29/$C$2,2)) | K29: =IF(A29="","",IFERROR(IF(F29="? Non mappe","Compte non trouve - mapper manuellement",IF(AND(ISNUMBER(SEARCH("516",L29)),D29>0),"CAISSE CREDITRICE - anomalie a corriger",IF(IFERROR(INDEX(Table_Complete_CGNC_PCG!$D:$D,MATCH(L29,Table_Complete_CGNC_PCG!$I:$I,0)),"")="?","Retraitement requis - voir table","OK"))),"Erreur")) -> OK | L29: =LEFT(TEXT(A29,"0"),4) -> 5161
A30: 6121100 | B30: Achats de matières premières A | C30: 93901.1 | F30: =IF(A30="","",IFERROR(INDEX(Table_Complete_CGNC_PCG!$E:$E,MATCH(L30,Table_Complete_CGNC_PCG!$I:$I,0)),"? Non mappe")) -> 601 | G30: =IF(A30="","",IFERROR(INDEX(Table_Complete_CGNC_PCG!$F:$F,MATCH(L30,Table_Complete_CGNC_PCG!$I:$I,0)),"Non trouve — ajouter dans la table")) -> Achats stockés - Matières premières et fournitures | H30: =IF(OR(A30="",C30="",C30=0),"",ROUND(C30/$C$2,2)) -> 8694.55 | I30: =IF(OR(A30="",D30="",D30=0),"",ROUND(D30/$C$2,2)) | K30: =IF(A30="","",IFERROR(IF(F30="? Non mappe","Compte non trouve - mapper manuellement",IF(AND(ISNUMBER(SEARCH("516",L30)),D30>0),"CAISSE CREDITRICE - anomalie a corriger",IF(IFERROR(INDEX(Table_Complete_CGNC_PCG!$D:$D,MATCH(L30,Table_Complete_CGNC_PCG!$I:$I,0)),"")="?","Retraitement requis - voir table","OK"))),"Erreur")) -> OK | L30: =LEFT(TEXT(A30,"0"),4) -> 6121
A31: 6122400 | B31: Achats de produits d'entretien | C31: 20595.42 | F31: =IF(A31="","",IFERROR(INDEX(Table_Complete_CGNC_PCG!$E:$E,MATCH(L31,Table_Complete_CGNC_PCG!$I:$I,0)),"? Non mappe")) -> 602 | G31: =IF(A31="","",IFERROR(INDEX(Table_Complete_CGNC_PCG!$F:$F,MATCH(L31,Table_Complete_CGNC_PCG!$I:$I,0)),"Non trouve — ajouter dans la table")) -> Achats stockés - Autres approvisionnements | H31: =IF(OR(A31="",C31="",C31=0),"",ROUND(C31/$C$2,2)) -> 1906.98 | I31: =IF(OR(A31="",D31="",D31=0),"",ROUND(D31/$C$2,2)) | K31: =IF(A31="","",IFERROR(IF(F31="? Non mappe","Compte non trouve - mapper manuellement",IF(AND(ISNUMBER(SEARCH("516",L31)),D31>0),"CAISSE CREDITRICE - anomalie a corriger",IF(IFERROR(INDEX(Table_Complete_CGNC_PCG!$D:$D,MATCH(L31,Table_Complete_CGNC_PCG!$I:$I,0)),"")="?","Retraitement requis - voir table","OK"))),"Erreur")) -> OK | L31: =LEFT(TEXT(A31,"0"),4) -> 6122
A32: 6125100 | B32: Achats de fournitures non stockables (eau, élec.) | C32: 9560.71 | F32: =IF(A32="","",IFERROR(INDEX(Table_Complete_CGNC_PCG!$E:$E,MATCH(L32,Table_Complete_CGNC_PCG!$I:$I,0)),"? Non mappe")) -> 6061 | G32: =IF(A32="","",IFERROR(INDEX(Table_Complete_CGNC_PCG!$F:$F,MATCH(L32,Table_Complete_CGNC_PCG!$I:$I,0)),"Non trouve — ajouter dans la table")) -> Fournitures non stockables (eau, énergie) | H32: =IF(OR(A32="",C32="",C32=0),"",ROUND(C32/$C$2,2)) -> 885.25 | I32: =IF(OR(A32="",D32="",D32=0),"",ROUND(D32/$C$2,2)) | K32: =IF(A32="","",IFERROR(IF(F32="? Non mappe","Compte non trouve - mapper manuellement",IF(AND(ISNUMBER(SEARCH("516",L32)),D32>0),"CAISSE CREDITRICE - anomalie a corriger",IF(IFERROR(INDEX(Table_Complete_CGNC_PCG!$D:$D,MATCH(L32,Table_Complete_CGNC_PCG!$I:$I,0)),"")="?","Retraitement requis - voir table","OK"))),"Erreur")) -> OK | L32: =LEFT(TEXT(A32,"0"),5) -> 61251
A33: 6125300 | B33: Achats de petit outillage et petit équipement | C33: 45528.66 | F33: =IF(A33="","",IFERROR(INDEX(Table_Complete_CGNC_PCG!$E:$E,MATCH(L33,Table_Complete_CGNC_PCG!$I:$I,0)),"? Non mappe")) -> 6063 | G33: =IF(A33="","",IFERROR(INDEX(Table_Complete_CGNC_PCG!$F:$F,MATCH(L33,Table_Complete_CGNC_PCG!$I:$I,0)),"Non trouve — ajouter dans la table")) -> Fournitures d'entretien et de petit équipement | H33: =IF(OR(A33="",C33="",C33=0),"",ROUND(C33/$C$2,2)) -> 4215.62 | I33: =IF(OR(A33="",D33="",D33=0),"",ROUND(D33/$C$2,2)) | K33: =IF(A33="","",IFERROR(IF(F33="? Non mappe","Compte non trouve - mapper manuellement",IF(AND(ISNUMBER(SEARCH("516",L33)),D33>0),"CAISSE CREDITRICE - anomalie a corriger",IF(IFERROR(INDEX(Table_Complete_CGNC_PCG!$D:$D,MATCH(L33,Table_Complete_CGNC_PCG!$I:$I,0)),"")="?","Retraitement requis - voir table","OK"))),"Erreur")) -> OK | L33: =LEFT(TEXT(A33,"0"),5) -> 61253
A34: 6133100 | B34: Entretien et réparations des biens immobiliers | C34: 46577.37 | F34: =IF(A34="","",IFERROR(INDEX(Table_Complete_CGNC_PCG!$E:$E,MATCH(L34,Table_Complete_CGNC_PCG!$I:$I,0)),"? Non mappe")) -> 6152 | G34: =IF(A34="","",IFERROR(INDEX(Table_Complete_CGNC_PCG!$F:$F,MATCH(L34,Table_Complete_CGNC_PCG!$I:$I,0)),"Non trouve — ajouter dans la table")) -> Entretien et réparation sur biens immobiliers | H34: =IF(OR(A34="",C34="",C34=0),"",ROUND(C34/$C$2,2)) -> 4312.72 | I34: =IF(OR(A34="",D34="",D34=0),"",ROUND(D34/$C$2,2)) | K34: =IF(A34="","",IFERROR(IF(F34="? Non mappe","Compte non trouve - mapper manuellement",IF(AND(ISNUMBER(SEARCH("516",L34)),D34>0),"CAISSE CREDITRICE - anomalie a corriger",IF(IFERROR(INDEX(Table_Complete_CGNC_PCG!$D:$D,MATCH(L34,Table_Complete_CGNC_PCG!$I:$I,0)),"")="?","Retraitement requis - voir table","OK"))),"Erreur")) -> OK | L34: =LEFT(TEXT(A34,"0"),5) -> 61331
A35: 6131200 | B35: Loyers Holding | C35: 114000 | F35: =IF(A35="","",IFERROR(INDEX(Table_Complete_CGNC_PCG!$E:$E,MATCH(L35,Table_Complete_CGNC_PCG!$I:$I,0)),"? Non mappe")) -> 6132 | G35: =IF(A35="","",IFERROR(INDEX(Table_Complete_CGNC_PCG!$F:$F,MATCH(L35,Table_Complete_CGNC_PCG!$I:$I,0)),"Non trouve — ajouter dans la table")) -> Locations immobilières | H35: =IF(OR(A35="",C35="",C35=0),"",ROUND(C35/$C$2,2)) -> 10555.56 | I35: =IF(OR(A35="",D35="",D35=0),"",ROUND(D35/$C$2,2)) | K35: =IF(A35="","",IFERROR(IF(F35="? Non mappe","Compte non trouve - mapper manuellement",IF(AND(ISNUMBER(SEARCH("516",L35)),D35>0),"CAISSE CREDITRICE - anomalie a corriger",IF(IFERROR(INDEX(Table_Complete_CGNC_PCG!$D:$D,MATCH(L35,Table_Complete_CGNC_PCG!$I:$I,0)),"")="?","Retraitement requis - voir table","OK"))),"Erreur")) -> OK | L35: =LEFT(TEXT(A35,"0"),5) -> 61312
A36: 6136500 | B36: Commissions plateformes | C36: 99388 | F36: =IF(A36="","",IFERROR(INDEX(Table_Complete_CGNC_PCG!$E:$E,MATCH(L36,Table_Complete_CGNC_PCG!$I:$I,0)),"? Non mappe")) -> 6226 | G36: =IF(A36="","",IFERROR(INDEX(Table_Complete_CGNC_PCG!$F:$F,MATCH(L36,Table_Complete_CGNC_PCG!$I:$I,0)),"Non trouve — ajouter dans la table")) -> Honoraires | H36: =IF(OR(A36="",C36="",C36=0),"",ROUND(C36/$C$2,2)) -> 9202.59 | I36: =IF(OR(A36="",D36="",D36=0),"",ROUND(D36/$C$2,2)) | K36: =IF(A36="","",IFERROR(IF(F36="? Non mappe","Compte non trouve - mapper manuellement",IF(AND(ISNUMBER(SEARCH("516",L36)),D36>0),"CAISSE CREDITRICE - anomalie a corriger",IF(IFERROR(INDEX(Table_Complete_CGNC_PCG!$D:$D,MATCH(L36,Table_Complete_CGNC_PCG!$I:$I,0)),"")="?","Retraitement requis - voir table","OK"))),"Erreur")) -> OK | L36: =LEFT(TEXT(A36,"0"),5) -> 61365
A37: 6136500 | B37: Honoraires divers | C37: 30605 | F37: =IF(A37="","",IFERROR(INDEX(Table_Complete_CGNC_PCG!$E:$E,MATCH(L37,Table_Complete_CGNC_PCG!$I:$I,0)),"? Non mappe")) -> 6226 | G37: =IF(A37="","",IFERROR(INDEX(Table_Complete_CGNC_PCG!$F:$F,MATCH(L37,Table_Complete_CGNC_PCG!$I:$I,0)),"Non trouve — ajouter dans la table")) -> Honoraires | H37: =IF(OR(A37="",C37="",C37=0),"",ROUND(C37/$C$2,2)) -> 2833.8 | I37: =IF(OR(A37="",D37="",D37=0),"",ROUND(D37/$C$2,2)) | K37: =IF(A37="","",IFERROR(IF(F37="? Non mappe","Compte non trouve - mapper manuellement",IF(AND(ISNUMBER(SEARCH("516",L37)),D37>0),"CAISSE CREDITRICE - anomalie a corriger",IF(IFERROR(INDEX(Table_Complete_CGNC_PCG!$D:$D,MATCH(L37,Table_Complete_CGNC_PCG!$I:$I,0)),"")="?","Retraitement requis - voir table","OK"))),"Erreur")) -> OK | L37: =LEFT(TEXT(A37,"0"),5) -> 61365
A38: 6141500 | B38: Documentation générale | C38: 4990 | F38: =IF(A38="","",IFERROR(INDEX(Table_Complete_CGNC_PCG!$E:$E,MATCH(L38,Table_Complete_CGNC_PCG!$I:$I,0)),"? Non mappe")) -> 6181 | G38: =IF(A38="","",IFERROR(INDEX(Table_Complete_CGNC_PCG!$F:$F,MATCH(L38,Table_Complete_CGNC_PCG!$I:$I,0)),"Non trouve — ajouter dans la table")) -> Documentation générale | H38: =IF(OR(A38="",C38="",C38=0),"",ROUND(C38/$C$2,2)) -> 462.04 | I38: =IF(OR(A38="",D38="",D38=0),"",ROUND(D38/$C$2,2)) | K38: =IF(A38="","",IFERROR(IF(F38="? Non mappe","Compte non trouve - mapper manuellement",IF(AND(ISNUMBER(SEARCH("516",L38)),D38>0),"CAISSE CREDITRICE - anomalie a corriger",IF(IFERROR(INDEX(Table_Complete_CGNC_PCG!$D:$D,MATCH(L38,Table_Complete_CGNC_PCG!$I:$I,0)),"")="?","Retraitement requis - voir table","OK"))),"Erreur")) -> OK | L38: =LEFT(TEXT(A38,"0"),5) -> 61415
A39: 6143100 | B39: Voyages et déplacements | C39: 32654.78 | F39: =IF(A39="","",IFERROR(INDEX(Table_Complete_CGNC_PCG!$E:$E,MATCH(L39,Table_Complete_CGNC_PCG!$I:$I,0)),"? Non mappe")) -> 6251 | G39: =IF(A39="","",IFERROR(INDEX(Table_Complete_CGNC_PCG!$F:$F,MATCH(L39,Table_Complete_CGNC_PCG!$I:$I,0)),"Non trouve — ajouter dans la table")) -> Voyages et déplacements | H39: =IF(OR(A39="",C39="",C39=0),"",ROUND(C39/$C$2,2)) -> 3023.59 | I39: =IF(OR(A39="",D39="",D39=0),"",ROUND(D39/$C$2,2)) | K39: =IF(A39="","",IFERROR(IF(F39="? Non mappe","Compte non trouve - mapper manuellement",IF(AND(ISNUMBER(SEARCH("516",L39)),D39>0),"CAISSE CREDITRICE - anomalie a corriger",IF(IFERROR(INDEX(Table_Complete_CGNC_PCG!$D:$D,MATCH(L39,Table_Complete_CGNC_PCG!$I:$I,0)),"")="?","Retraitement requis - voir table","OK"))),"Erreur")) -> OK | L39: =LEFT(TEXT(A39,"0"),5) -> 61431
A40: 6143600 | B40: Réceptions | C40: 20153.52 | F40: =IF(A40="","",IFERROR(INDEX(Table_Complete_CGNC_PCG!$E:$E,MATCH(L40,Table_Complete_CGNC_PCG!$I:$I,0)),"? Non mappe")) -> 6257 | G40: =IF(A40="","",IFERROR(INDEX(Table_Complete_CGNC_PCG!$F:$F,MATCH(L40,Table_Complete_CGNC_PCG!$I:$I,0)),"Non trouve — ajouter dans la table")) -> Réceptions | H40: =IF(OR(A40="",C40="",C40=0),"",ROUND(C40/$C$2,2)) -> 1866.07 | I40: =IF(OR(A40="",D40="",D40=0),"",ROUND(D40/$C$2,2)) | K40: =IF(A40="","",IFERROR(IF(F40="? Non mappe","Compte non trouve - mapper manuellement",IF(AND(ISNUMBER(SEARCH("516",L40)),D40>0),"CAISSE CREDITRICE - anomalie a corriger",IF(IFERROR(INDEX(Table_Complete_CGNC_PCG!$D:$D,MATCH(L40,Table_Complete_CGNC_PCG!$I:$I,0)),"")="?","Retraitement requis - voir table","OK"))),"Erreur")) -> OK | L40: =LEFT(TEXT(A40,"0"),5) -> 61436
A41: 6145500 | B41: Frais de téléphone | C41: 3359.97 | F41: =IF(A41="","",IFERROR(INDEX(Table_Complete_CGNC_PCG!$E:$E,MATCH(L41,Table_Complete_CGNC_PCG!$I:$I,0)),"? Non mappe")) -> 6262 | G41: =IF(A41="","",IFERROR(INDEX(Table_Complete_CGNC_PCG!$F:$F,MATCH(L41,Table_Complete_CGNC_PCG!$I:$I,0)),"Non trouve — ajouter dans la table")) -> Frais de téléphone | H41: =IF(OR(A41="",C41="",C41=0),"",ROUND(C41/$C$2,2)) -> 311.11 | I41: =IF(OR(A41="",D41="",D41=0),"",ROUND(D41/$C$2,2)) | K41: =IF(A41="","",IFERROR(IF(F41="? Non mappe","Compte non trouve - mapper manuellement",IF(AND(ISNUMBER(SEARCH("516",L41)),D41>0),"CAISSE CREDITRICE - anomalie a corriger",IF(IFERROR(INDEX(Table_Complete_CGNC_PCG!$D:$D,MATCH(L41,Table_Complete_CGNC_PCG!$I:$I,0)),"")="?","Retraitement requis - voir table","OK"))),"Erreur")) -> OK | L41: =LEFT(TEXT(A41,"0"),5) -> 61455
A42: 61312000 | B42: Location de materiel | C42: 78068.5 | F42: =IF(A42="","",IFERROR(INDEX(Table_Complete_CGNC_PCG!$E:$E,MATCH(L42,Table_Complete_CGNC_PCG!$I:$I,0)),"? Non mappe")) -> 6132 | G42: =IF(A42="","",IFERROR(INDEX(Table_Complete_CGNC_PCG!$F:$F,MATCH(L42,Table_Complete_CGNC_PCG!$I:$I,0)),"Non trouve — ajouter dans la table")) -> Locations immobilières | H42: =IF(OR(A42="",C42="",C42=0),"",ROUND(C42/$C$2,2)) -> 7228.56 | I42: =IF(OR(A42="",D42="",D42=0),"",ROUND(D42/$C$2,2)) | K42: =IF(A42="","",IFERROR(IF(F42="? Non mappe","Compte non trouve - mapper manuellement",IF(AND(ISNUMBER(SEARCH("516",L42)),D42>0),"CAISSE CREDITRICE - anomalie a corriger",IF(IFERROR(INDEX(Table_Complete_CGNC_PCG!$D:$D,MATCH(L42,Table_Complete_CGNC_PCG!$I:$I,0)),"")="?","Retraitement requis - voir table","OK"))),"Erreur")) -> OK | L42: =LEFT(TEXT(A42,"0"),5) -> 61312
A43: 6147300 | B43: Frais et commissions sur services bancaires | C43: 1121.9 | F43: =IF(A43="","",IFERROR(INDEX(Table_Complete_CGNC_PCG!$E:$E,MATCH(L43,Table_Complete_CGNC_PCG!$I:$I,0)),"? Non mappe")) -> 6278 | G43: =IF(A43="","",IFERROR(INDEX(Table_Complete_CGNC_PCG!$F:$F,MATCH(L43,Table_Complete_CGNC_PCG!$I:$I,0)),"Non trouve — ajouter dans la table")) -> Autres frais et commissions sur prestations de services | H43: =IF(OR(A43="",C43="",C43=0),"",ROUND(C43/$C$2,2)) -> 103.88 | I43: =IF(OR(A43="",D43="",D43=0),"",ROUND(D43/$C$2,2)) | K43: =IF(A43="","",IFERROR(IF(F43="? Non mappe","Compte non trouve - mapper manuellement",IF(AND(ISNUMBER(SEARCH("516",L43)),D43>0),"CAISSE CREDITRICE - anomalie a corriger",IF(IFERROR(INDEX(Table_Complete_CGNC_PCG!$D:$D,MATCH(L43,Table_Complete_CGNC_PCG!$I:$I,0)),"")="?","Retraitement requis - voir table","OK"))),"Erreur")) -> OK | L43: =LEFT(TEXT(A43,"0"),5) -> 61473
... A45: 6161100 | B45: Impots locaux | C45: 28239.8 | F45: =IF(A45="","",IFERROR(INDEX(Table_Complete_CGNC_PCG!$E:$E,MATCH(L45,Table_Complete_CGNC_PCG!$I:$I,0)),"? Non mappe")) -> 63513 | G45: =IF(A45="","",IFERROR(INDEX(Table_Complete_CGNC_PCG!$F:$F,MATCH(L45,Table_Complete_CGNC_PCG!$I:$I,0)),"Non trouve — ajouter dans la table")) -> Autres impôts locaux | H45: =IF(OR(A45="",C45="",C45=0),"",ROUND(C45/$C$2,2)) -> 2614.8 | I45: =IF(OR(A45="",D45="",D45=0),"",ROUND(D45/$C$2,2)) | K45: =IF(A45="","",IFERROR(IF(F45="? Non mappe","Compte non trouve - mapper manuellement",IF(AND(ISNUMBER(SEARCH("516",L45)),D45>0),"CAISSE CREDITRICE - anomalie a corriger",IF(IFERROR(INDEX(Table_Complete_CGNC_PCG!$D:$D,MATCH(L45,Table_Complete_CGNC_PCG!$I:$I,0)),"")="?","Retraitement requis - voir table","OK"))),"Erreur")) -> OK | L45: =LEFT(TEXT(A45,"0"),5) -> 61611
A46: 6134000 | B46: Prime d'assurance | C46: 28565.34 | F46: =IF(A46="","",IFERROR(INDEX(Table_Complete_CGNC_PCG!$E:$E,MATCH(L46,Table_Complete_CGNC_PCG!$I:$I,0)),"? Non mappe")) -> 616 | G46: =IF(A46="","",IFERROR(INDEX(Table_Complete_CGNC_PCG!$F:$F,MATCH(L46,Table_Complete_CGNC_PCG!$I:$I,0)),"Non trouve — ajouter dans la table")) -> Primes d'assurances | H46: =IF(OR(A46="",C46="",C46=0),"",ROUND(C46/$C$2,2)) -> 2644.94 | I46: =IF(OR(A46="",D46="",D46=0),"",ROUND(D46/$C$2,2)) | K46: =IF(A46="","",IFERROR(IF(F46="? Non mappe","Compte non trouve - mapper manuellement",IF(AND(ISNUMBER(SEARCH("516",L46)),D46>0),"CAISSE CREDITRICE - anomalie a corriger",IF(IFERROR(INDEX(Table_Complete_CGNC_PCG!$D:$D,MATCH(L46,Table_Complete_CGNC_PCG!$I:$I,0)),"")="?","Retraitement requis - voir table","OK"))),"Erreur")) -> OK | L46: =LEFT(TEXT(A46,"0"),4) -> 6134
A47: 6171100 | B47: Appointements et salaires | C47: 115609.28 | F47: =IF(A47="","",IFERROR(INDEX(Table_Complete_CGNC_PCG!$E:$E,MATCH(L47,Table_Complete_CGNC_PCG!$I:$I,0)),"? Non mappe")) -> 6411 | G47: =IF(A47="","",IFERROR(INDEX(Table_Complete_CGNC_PCG!$F:$F,MATCH(L47,Table_Complete_CGNC_PCG!$I:$I,0)),"Non trouve — ajouter dans la table")) -> Salaires, appointements | H47: =IF(OR(A47="",C47="",C47=0),"",ROUND(C47/$C$2,2)) -> 10704.56 | I47: =IF(OR(A47="",D47="",D47=0),"",ROUND(D47/$C$2,2)) | K47: =IF(A47="","",IFERROR(IF(F47="? Non mappe","Compte non trouve - mapper manuellement",IF(AND(ISNUMBER(SEARCH("516",L47)),D47>0),"CAISSE CREDITRICE - anomalie a corriger",IF(IFERROR(INDEX(Table_Complete_CGNC_PCG!$D:$D,MATCH(L47,Table_Complete_CGNC_PCG!$I:$I,0)),"")="?","Retraitement requis - voir table","OK"))),"Erreur")) -> OK | L47: =LEFT(TEXT(A47,"0"),5) -> 61711
A48: 6174100 | B48: Cotisations de sécurité sociale | C48: 19085.21 | F48: =IF(A48="","",IFERROR(INDEX(Table_Complete_CGNC_PCG!$E:$E,MATCH(L48,Table_Complete_CGNC_PCG!$I:$I,0)),"? Non mappe")) -> 6451 | G48: =IF(A48="","",IFERROR(INDEX(Table_Complete_CGNC_PCG!$F:$F,MATCH(L48,Table_Complete_CGNC_PCG!$I:$I,0)),"Non trouve — ajouter dans la table")) -> Cotisations à l'Urssaf | H48: =IF(OR(A48="",C48="",C48=0),"",ROUND(C48/$C$2,2)) -> 1767.15 | I48: =IF(OR(A48="",D48="",D48=0),"",ROUND(D48/$C$2,2)) | K48: =IF(A48="","",IFERROR(IF(F48="? Non mappe","Compte non trouve - mapper manuellement",IF(AND(ISNUMBER(SEARCH("516",L48)),D48>0),"CAISSE CREDITRICE - anomalie a corriger",IF(IFERROR(INDEX(Table_Complete_CGNC_PCG!$D:$D,MATCH(L48,Table_Complete_CGNC_PCG!$I:$I,0)),"")="?","Retraitement requis - voir table","OK"))),"Erreur")) -> OK | L48: =LEFT(TEXT(A48,"0"),5) -> 61741
A49: 6174300 | B49: Cotisations aux mutuelles | C49: 4283.35 | F49: =IF(A49="","",IFERROR(INDEX(Table_Complete_CGNC_PCG!$E:$E,MATCH(L49,Table_Complete_CGNC_PCG!$I:$I,0)),"? Non mappe")) -> 6452 | G49: =IF(A49="","",IFERROR(INDEX(Table_Complete_CGNC_PCG!$F:$F,MATCH(L49,Table_Complete_CGNC_PCG!$I:$I,0)),"Non trouve — ajouter dans la table")) -> Cotisations aux mutuelles | H49: =IF(OR(A49="",C49="",C49=0),"",ROUND(C49/$C$2,2)) -> 396.61 | I49: =IF(OR(A49="",D49="",D49=0),"",ROUND(D49/$C$2,2)) | K49: =IF(A49="","",IFERROR(IF(F49="? Non mappe","Compte non trouve - mapper manuellement",IF(AND(ISNUMBER(SEARCH("516",L49)),D49>0),"CAISSE CREDITRICE - anomalie a corriger",IF(IFERROR(INDEX(Table_Complete_CGNC_PCG!$D:$D,MATCH(L49,Table_Complete_CGNC_PCG!$I:$I,0)),"")="?","Retraitement requis - voir table","OK"))),"Erreur")) -> OK | L49: =LEFT(TEXT(A49,"0"),5) -> 61743
A50: 6583000 | B50: Pénalités et amendes fiscales | C50: 150 | F50: =IF(A50="","",IFERROR(INDEX(Table_Complete_CGNC_PCG!$E:$E,MATCH(L50,Table_Complete_CGNC_PCG!$I:$I,0)),"? Non mappe")) -> 6712 | G50: =IF(A50="","",IFERROR(INDEX(Table_Complete_CGNC_PCG!$F:$F,MATCH(L50,Table_Complete_CGNC_PCG!$I:$I,0)),"Non trouve — ajouter dans la table")) -> Pénalités et amendes fiscales et pénales | H50: =IF(OR(A50="",C50="",C50=0),"",ROUND(C50/$C$2,2)) -> 13.89 | I50: =IF(OR(A50="",D50="",D50=0),"",ROUND(D50/$C$2,2)) | K50: =IF(A50="","",IFERROR(IF(F50="? Non mappe","Compte non trouve - mapper manuellement",IF(AND(ISNUMBER(SEARCH("516",L50)),D50>0),"CAISSE CREDITRICE - anomalie a corriger",IF(IFERROR(INDEX(Table_Complete_CGNC_PCG!$D:$D,MATCH(L50,Table_Complete_CGNC_PCG!$I:$I,0)),"")="?","Retraitement requis - voir table","OK"))),"Erreur")) -> OK | L50: =LEFT(TEXT(A50,"0"),4) -> 6583
A51: 6192000 | B51: Dotations aux amortissements immos incorpo | C51: 3462.22 | F51: =IF(A51="","",IFERROR(INDEX(Table_Complete_CGNC_PCG!$E:$E,MATCH(L51,Table_Complete_CGNC_PCG!$I:$I,0)),"? Non mappe")) -> 68111 | G51: =IF(A51="","",IFERROR(INDEX(Table_Complete_CGNC_PCG!$F:$F,MATCH(L51,Table_Complete_CGNC_PCG!$I:$I,0)),"Non trouve — ajouter dans la table")) -> Immobilisations incorporelles | H51: =IF(OR(A51="",C51="",C51=0),"",ROUND(C51/$C$2,2)) -> 320.58 | I51: =IF(OR(A51="",D51="",D51=0),"",ROUND(D51/$C$2,2)) | K51: =IF(A51="","",IFERROR(IF(F51="? Non mappe","Compte non trouve - mapper manuellement",IF(AND(ISNUMBER(SEARCH("516",L51)),D51>0),"CAISSE CREDITRICE - anomalie a corriger",IF(IFERROR(INDEX(Table_Complete_CGNC_PCG!$D:$D,MATCH(L51,Table_Complete_CGNC_PCG!$I:$I,0)),"")="?","Retraitement requis - voir table","OK"))),"Erreur")) -> OK | L51: =LEFT(TEXT(A51,"0"),4) -> 6192
A52: 6193000 | B52: Dotations aux amortissements immos corpo | C52: 4045.36 | F52: =IF(A52="","",IFERROR(INDEX(Table_Complete_CGNC_PCG!$E:$E,MATCH(L52,Table_Complete_CGNC_PCG!$I:$I,0)),"? Non mappe")) -> 68112 | G52: =IF(A52="","",IFERROR(INDEX(Table_Complete_CGNC_PCG!$F:$F,MATCH(L52,Table_Complete_CGNC_PCG!$I:$I,0)),"Non trouve — ajouter dans la table")) -> Immobilisations corporelles | H52: =IF(OR(A52="",C52="",C52=0),"",ROUND(C52/$C$2,2)) -> 374.57 | I52: =IF(OR(A52="",D52="",D52=0),"",ROUND(D52/$C$2,2)) | K52: =IF(A52="","",IFERROR(IF(F52="? Non mappe","Compte non trouve - mapper manuellement",IF(AND(ISNUMBER(SEARCH("516",L52)),D52>0),"CAISSE CREDITRICE - anomalie a corriger",IF(IFERROR(INDEX(Table_Complete_CGNC_PCG!$D:$D,MATCH(L52,Table_Complete_CGNC_PCG!$I:$I,0)),"")="?","Retraitement requis - voir table","OK"))),"Erreur")) -> OK | L52: =LEFT(TEXT(A52,"0"),4) -> 6193
A53: 6588000 | B53: Autres charges non courantes des exercices antérieurs | C53: 2007.82 | F53: =IF(A53="","",IFERROR(INDEX(Table_Complete_CGNC_PCG!$E:$E,MATCH(L53,Table_Complete_CGNC_PCG!$I:$I,0)),"? Non mappe")) -> 672 | G53: =IF(A53="","",IFERROR(INDEX(Table_Complete_CGNC_PCG!$F:$F,MATCH(L53,Table_Complete_CGNC_PCG!$I:$I,0)),"Non trouve — ajouter dans la table")) -> Charges sur exercices antérieurs | H53: =IF(OR(A53="",C53="",C53=0),"",ROUND(C53/$C$2,2)) -> 185.91 | I53: =IF(OR(A53="",D53="",D53=0),"",ROUND(D53/$C$2,2)) | K53: =IF(A53="","",IFERROR(IF(F53="? Non mappe","Compte non trouve - mapper manuellement",IF(AND(ISNUMBER(SEARCH("516",L53)),D53>0),"CAISSE CREDITRICE - anomalie a corriger",IF(IFERROR(INDEX(Table_Complete_CGNC_PCG!$D:$D,MATCH(L53,Table_Complete_CGNC_PCG!$I:$I,0)),"")="?","Retraitement requis - voir table","OK"))),"Erreur")) -> OK | L53: =LEFT(TEXT(A53,"0"),4) -> 6588
A54: 7124300 | B54: hébergement | D54: 621180.56 | F54: =IF(A54="","",IFERROR(INDEX(Table_Complete_CGNC_PCG!$E:$E,MATCH(L54,Table_Complete_CGNC_PCG!$I:$I,0)),"? Non mappe")) -> 706 | G54: =IF(A54="","",IFERROR(INDEX(Table_Complete_CGNC_PCG!$F:$F,MATCH(L54,Table_Complete_CGNC_PCG!$I:$I,0)),"Non trouve — ajouter dans la table")) -> Prestations de services | H54: =IF(OR(A54="",C54="",C54=0),"",ROUND(C54/$C$2,2)) | I54: =IF(OR(A54="",D54="",D54=0),"",ROUND(D54/$C$2,2)) -> 57516.72 | K54: =IF(A54="","",IFERROR(IF(F54="? Non mappe","Compte non trouve - mapper manuellement",IF(AND(ISNUMBER(SEARCH("516",L54)),D54>0),"CAISSE CREDITRICE - anomalie a corriger",IF(IFERROR(INDEX(Table_Complete_CGNC_PCG!$D:$D,MATCH(L54,Table_Complete_CGNC_PCG!$I:$I,0)),"")="?","Retraitement requis - voir table","OK"))),"Erreur")) -> OK | L54: =LEFT(TEXT(A54,"0"),5) -> 71243 | S54: =IF(R54="","",IF(AND(LEN(R54)>3,RIGHT(R54,1)="0"),LEFT(R54,LEN(R54)-1),R54)) | T54: =IF(S54="","",IF(AND(LEN(S54)>3,RIGHT(S54,1)="0"),LEFT(S54,LEN(S54)-1),S54)) | U54: =IF(T54="","",IF(AND(LEN(T54)>3,RIGHT(T54,1)="0"),LEFT(T54,LEN(T54)-1),T54))
A55: 7124310 | B55: Petits dejeuners | D55: 96524.09 | F55: =IF(A55="","",IFERROR(INDEX(Table_Complete_CGNC_PCG!$E:$E,MATCH(L55,Table_Complete_CGNC_PCG!$I:$I,0)),"? Non mappe")) -> 706 | G55: =IF(A55="","",IFERROR(INDEX(Table_Complete_CGNC_PCG!$F:$F,MATCH(L55,Table_Complete_CGNC_PCG!$I:$I,0)),"Non trouve — ajouter dans la table")) -> Prestations de services | H55: =IF(OR(A55="",C55="",C55=0),"",ROUND(C55/$C$2,2)) | I55: =IF(OR(A55="",D55="",D55=0),"",ROUND(D55/$C$2,2)) -> 8937.42 | K55: =IF(A55="","",IFERROR(IF(F55="? Non mappe","Compte non trouve - mapper manuellement",IF(AND(ISNUMBER(SEARCH("516",L55)),D55>0),"CAISSE CREDITRICE - anomalie a corriger",IF(IFERROR(INDEX(Table_Complete_CGNC_PCG!$D:$D,MATCH(L55,Table_Complete_CGNC_PCG!$I:$I,0)),"")="?","Retraitement requis - voir table","OK"))),"Erreur")) -> OK | L55: =LEFT(TEXT(A55,"0"),5) -> 71243 | S55: =IF(R55="","",IF(AND(LEN(R55)>3,RIGHT(R55,1)="0"),LEFT(R55,LEN(R55)-1),R55)) | T55: =IF(S55="","",IF(AND(LEN(S55)>3,RIGHT(S55,1)="0"),LEFT(S55,LEN(S55)-1),S55)) | U55: =IF(T55="","",IF(AND(LEN(T55)>3,RIGHT(T55,1)="0"),LEFT(T55,LEN(T55)-1),T55))
A56: 7124320 | B56: Spa | D56: 88903.51 | F56: =IF(A56="","",IFERROR(INDEX(Table_Complete_CGNC_PCG!$E:$E,MATCH(L56,Table_Complete_CGNC_PCG!$I:$I,0)),"? Non mappe")) -> 706 | G56: =IF(A56="","",IFERROR(INDEX(Table_Complete_CGNC_PCG!$F:$F,MATCH(L56,Table_Complete_CGNC_PCG!$I:$I,0)),"Non trouve — ajouter dans la table")) -> Prestations de services | H56: =IF(OR(A56="",C56="",C56=0),"",ROUND(C56/$C$2,2)) | I56: =IF(OR(A56="",D56="",D56=0),"",ROUND(D56/$C$2,2)) -> 8231.81 | K56: =IF(A56="","",IFERROR(IF(F56="? Non mappe","Compte non trouve - mapper manuellement",IF(AND(ISNUMBER(SEARCH("516",L56)),D56>0),"CAISSE CREDITRICE - anomalie a corriger",IF(IFERROR(INDEX(Table_Complete_CGNC_PCG!$D:$D,MATCH(L56,Table_Complete_CGNC_PCG!$I:$I,0)),"")="?","Retraitement requis - voir table","OK"))),"Erreur")) -> OK | L56: =LEFT(TEXT(A56,"0"),5) -> 71243 | S56: =IF(R56="","",IF(AND(LEN(R56)>3,RIGHT(R56,1)="0"),LEFT(R56,LEN(R56)-1),R56)) | T56: =IF(S56="","",IF(AND(LEN(S56)>3,RIGHT(S56,1)="0"),LEFT(S56,LEN(S56)-1),S56)) | U56: =IF(T56="","",IF(AND(LEN(T56)>3,RIGHT(T56,1)="0"),LEFT(T56,LEN(T56)-1),T56))
A57: 7124330 | B57: Activites excursion | D57: 68750.45 | F57: =IF(A57="","",IFERROR(INDEX(Table_Complete_CGNC_PCG!$E:$E,MATCH(L57,Table_Complete_CGNC_PCG!$I:$I,0)),"? Non mappe")) -> 706 | G57: =IF(A57="","",IFERROR(INDEX(Table_Complete_CGNC_PCG!$F:$F,MATCH(L57,Table_Complete_CGNC_PCG!$I:$I,0)),"Non trouve — ajouter dans la table")) -> Prestations de services | H57: =IF(OR(A57="",C57="",C57=0),"",ROUND(C57/$C$2,2)) | I57: =IF(OR(A57="",D57="",D57=0),"",ROUND(D57/$C$2,2)) -> 6365.78 | K57: =IF(A57="","",IFERROR(IF(F57="? Non mappe","Compte non trouve - mapper manuellement",IF(AND(ISNUMBER(SEARCH("516",L57)),D57>0),"CAISSE CREDITRICE - anomalie a corriger",IF(IFERROR(INDEX(Table_Complete_CGNC_PCG!$D:$D,MATCH(L57,Table_Complete_CGNC_PCG!$I:$I,0)),"")="?","Retraitement requis - voir table","OK"))),"Erreur")) -> OK | L57: =LEFT(TEXT(A57,"0"),5) -> 71243 | S57: =IF(R57="","",IF(AND(LEN(R57)>3,RIGHT(R57,1)="0"),LEFT(R57,LEN(R57)-1),R57)) | T57: =IF(S57="","",IF(AND(LEN(S57)>3,RIGHT(S57,1)="0"),LEFT(S57,LEN(S57)-1),S57)) | U57: =IF(T57="","",IF(AND(LEN(T57)>3,RIGHT(T57,1)="0"),LEFT(T57,LEN(T57)-1),T57))
A58: 7111000 | B58: Boissons alcools | D58: 96487.89 | F58: =IF(A58="","",IFERROR(INDEX(Table_Complete_CGNC_PCG!$E:$E,MATCH(L58,Table_Complete_CGNC_PCG!$I:$I,0)),"? Non mappe")) -> 707 | G58: =IF(A58="","",IFERROR(INDEX(Table_Complete_CGNC_PCG!$F:$F,MATCH(L58,Table_Complete_CGNC_PCG!$I:$I,0)),"Non trouve — ajouter dans la table")) -> Ventes de marchandises | H58: =IF(OR(A58="",C58="",C58=0),"",ROUND(C58/$C$2,2)) | I58: =IF(OR(A58="",D58="",D58=0),"",ROUND(D58/$C$2,2)) -> 8934.06 | K58: =IF(A58="","",IFERROR(IF(F58="? Non mappe","Compte non trouve - mapper manuellement",IF(AND(ISNUMBER(SEARCH("516",L58)),D58>0),"CAISSE CREDITRICE - anomalie a corriger",IF(IFERROR(INDEX(Table_Complete_CGNC_PCG!$D:$D,MATCH(L58,Table_Complete_CGNC_PCG!$I:$I,0)),"")="?","Retraitement requis - voir table","OK"))),"Erreur")) -> OK | L58: =LEFT(TEXT(A58,"0"),3) -> 711 | S58: =IF(R58="","",IF(AND(LEN(R58)>3,RIGHT(R58,1)="0"),LEFT(R58,LEN(R58)-1),R58)) | T58: =IF(S58="","",IF(AND(LEN(S58)>3,RIGHT(S58,1)="0"),LEFT(S58,LEN(S58)-1),S58)) | U58: =IF(T58="","",IF(AND(LEN(T58)>3,RIGHT(T58,1)="0"),LEFT(T58,LEN(T58)-1),T58))
F59: =IF(A59="","",IFERROR(INDEX(Table_Complete_CGNC_PCG!$E:$E,MATCH(L59,Table_Complete_CGNC_PCG!$I:$I,0)),"? Non mappe")) | G59: =IF(A59="","",IFERROR(INDEX(Table_Complete_CGNC_PCG!$F:$F,MATCH(L59,Table_Complete_CGNC_PCG!$I:$I,0)),"Non trouve — ajouter dans la table")) | H59: =IF(OR(A59="",C59="",C59=0),"",ROUND(C59/$C$2,2)) | I59: =IF(OR(A59="",D59="",D59=0),"",ROUND(D59/$C$2,2)) | K59: =IF(A59="","",IFERROR(IF(F59="? Non mappe","Compte non trouve - mapper manuellement",IF(AND(ISNUMBER(SEARCH("516",L59)),D59>0),"CAISSE CREDITRICE - anomalie a corriger",IF(IFERROR(INDEX(Table_Complete_CGNC_PCG!$D:$D,MATCH(L59,Table_Complete_CGNC_PCG!$I:$I,0)),"")="?","Retraitement requis - voir table","OK"))),"Erreur")) | L59: =LEFT(TEXT(A59,"0"),4) -> 0 | M59: =IF(A59="","",TRIM(A59&"")) | N59: =IF(M59="","",IF(AND(LEN(M59)>3,RIGHT(M59,1)="0"),LEFT(M59,LEN(M59)-1),M59)) | O59: =IF(N59="","",IF(AND(LEN(N59)>3,RIGHT(N59,1)="0"),LEFT(N59,LEN(N59)-1),N59)) | P59: =IF(O59="","",IF(AND(LEN(O59)>3,RIGHT(O59,1)="0"),LEFT(O59,LEN(O59)-1),O59)) | Q59: =IF(P59="","",IF(AND(LEN(P59)>3,RIGHT(P59,1)="0"),LEFT(P59,LEN(P59)-1),P59)) | R59: =IF(Q59="","",IF(AND(LEN(Q59)>3,RIGHT(Q59,1)="0"),LEFT(Q59,LEN(Q59)-1),Q59)) | S59: =IF(R59="","",IF(AND(LEN(R59)>3,RIGHT(R59,1)="0"),LEFT(R59,LEN(R59)-1),R59)) | T59: =IF(S59="","",IF(AND(LEN(S59)>3,RIGHT(S59,1)="0"),LEFT(S59,LEN(S59)-1),S59)) | U59: =IF(T59="","",IF(AND(LEN(T59)>3,RIGHT(T59,1)="0"),LEFT(T59,LEN(T59)-1),T59))
F60: =IF(A60="","",IFERROR(INDEX(Table_Complete_CGNC_PCG!$E:$E,MATCH(L60,Table_Complete_CGNC_PCG!$I:$I,0)),"? Non mappe")) | G60: =IF(A60="","",IFERROR(INDEX(Table_Complete_CGNC_PCG!$F:$F,MATCH(L60,Table_Complete_CGNC_PCG!$I:$I,0)),"Non trouve — ajouter dans la table")) | H60: =IF(OR(A60="",C60="",C60=0),"",ROUND(C60/$C$2,2)) | I60: =IF(OR(A60="",D60="",D60=0),"",ROUND(D60/$C$2,2)) | K60: =IF(A60="","",IFERROR(IF(F60="? Non mappe","Compte non trouve - mapper manuellement",IF(AND(ISNUMBER(SEARCH("516",L60)),D60>0),"CAISSE CREDITRICE - anomalie a corriger",IF(IFERROR(INDEX(Table_Complete_CGNC_PCG!$D:$D,MATCH(L60,Table_Complete_CGNC_PCG!$I:$I,0)),"")="?","Retraitement requis - voir table","OK"))),"Erreur")) | L60: =LEFT(TEXT(A60,"0"),4) -> 0 | M60: =IF(A60="","",TRIM(A60&"")) | N60: =IF(M60="","",IF(AND(LEN(M60)>3,RIGHT(M60,1)="0"),LEFT(M60,LEN(M60)-1),M60)) | O60: =IF(N60="","",IF(AND(LEN(N60)>3,RIGHT(N60,1)="0"),LEFT(N60,LEN(N60)-1),N60)) | P60: =IF(O60="","",IF(AND(LEN(O60)>3,RIGHT(O60,1)="0"),LEFT(O60,LEN(O60)-1),O60)) | Q60: =IF(P60="","",IF(AND(LEN(P60)>3,RIGHT(P60,1)="0"),LEFT(P60,LEN(P60)-1),P60)) | R60: =IF(Q60="","",IF(AND(LEN(Q60)>3,RIGHT(Q60,1)="0"),LEFT(Q60,LEN(Q60)-1),Q60)) | S60: =IF(R60="","",IF(AND(LEN(R60)>3,RIGHT(R60,1)="0"),LEFT(R60,LEN(R60)-1),R60)) | T60: =IF(S60="","",IF(AND(LEN(S60)>3,RIGHT(S60,1)="0"),LEFT(S60,LEN(S60)-1),S60)) | U60: =IF(T60="","",IF(AND(LEN(T60)>3,RIGHT(T60,1)="0"),LEFT(T60,LEN(T60)-1),T60))
F61: =IF(A61="","",IFERROR(INDEX(Table_Complete_CGNC_PCG!$E:$E,MATCH(L61,Table_Complete_CGNC_PCG!$I:$I,0)),"? Non mappe")) | G61: =IF(A61="","",IFERROR(INDEX(Table_Complete_CGNC_PCG!$F:$F,MATCH(L61,Table_Complete_CGNC_PCG!$I:$I,0)),"Non trouve — ajouter dans la table")) | H61: =IF(OR(A61="",C61="",C61=0),"",ROUND(C61/$C$2,2)) | I61: =IF(OR(A61="",D61="",D61=0),"",ROUND(D61/$C$2,2)) | K61: =IF(A61="","",IFERROR(IF(F61="? Non mappe","Compte non trouve - mapper manuellement",IF(AND(ISNUMBER(SEARCH("516",L61)),D61>0),"CAISSE CREDITRICE - anomalie a corriger",IF(IFERROR(INDEX(Table_Complete_CGNC_PCG!$D:$D,MATCH(L61,Table_Complete_CGNC_PCG!$I:$I,0)),"")="?","Retraitement requis - voir table","OK"))),"Erreur")) | L61: =LEFT(TEXT(A61,"0"),4) -> 0 | M61: =IF(A61="","",TRIM(A61&"")) | N61: =IF(M61="","",IF(AND(LEN(M61)>3,RIGHT(M61,1)="0"),LEFT(M61,LEN(M61)-1),M61)) | O61: =IF(N61="","",IF(AND(LEN(N61)>3,RIGHT(N61,1)="0"),LEFT(N61,LEN(N61)-1),N61)) | P61: =IF(O61="","",IF(AND(LEN(O61)>3,RIGHT(O61,1)="0"),LEFT(O61,LEN(O61)-1),O61)) | Q61: =IF(P61="","",IF(AND(LEN(P61)>3,RIGHT(P61,1)="0"),LEFT(P61,LEN(P61)-1),P61)) | R61: =IF(Q61="","",IF(AND(LEN(Q61)>3,RIGHT(Q61,1)="0"),LEFT(Q61,LEN(Q61)-1),Q61)) | S61: =IF(R61="","",IF(AND(LEN(R61)>3,RIGHT(R61,1)="0"),LEFT(R61,LEN(R61)-1),R61)) | T61: =IF(S61="","",IF(AND(LEN(S61)>3,RIGHT(S61,1)="0"),LEFT(S61,LEN(S61)-1),S61)) | U61: =IF(T61="","",IF(AND(LEN(T61)>3,RIGHT(T61,1)="0"),LEFT(T61,LEN(T61)-1),T61))
F62: =IF(A62="","",IFERROR(INDEX(Table_Complete_CGNC_PCG!$E:$E,MATCH(L62,Table_Complete_CGNC_PCG!$I:$I,0)),"? Non mappe")) | G62: =IF(A62="","",IFERROR(INDEX(Table_Complete_CGNC_PCG!$F:$F,MATCH(L62,Table_Complete_CGNC_PCG!$I:$I,0)),"Non trouve — ajouter dans la table")) | H62: =IF(OR(A62="",C62="",C62=0),"",ROUND(C62/$C$2,2)) | I62: =IF(OR(A62="",D62="",D62=0),"",ROUND(D62/$C$2,2)) | K62: =IF(A62="","",IFERROR(IF(F62="? Non mappe","Compte non trouve - mapper manuellement",IF(AND(ISNUMBER(SEARCH("516",L62)),D62>0),"CAISSE CREDITRICE - anomalie a corriger",IF(IFERROR(INDEX(Table_Complete_CGNC_PCG!$D:$D,MATCH(L62,Table_Complete_CGNC_PCG!$I:$I,0)),"")="?","Retraitement requis - voir table","OK"))),"Erreur")) | L62: =LEFT(TEXT(A62,"0"),4) -> 0 | M62: =IF(A62="","",TRIM(A62&"")) | N62: =IF(M62="","",IF(AND(LEN(M62)>3,RIGHT(M62,1)="0"),LEFT(M62,LEN(M62)-1),M62)) | O62: =IF(N62="","",IF(AND(LEN(N62)>3,RIGHT(N62,1)="0"),LEFT(N62,LEN(N62)-1),N62)) | P62: =IF(O62="","",IF(AND(LEN(O62)>3,RIGHT(O62,1)="0"),LEFT(O62,LEN(O62)-1),O62)) | Q62: =IF(P62="","",IF(AND(LEN(P62)>3,RIGHT(P62,1)="0"),LEFT(P62,LEN(P62)-1),P62)) | R62: =IF(Q62="","",IF(AND(LEN(Q62)>3,RIGHT(Q62,1)="0"),LEFT(Q62,LEN(Q62)-1),Q62)) | S62: =IF(R62="","",IF(AND(LEN(R62)>3,RIGHT(R62,1)="0"),LEFT(R62,LEN(R62)-1),R62)) | T62: =IF(S62="","",IF(AND(LEN(S62)>3,RIGHT(S62,1)="0"),LEFT(S62,LEN(S62)-1),S62)) | U62: =IF(T62="","",IF(AND(LEN(T62)>3,RIGHT(T62,1)="0"),LEFT(T62,LEN(T62)-1),T62))
F63: =IF(A63="","",IFERROR(INDEX(Table_Complete_CGNC_PCG!$E:$E,MATCH(L63,Table_Complete_CGNC_PCG!$I:$I,0)),"? Non mappe")) | G63: =IF(A63="","",IFERROR(INDEX(Table_Complete_CGNC_PCG!$F:$F,MATCH(L63,Table_Complete_CGNC_PCG!$I:$I,0)),"Non trouve — ajouter dans la table")) | H63: =IF(OR(A63="",C63="",C63=0),"",ROUND(C63/$C$2,2)) | I63: =IF(OR(A63="",D63="",D63=0),"",ROUND(D63/$C$2,2)) | K63: =IF(A63="","",IFERROR(IF(F63="? Non mappe","Compte non trouve - mapper manuellement",IF(AND(ISNUMBER(SEARCH("516",L63)),D63>0),"CAISSE CREDITRICE - anomalie a corriger",IF(IFERROR(INDEX(Table_Complete_CGNC_PCG!$D:$D,MATCH(L63,Table_Complete_CGNC_PCG!$I:$I,0)),"")="?","Retraitement requis - voir table","OK"))),"Erreur")) | L63: =LEFT(TEXT(A63,"0"),4) -> 0 | M63: =IF(A63="","",TRIM(A63&"")) | N63: =IF(M63="","",IF(AND(LEN(M63)>3,RIGHT(M63,1)="0"),LEFT(M63,LEN(M63)-1),M63)) | O63: =IF(N63="","",IF(AND(LEN(N63)>3,RIGHT(N63,1)="0"),LEFT(N63,LEN(N63)-1),N63)) | P63: =IF(O63="","",IF(AND(LEN(O63)>3,RIGHT(O63,1)="0"),LEFT(O63,LEN(O63)-1),O63)) | Q63: =IF(P63="","",IF(AND(LEN(P63)>3,RIGHT(P63,1)="0"),LEFT(P63,LEN(P63)-1),P63)) | R63: =IF(Q63="","",IF(AND(LEN(Q63)>3,RIGHT(Q63,1)="0"),LEFT(Q63,LEN(Q63)-1),Q63)) | S63: =IF(R63="","",IF(AND(LEN(R63)>3,RIGHT(R63,1)="0"),LEFT(R63,LEN(R63)-1),R63)) | T63: =IF(S63="","",IF(AND(LEN(S63)>3,RIGHT(S63,1)="0"),LEFT(S63,LEN(S63)-1),S63)) | U63: =IF(T63="","",IF(AND(LEN(T63)>3,RIGHT(T63,1)="0"),LEFT(T63,LEN(T63)-1),T63))
F64: =IF(A64="","",IFERROR(INDEX(Table_Complete_CGNC_PCG!$E:$E,MATCH(L64,Table_Complete_CGNC_PCG!$I:$I,0)),"? Non mappe")) | G64: =IF(A64="","",IFERROR(INDEX(Table_Complete_CGNC_PCG!$F:$F,MATCH(L64,Table_Complete_CGNC_PCG!$I:$I,0)),"Non trouve — ajouter dans la table")) | H64: =IF(OR(A64="",C64="",C64=0),"",ROUND(C64/$C$2,2)) | I64: =IF(OR(A64="",D64="",D64=0),"",ROUND(D64/$C$2,2)) | K64: =IF(A64="","",IFERROR(IF(F64="? Non mappe","Compte non trouve - mapper manuellement",IF(AND(ISNUMBER(SEARCH("516",L64)),D64>0),"CAISSE CREDITRICE - anomalie a corriger",IF(IFERROR(INDEX(Table_Complete_CGNC_PCG!$D:$D,MATCH(L64,Table_Complete_CGNC_PCG!$I:$I,0)),"")="?","Retraitement requis - voir table","OK"))),"Erreur")) | L64: =LEFT(TEXT(A64,"0"),4) -> 0 | M64: =IF(A64="","",TRIM(A64&"")) | N64: =IF(M64="","",IF(AND(LEN(M64)>3,RIGHT(M64,1)="0"),LEFT(M64,LEN(M64)-1),M64)) | O64: =IF(N64="","",IF(AND(LEN(N64)>3,RIGHT(N64,1)="0"),LEFT(N64,LEN(N64)-1),N64)) | P64: =IF(O64="","",IF(AND(LEN(O64)>3,RIGHT(O64,1)="0"),LEFT(O64,LEN(O64)-1),O64)) | Q64: =IF(P64="","",IF(AND(LEN(P64)>3,RIGHT(P64,1)="0"),LEFT(P64,LEN(P64)-1),P64)) | R64: =IF(Q64="","",IF(AND(LEN(Q64)>3,RIGHT(Q64,1)="0"),LEFT(Q64,LEN(Q64)-1),Q64)) | S64: =IF(R64="","",IF(AND(LEN(R64)>3,RIGHT(R64,1)="0"),LEFT(R64,LEN(R64)-1),R64)) | T64: =IF(S64="","",IF(AND(LEN(S64)>3,RIGHT(S64,1)="0"),LEFT(S64,LEN(S64)-1),S64)) | U64: =IF(T64="","",IF(AND(LEN(T64)>3,RIGHT(T64,1)="0"),LEFT(T64,LEN(T64)-1),T64))
F65: =IF(A65="","",IFERROR(INDEX(Table_Complete_CGNC_PCG!$E:$E,MATCH(L65,Table_Complete_CGNC_PCG!$I:$I,0)),"? Non mappe")) | G65: =IF(A65="","",IFERROR(INDEX(Table_Complete_CGNC_PCG!$F:$F,MATCH(L65,Table_Complete_CGNC_PCG!$I:$I,0)),"Non trouve — ajouter dans la table")) | H65: =IF(OR(A65="",C65="",C65=0),"",ROUND(C65/$C$2,2)) | I65: =IF(OR(A65="",D65="",D65=0),"",ROUND(D65/$C$2,2)) | K65: =IF(A65="","",IFERROR(IF(F65="? Non mappe","Compte non trouve - mapper manuellement",IF(AND(ISNUMBER(SEARCH("516",L65)),D65>0),"CAISSE CREDITRICE - anomalie a corriger",IF(IFERROR(INDEX(Table_Complete_CGNC_PCG!$D:$D,MATCH(L65,Table_Complete_CGNC_PCG!$I:$I,0)),"")="?","Retraitement requis - voir table","OK"))),"Erreur")) | L65: =LEFT(TEXT(A65,"0"),4) -> 0 | M65: =IF(A65="","",TRIM(A65&"")) | N65: =IF(M65="","",IF(AND(LEN(M65)>3,RIGHT(M65,1)="0"),LEFT(M65,LEN(M65)-1),M65)) | O65: =IF(N65="","",IF(AND(LEN(N65)>3,RIGHT(N65,1)="0"),LEFT(N65,LEN(N65)-1),N65)) | P65: =IF(O65="","",IF(AND(LEN(O65)>3,RIGHT(O65,1)="0"),LEFT(O65,LEN(O65)-1),O65)) | Q65: =IF(P65="","",IF(AND(LEN(P65)>3,RIGHT(P65,1)="0"),LEFT(P65,LEN(P65)-1),P65)) | R65: =IF(Q65="","",IF(AND(LEN(Q65)>3,RIGHT(Q65,1)="0"),LEFT(Q65,LEN(Q65)-1),Q65)) | S65: =IF(R65="","",IF(AND(LEN(R65)>3,RIGHT(R65,1)="0"),LEFT(R65,LEN(R65)-1),R65)) | T65: =IF(S65="","",IF(AND(LEN(S65)>3,RIGHT(S65,1)="0"),LEFT(S65,LEN(S65)-1),S65)) | U65: =IF(T65="","",IF(AND(LEN(T65)>3,RIGHT(T65,1)="0"),LEFT(T65,LEN(T65)-1),T65))
F66: =IF(A66="","",IFERROR(INDEX(Table_Complete_CGNC_PCG!$E:$E,MATCH(L66,Table_Complete_CGNC_PCG!$I:$I,0)),"? Non mappe")) | G66: =IF(A66="","",IFERROR(INDEX(Table_Complete_CGNC_PCG!$F:$F,MATCH(L66,Table_Complete_CGNC_PCG!$I:$I,0)),"Non trouve — ajouter dans la table")) | H66: =IF(OR(A66="",C66="",C66=0),"",ROUND(C66/$C$2,2)) | I66: =IF(OR(A66="",D66="",D66=0),"",ROUND(D66/$C$2,2)) | K66: =IF(A66="","",IFERROR(IF(F66="? Non mappe","Compte non trouve - mapper manuellement",IF(AND(ISNUMBER(SEARCH("516",L66)),D66>0),"CAISSE CREDITRICE - anomalie a corriger",IF(IFERROR(INDEX(Table_Complete_CGNC_PCG!$D:$D,MATCH(L66,Table_Complete_CGNC_PCG!$I:$I,0)),"")="?","Retraitement requis - voir table","OK"))),"Erreur")) | L66: =LEFT(TEXT(A66,"0"),4) -> 0 | M66: =IF(A66="","",TRIM(A66&"")) | N66: =IF(M66="","",IF(AND(LEN(M66)>3,RIGHT(M66,1)="0"),LEFT(M66,LEN(M66)-1),M66)) | O66: =IF(N66="","",IF(AND(LEN(N66)>3,RIGHT(N66,1)="0"),LEFT(N66,LEN(N66)-1),N66)) | P66: =IF(O66="","",IF(AND(LEN(O66)>3,RIGHT(O66,1)="0"),LEFT(O66,LEN(O66)-1),O66)) | Q66: =IF(P66="","",IF(AND(LEN(P66)>3,RIGHT(P66,1)="0"),LEFT(P66,LEN(P66)-1),P66)) | R66: =IF(Q66="","",IF(AND(LEN(Q66)>3,RIGHT(Q66,1)="0"),LEFT(Q66,LEN(Q66)-1),Q66)) | S66: =IF(R66="","",IF(AND(LEN(R66)>3,RIGHT(R66,1)="0"),LEFT(R66,LEN(R66)-1),R66)) | T66: =IF(S66="","",IF(AND(LEN(S66)>3,RIGHT(S66,1)="0"),LEFT(S66,LEN(S66)-1),S66)) | U66: =IF(T66="","",IF(AND(LEN(T66)>3,RIGHT(T66,1)="0"),LEFT(T66,LEN(T66)-1),T66))
F67: =IF(A67="","",IFERROR(INDEX(Table_Complete_CGNC_PCG!$E:$E,MATCH(L67,Table_Complete_CGNC_PCG!$I:$I,0)),"? Non mappe")) | G67: =IF(A67="","",IFERROR(INDEX(Table_Complete_CGNC_PCG!$F:$F,MATCH(L67,Table_Complete_CGNC_PCG!$I:$I,0)),"Non trouve — ajouter dans la table")) | H67: =IF(OR(A67="",C67="",C67=0),"",ROUND(C67/$C$2,2)) | I67: =IF(OR(A67="",D67="",D67=0),"",ROUND(D67/$C$2,2)) | K67: =IF(A67="","",IFERROR(IF(F67="? Non mappe","Compte non trouve - mapper manuellement",IF(AND(ISNUMBER(SEARCH("516",L67)),D67>0),"CAISSE CREDITRICE - anomalie a corriger",IF(IFERROR(INDEX(Table_Complete_CGNC_PCG!$D:$D,MATCH(L67,Table_Complete_CGNC_PCG!$I:$I,0)),"")="?","Retraitement requis - voir table","OK"))),"Erreur")) | L67: =LEFT(TEXT(A67,"0"),4) -> 0 | M67: =IF(A67="","",TRIM(A67&"")) | N67: =IF(M67="","",IF(AND(LEN(M67)>3,RIGHT(M67,1)="0"),LEFT(M67,LEN(M67)-1),M67)) | O67: =IF(N67="","",IF(AND(LEN(N67)>3,RIGHT(N67,1)="0"),LEFT(N67,LEN(N67)-1),N67)) | P67: =IF(O67="","",IF(AND(LEN(O67)>3,RIGHT(O67,1)="0"),LEFT(O67,LEN(O67)-1),O67)) | Q67: =IF(P67="","",IF(AND(LEN(P67)>3,RIGHT(P67,1)="0"),LEFT(P67,LEN(P67)-1),P67)) | R67: =IF(Q67="","",IF(AND(LEN(Q67)>3,RIGHT(Q67,1)="0"),LEFT(Q67,LEN(Q67)-1),Q67)) | S67: =IF(R67="","",IF(AND(LEN(R67)>3,RIGHT(R67,1)="0"),LEFT(R67,LEN(R67)-1),R67)) | T67: =IF(S67="","",IF(AND(LEN(S67)>3,RIGHT(S67,1)="0"),LEFT(S67,LEN(S67)-1),S67)) | U67: =IF(T67="","",IF(AND(LEN(T67)>3,RIGHT(T67,1)="0"),LEFT(T67,LEN(T67)-1),T67))
F68: =IF(A68="","",IFERROR(INDEX(Table_Complete_CGNC_PCG!$E:$E,MATCH(L68,Table_Complete_CGNC_PCG!$I:$I,0)),"? Non mappe")) | G68: =IF(A68="","",IFERROR(INDEX(Table_Complete_CGNC_PCG!$F:$F,MATCH(L68,Table_Complete_CGNC_PCG!$I:$I,0)),"Non trouve — ajouter dans la table")) | H68: =IF(OR(A68="",C68="",C68=0),"",ROUND(C68/$C$2,2)) | I68: =IF(OR(A68="",D68="",D68=0),"",ROUND(D68/$C$2,2)) | K68: =IF(A68="","",IFERROR(IF(F68="? Non mappe","Compte non trouve - mapper manuellement",IF(AND(ISNUMBER(SEARCH("516",L68)),D68>0),"CAISSE CREDITRICE - anomalie a corriger",IF(IFERROR(INDEX(Table_Complete_CGNC_PCG!$D:$D,MATCH(L68,Table_Complete_CGNC_PCG!$I:$I,0)),"")="?","Retraitement requis - voir table","OK"))),"Erreur")) | L68: =LEFT(TEXT(A68,"0"),4) -> 0 | M68: =IF(A68="","",TRIM(A68&"")) | N68: =IF(M68="","",IF(AND(LEN(M68)>3,RIGHT(M68,1)="0"),LEFT(M68,LEN(M68)-1),M68)) | O68: =IF(N68="","",IF(AND(LEN(N68)>3,RIGHT(N68,1)="0"),LEFT(N68,LEN(N68)-1),N68)) | P68: =IF(O68="","",IF(AND(LEN(O68)>3,RIGHT(O68,1)="0"),LEFT(O68,LEN(O68)-1),O68)) | Q68: =IF(P68="","",IF(AND(LEN(P68)>3,RIGHT(P68,1)="0"),LEFT(P68,LEN(P68)-1),P68)) | R68: =IF(Q68="","",IF(AND(LEN(Q68)>3,RIGHT(Q68,1)="0"),LEFT(Q68,LEN(Q68)-1),Q68)) | S68: =IF(R68="","",IF(AND(LEN(R68)>3,RIGHT(R68,1)="0"),LEFT(R68,LEN(R68)-1),R68)) | T68: =IF(S68="","",IF(AND(LEN(S68)>3,RIGHT(S68,1)="0"),LEFT(S68,LEN(S68)-1),S68)) | U68: =IF(T68="","",IF(AND(LEN(T68)>3,RIGHT(T68,1)="0"),LEFT(T68,LEN(T68)-1),T68))
F69: =IF(A69="","",IFERROR(INDEX(Table_Complete_CGNC_PCG!$E:$E,MATCH(L69,Table_Complete_CGNC_PCG!$I:$I,0)),"? Non mappe")) | G69: =IF(A69="","",IFERROR(INDEX(Table_Complete_CGNC_PCG!$F:$F,MATCH(L69,Table_Complete_CGNC_PCG!$I:$I,0)),"Non trouve — ajouter dans la table")) | H69: =IF(OR(A69="",C69="",C69=0),"",ROUND(C69/$C$2,2)) | I69: =IF(OR(A69="",D69="",D69=0),"",ROUND(D69/$C$2,2)) | K69: =IF(A69="","",IFERROR(IF(F69="? Non mappe","Compte non trouve - mapper manuellement",IF(AND(ISNUMBER(SEARCH("516",L69)),D69>0),"CAISSE CREDITRICE - anomalie a corriger",IF(IFERROR(INDEX(Table_Complete_CGNC_PCG!$D:$D,MATCH(L69,Table_Complete_CGNC_PCG!$I:$I,0)),"")="?","Retraitement requis - voir table","OK"))),"Erreur")) | L69: =LEFT(TEXT(A69,"0"),4) -> 0 | M69: =IF(A69="","",TRIM(A69&"")) | N69: =IF(M69="","",IF(AND(LEN(M69)>3,RIGHT(M69,1)="0"),LEFT(M69,LEN(M69)-1),M69)) | O69: =IF(N69="","",IF(AND(LEN(N69)>3,RIGHT(N69,1)="0"),LEFT(N69,LEN(N69)-1),N69)) | P69: =IF(O69="","",IF(AND(LEN(O69)>3,RIGHT(O69,1)="0"),LEFT(O69,LEN(O69)-1),O69)) | Q69: =IF(P69="","",IF(AND(LEN(P69)>3,RIGHT(P69,1)="0"),LEFT(P69,LEN(P69)-1),P69)) | R69: =IF(Q69="","",IF(AND(LEN(Q69)>3,RIGHT(Q69,1)="0"),LEFT(Q69,LEN(Q69)-1),Q69)) | S69: =IF(R69="","",IF(AND(LEN(R69)>3,RIGHT(R69,1)="0"),LEFT(R69,LEN(R69)-1),R69)) | T69: =IF(S69="","",IF(AND(LEN(S69)>3,RIGHT(S69,1)="0"),LEFT(S69,LEN(S69)-1),S69)) | U69: =IF(T69="","",IF(AND(LEN(T69)>3,RIGHT(T69,1)="0"),LEFT(T69,LEN(T69)-1),T69))
F70: =IF(A70="","",IFERROR(INDEX(Table_Complete_CGNC_PCG!$E:$E,MATCH(L70,Table_Complete_CGNC_PCG!$I:$I,0)),"? Non mappe")) | G70: =IF(A70="","",IFERROR(INDEX(Table_Complete_CGNC_PCG!$F:$F,MATCH(L70,Table_Complete_CGNC_PCG!$I:$I,0)),"Non trouve — ajouter dans la table")) | H70: =IF(OR(A70="",C70="",C70=0),"",ROUND(C70/$C$2,2)) | I70: =IF(OR(A70="",D70="",D70=0),"",ROUND(D70/$C$2,2)) | K70: =IF(A70="","",IFERROR(IF(F70="? Non mappe","Compte non trouve - mapper manuellement",IF(AND(ISNUMBER(SEARCH("516",L70)),D70>0),"CAISSE CREDITRICE - anomalie a corriger",IF(IFERROR(INDEX(Table_Complete_CGNC_PCG!$D:$D,MATCH(L70,Table_Complete_CGNC_PCG!$I:$I,0)),"")="?","Retraitement requis - voir table","OK"))),"Erreur")) | L70: =LEFT(TEXT(A70,"0"),4) -> 0 | M70: =IF(A70="","",TRIM(A70&"")) | N70: =IF(M70="","",IF(AND(LEN(M70)>3,RIGHT(M70,1)="0"),LEFT(M70,LEN(M70)-1),M70)) | O70: =IF(N70="","",IF(AND(LEN(N70)>3,RIGHT(N70,1)="0"),LEFT(N70,LEN(N70)-1),N70)) | P70: =IF(O70="","",IF(AND(LEN(O70)>3,RIGHT(O70,1)="0"),LEFT(O70,LEN(O70)-1),O70)) | Q70: =IF(P70="","",IF(AND(LEN(P70)>3,RIGHT(P70,1)="0"),LEFT(P70,LEN(P70)-1),P70)) | R70: =IF(Q70="","",IF(AND(LEN(Q70)>3,RIGHT(Q70,1)="0"),LEFT(Q70,LEN(Q70)-1),Q70)) | S70: =IF(R70="","",IF(AND(LEN(R70)>3,RIGHT(R70,1)="0"),LEFT(R70,LEN(R70)-1),R70)) | T70: =IF(S70="","",IF(AND(LEN(S70)>3,RIGHT(S70,1)="0"),LEFT(S70,LEN(S70)-1),S70)) | U70: =IF(T70="","",IF(AND(LEN(T70)>3,RIGHT(T70,1)="0"),LEFT(T70,LEN(T70)-1),T70))
... F212: =IF(A212="","",IFERROR(INDEX(Table_Complete_CGNC_PCG!$E:$E,MATCH(L212,Table_Complete_CGNC_PCG!$I:$I,0)),"? Non mappe")) | G212: =IF(A212="","",IFERROR(INDEX(Table_Complete_CGNC_PCG!$F:$F,MATCH(L212,Table_Complete_CGNC_PCG!$I:$I,0)),"Non trouve — ajouter dans la table")) | H212: =IF(OR(A212="",C212="",C212=0),"",ROUND(C212/$C$2,2)) | I212: =IF(OR(A212="",D212="",D212=0),"",ROUND(D212/$C$2,2)) | K212: =IF(A212="","",IFERROR(IF(F212="? Non mappe","Compte non trouve - mapper manuellement",IF(AND(ISNUMBER(SEARCH("516",L212)),D212>0),"CAISSE CREDITRICE - anomalie a corriger",IF(IFERROR(INDEX(Table_Complete_CGNC_PCG!$D:$D,MATCH(L212,Table_Complete_CGNC_PCG!$I:$I,0)),"")="?","Retraitement requis - voir table","OK"))),"Erreur")) | L212: =LEFT(TEXT(A212,"0"),4) -> 0 | M212: =IF(A212="","",TRIM(A212&"")) | N212: =IF(M212="","",IF(AND(LEN(M212)>3,RIGHT(M212,1)="0"),LEFT(M212,LEN(M212)-1),M212)) | O212: =IF(N212="","",IF(AND(LEN(N212)>3,RIGHT(N212,1)="0"),LEFT(N212,LEN(N212)-1),N212)) | P212: =IF(O212="","",IF(AND(LEN(O212)>3,RIGHT(O212,1)="0"),LEFT(O212,LEN(O212)-1),O212)) | Q212: =IF(P212="","",IF(AND(LEN(P212)>3,RIGHT(P212,1)="0"),LEFT(P212,LEN(P212)-1),P212)) | R212: =IF(Q212="","",IF(AND(LEN(Q212)>3,RIGHT(Q212,1)="0"),LEFT(Q212,LEN(Q212)-1),Q212)) | S212: =IF(R212="","",IF(AND(LEN(R212)>3,RIGHT(R212,1)="0"),LEFT(R212,LEN(R212)-1),R212)) | T212: =IF(S212="","",IF(AND(LEN(S212)>3,RIGHT(S212,1)="0"),LEFT(S212,LEN(S212)-1),S212)) | U212: =IF(T212="","",IF(AND(LEN(T212)>3,RIGHT(T212,1)="0"),LEFT(T212,LEN(T212)-1),T212))
A213: TOTAUX | C213: =IFERROR(SUM(C5:C212),0) -> 2172985.3 | D213: =IFERROR(SUM(D5:D212),0) -> 2172985.3 | H213: =IFERROR(SUM(H5:H212),0) -> 201202.37 | I213: =IFERROR(SUM(I5:I212),0) -> 201202.34
A214: CONTRÔLE ÉQUILIBRE MAD : Total Débit = Total Crédit ? | C214: =IF(ABS(D213-C213)<0.01,"✓ Balance équilibrée","⚠ Déséquilibre : "&TEXT(ABS(C213-D213),"#,##0.00")&" MAD") -> ✓ Balance équilibrée | F214: CONTRÔLE ÉQUILIBRE EUR : | H214: =IF(ABS(H213-I213)<0.01,"✓ Balance équilibrée","⚠ Écart arrondi : "&TEXT(ABS(H213-I213),"#,##")&" €") -> ⚠ Écart arrondi : ,03 €
