Workbook

Sheet 📋 Notice
B1: NOTICE D'UTILISATION MATRICE FINANCEMENT RIAD MARRAKECH
B3: ► OBJECTIF → Cet outil aide l'expert-comptable et l'investisseur franco-marocain à arbitrer entre 3 options de financement pour l'acquisition d'un riad à usage touristique à Marrakech.
B5: ONGLETS
B6: ► Paramètres → Saisir toutes les données en JAUNE : prix du bien, apport, taux, durée, revenus estimés.
B7: ► Matrice Décision → Vision comparative des 3 options : bancaire, fonds propres, hybride. Indicateurs
B8: ► Plan 20 ans → Projection année par année du cash-flow, du capital restant dû et de la valeur du bien (option bancaire).
B9: ► Arbitrage → Modulez librement le % d'apport, la durée et le taux pour voir l'impact immédiat. Table de sensibilité incluse.
B11: HYPOTHÈSES DU CAS PRATIQUE
B12: ► Prix d'acquisition → 5 500 000 MAD (≈ 550 000 EUR) — riad 8 chambres, Médina Marrakech
B13: ► Travaux/rénovation → 800 000 MAD
B14: ► Taux crédit → 6%/an sur 20 ans (Banque Populaire Maroc, hors assurance)
B15: ► Apport minimal → 30% selon réglementation bancaire marocaine
... B25: ► AVERTISSEMENT → Ce modèle est à usage d'aide à la décision. Les projections financières sont des estimations basées sur les hypothèses saisies. Ces estimations n'ont pour but que d'ouvrir la reflexion. La décision finale ser aprise en consultant aussi l'expert-comptable marocain car c'est lui qui va proposer aussi son expertise terrain

Sheet Paramètres
B1: MATRICE D'AIDE À LA DÉCISION FINANCEMENT RIAD MARRAKECH
B4: 1. CARACTÉRISTIQUES DU BIEN
B5: Prix d'acquisition du Riad (MAD) | C5: 5500000
B6: Frais d'acquisition (notaire, enregistrement ~10%) | C6: =Paramètres!C5*0.1 -> 550000
B7: Budget travaux / rénovation (MAD) | C7: 150000
B8: Coût total projet (MAD) | C8: =C5+C6+C7 -> 6200000
B9: Taux de change EUR/MAD | C9: 10.8 | E9: Moyenne
B10: Coût total projet (EUR) | C10: =C8/C9 -> 574074.07
B12: 2. PARAMÈTRES FINANCEMENT BANCAIRE (Banque Marocaine)
B13: Apport personnel minimal (%) | C13: 0.3
B14: Apport personnel retenu (%) | C14: 0.5 | E14: Le client apport 50% du montant pour renforcer son dossier de prêt
B15: Apport personnel (MAD) | C15: =C14*Paramètres!C8 -> 3100000
B16: Montant emprunté (MAD) | C16: =Paramètres!C8-C15 -> 3100000
B17: Taux d'intérêt annuel | C17: 0.06
B18: Durée du prêt (années) | C18: 20
B19: Mensualité (MAD) | C19: =C16*(C17/12)/((1-(1+C17/12)^(-C18*12))) -> 22209.363
B20: Total remboursé (MAD) | C20: =C19*C18*12 -> 5330247.1
B21: Coût total du crédit (MAD) | C21: =C20-C16 -> 2230247.1
B23: 3. PARAMÈTRES FINANCEMENT PERSONNEL / PATRIMONIAL
B24: Capital propre disponible (MAD) | C24: 600000
B25: Rendement alternatif du capital (%/an) | C25: 0.045
B26: Montant autofinancé (MAD) | C26: =Paramètres!C8 -> 6200000
B27: Coût d'opportunité annuel (MAD) | C27: =C24*C25 -> 27000
B28: Coût d'opportunité total 20 ans (MAD) | C28: =C27*20 -> 540000
B30: 4. HYPOTHÈSES DE REVENUS & EXPLOITATION
B31: Prix nuit/chambre (MAD) | C31: 1200
B32: Nombre de chambres | C32: 8
B33: Taux d'occupation annuel | C33: 0.65
B34: Revenu brut annuel (MAD) | C34: =C31*C32*C33*365 -> 2277600
B35: Charges exploitation (% revenus) | C35: 0.5
B36: Revenu net annuel avant charges fin. (MAD) | C36: =C34*(1-C35) -> 1138800
B37: Taux de croissance annuel revenus | C37: 0.015
B38: Frais de gestion déléguée (% revenus) | C38: 0.15
B39: Revenu net après gestion (MAD) | C39: =C36*(1-C38) -> 967980
B40: Valeur de revente estimée (an 20, +2%/an) | C40: =Paramètres!C5*(1.02^20) -> 8172710.7
B43: LÉGENDE DES COULEURS
B44: Fond jaune - Texte bleu | C44: Input modifiable par l'utilisateur
B45: Fond blanc - Texte noir | C45: Formule calculée automatiquement
B46: Fond bleu clair - Texte noir | C46: Résultat intermédiaire clé

Sheet Matrice Décision
B1: 📊 MATRICE COMPARATIVE FINANCEMENT BANCAIRE vs PERSONNEL
B2: Les valeurs s'actualisent automatiquement selon les paramètres
B4: CRITÈRES D'ANALYSE | C4: FINANCEMENT BANCAIRE | D4: FONDS PROPRES
B5: A. STRUCTURE DE FINANCEMENT
B6: Coût total projet | C6: =Paramètres!C8 -> 6200000 | D6: =Paramètres!C8 -> 6200000
B7: Apport initial (MAD) | C7: =Paramètres!C15 -> 3100000 | D7: =Paramètres!C8 -> 6200000
B8: Apport initial (%) | C8: =Paramètres!C14 -> 0.5 | D8: 100%
B9: Montant financé en dette (MAD) | C9: =Paramètres!C16 -> 3100000 | D9: 0
B10: Mensualité (MAD) | C10: =Paramètres!C19 -> 22209.363 | D10: —
B12: B. ANALYSE DU COÛT FINANCIER
B13: Coût total du crédit (MAD) | C13: =Paramètres!C21 -> 2230247.1 | D13: 0
B14: Coût d'opportunité 20 ans (MAD) | C14: =Paramètres!C15*Paramètres!C25*20 -> 2790000 | D14: =Paramètres!C28 -> 540000
B15: Coût financier TOTAL (MAD) | C15: =Paramètres!C21+Paramètres!C15*Paramètres!C25*20 -> 5020247.1 | D15: =Paramètres!C28 -> 540000
B16: Taux de rendement annuel requis (%) | C16: =Paramètres!C17 -> 0.06 | D16: =Paramètres!C25 -> 0.045
B18: C. ANALYSE DE RENTABILITÉ (Cash-Flow & ROI)
B19: Revenu net annuel après gestion (MAD) | C19: =Paramètres!C39 -> 967980 | D19: =Paramètres!C39 -> 967980
B20: Charges financières annuelles (MAD) | C20: =Paramètres!C19*12 -> 266512.35 | D20: 0
B21: Cash-Flow net annuel (MAD) | C21: =Paramètres!C39-Paramètres!C19*12 -> 701467.65 | D21: =Paramètres!C39 -> 967980
B22: Cash-Flow net annuel (EUR) | C22: =(Paramètres!C39-Paramètres!C19*12)/Paramètres!C9 -> 64950.708 | D22: =Paramètres!C39/Paramètres!C9 -> 89627.778
B23: Rendement brut (sur coût total, %) | C23: =Paramètres!C36/Paramètres!C8 -> 0.18367742 | D23: =Paramètres!C36/Paramètres!C8 -> 0.18367742
B24: Rendement net sur fonds propres (ROE, %) | C24: =(Paramètres!C39-Paramètres!C19*12)/Paramètres!C15 -> 0.22627989 | D24: =Paramètres!C39/Paramètres!C8 -> 0.15612581
B25: Payback (années) | C25: =Paramètres!C15/MAX(1,Paramètres!C39-Paramètres!C19*12) -> 4.4193057 | D25: =Paramètres!C8/MAX(1,Paramètres!C39) -> 6.405091
B27: D. CRITÈRES QUALITATIFS & RISQUES
B28: Disponibilité du capital propre | C28: Capital conservé | D28: Capital immobilisé
B29: Effet de levier financier | C29: Interessant | D29: Aucun
B30: Risque de taux / refinancement | C30: Risque réel | D30: Aucun
B31: Souplesse de trésorerie | C31: Mensualités rigides | D31: Maximale
B32: Protection patrimoine personnel | C32: Capital libre | D32: Risque concentré
B33: Déductibilité intérêts (IS Maroc) | C33: Déductibles | D33: Non applicable
B36: Commentaires
B37: Le financement bancaire offre un ROE plus élevé (22,63 % contre 15,61 %) grâce à l’effet de levier et permet de conserver du capital disponible. Les fonds propres génèrent toutefois un cash-flow annuel supérieur (+266 512 MAD).

Sheet ESTIMATION du Plan 20 ans
B1: PLAN DE FINANCEMENT SUR 20 ANS - OPTION BANCAIRE
B3: Année | C3: Revenu brut (MAD) | D3: Annuité crédit (MAD) | E3: Cash-Flow net (MAD) | F3: Capital restant dû (MAD) | G3: Cumul CF net (MAD) | H3: Valeur estimée riad (MAD)
B4: 1 | C4: =Paramètres!C36 -> 1138800 | D4: =Paramètres!C19*12 -> 266512.35 | E4: =C4-D4 -> 872287.65 | F4: =Paramètres!C16*(1+Paramètres!C17/12)^12-Paramètres!C19*(((1+Paramètres!C17/12)^12-1)/(Paramètres!C17/12)) -> 3017236.2 | G4: =E4 -> 872287.65 | H4: =Paramètres!C5*(1.02^1) -> 5610000
B5: 2 | C5: =C4*(1+Paramètres!C37) -> 1155882 | D5: =Paramètres!C19*12 -> 266512.35 | E5: =C5-D5 -> 889369.65 | F5: =F4*(1+Paramètres!C17/12)^12-Paramètres!C19*(((1+Paramètres!C17/12)^12-1)/(Paramètres!C17/12)) -> 2929367.8 | G5: =G4+E5 -> 1761657.3 | H5: =Paramètres!C5*(1.02^2) -> 5722200
B6: 3 | C6: =C5*(1+Paramètres!C37) -> 1173220.2 | D6: =Paramètres!C19*12 -> 266512.35 | E6: =C6-D6 -> 906707.88 | F6: =F5*(1+Paramètres!C17/12)^12-Paramètres!C19*(((1+Paramètres!C17/12)^12-1)/(Paramètres!C17/12)) -> 2836079.8 | G6: =G5+E6 -> 2668365.2 | H6: =Paramètres!C5*(1.02^3) -> 5836644
B7: 4 | C7: =C6*(1+Paramètres!C37) -> 1190818.5 | D7: =Paramètres!C19*12 -> 266512.35 | E7: =C7-D7 -> 924306.18 | F7: =F6*(1+Paramètres!C17/12)^12-Paramètres!C19*(((1+Paramètres!C17/12)^12-1)/(Paramètres!C17/12)) -> 2737038 | G7: =G6+E7 -> 3592671.3 | H7: =Paramètres!C5*(1.02^4) -> 5953376.9
B8: 5 | C8: =C7*(1+Paramètres!C37) -> 1208680.8 | D8: =Paramètres!C19*12 -> 266512.35 | E8: =C8-D8 -> 942168.46 | F8: =F7*(1+Paramètres!C17/12)^12-Paramètres!C19*(((1+Paramètres!C17/12)^12-1)/(Paramètres!C17/12)) -> 2631887.6 | G8: =G7+E8 -> 4534839.8 | H8: =Paramètres!C5*(1.02^5) -> 6072444.4
B9: 6 | C9: =C8*(1+Paramètres!C37) -> 1226811 | D9: =Paramètres!C19*12 -> 266512.35 | E9: =C9-D9 -> 960298.67 | F9: =F8*(1+Paramètres!C17/12)^12-Paramètres!C19*(((1+Paramètres!C17/12)^12-1)/(Paramètres!C17/12)) -> 2520251.6 | G9: =G8+E9 -> 5495138.5 | H9: =Paramètres!C5*(1.02^6) -> 6193893.3
B10: 7 | C10: =C9*(1+Paramètres!C37) -> 1245213.2 | D10: =Paramètres!C19*12 -> 266512.35 | E10: =C10-D10 -> 978700.84 | F10: =F9*(1+Paramètres!C17/12)^12-Paramètres!C19*(((1+Paramètres!C17/12)^12-1)/(Paramètres!C17/12)) -> 2401730.3 | G10: =G9+E10 -> 6473839.3 | H10: =Paramètres!C5*(1.02^7) -> 6317771.2
B11: 8 | C11: =C10*(1+Paramètres!C37) -> 1263891.4 | D11: =Paramètres!C19*12 -> 266512.35 | E11: =C11-D11 -> 997379.03 | F11: =F10*(1+Paramètres!C17/12)^12-Paramètres!C19*(((1+Paramètres!C17/12)^12-1)/(Paramètres!C17/12)) -> 2275898.8 | G11: =G10+E11 -> 7471218.3 | H11: =Paramètres!C5*(1.02^8) -> 6444126.6
B12: 9 | C12: =C11*(1+Paramètres!C37) -> 1282849.8 | D12: =Paramètres!C19*12 -> 266512.35 | E12: =C12-D12 -> 1016337.4 | F12: =F11*(1+Paramètres!C17/12)^12-Paramètres!C19*(((1+Paramètres!C17/12)^12-1)/(Paramètres!C17/12)) -> 2142306.2 | G12: =G11+E12 -> 8487555.7 | H12: =Paramètres!C5*(1.02^9) -> 6573009.1
B13: 10 | C13: =C12*(1+Paramètres!C37) -> 1302092.5 | D13: =Paramètres!C19*12 -> 266512.35 | E13: =C13-D13 -> 1035580.2 | F13: =F12*(1+Paramètres!C17/12)^12-Paramètres!C19*(((1+Paramètres!C17/12)^12-1)/(Paramètres!C17/12)) -> 2000474 | G13: =G12+E13 -> 9523135.9 | H13: =Paramètres!C5*(1.02^10) -> 6704469.3
B14: 11 | C14: =C13*(1+Paramètres!C37) -> 1321623.9 | D14: =Paramètres!C19*12 -> 266512.35 | E14: =C14-D14 -> 1055111.5 | F14: =F13*(1+Paramètres!C17/12)^12-Paramètres!C19*(((1+Paramètres!C17/12)^12-1)/(Paramètres!C17/12)) -> 1849893.9 | G14: =G13+E14 -> 10578247 | H14: =Paramètres!C5*(1.02^11) -> 6838558.7
B15: 12 | C15: =C14*(1+Paramètres!C37) -> 1341448.2 | D15: =Paramètres!C19*12 -> 266512.35 | E15: =C15-D15 -> 1074935.9 | F15: =F14*(1+Paramètres!C17/12)^12-Paramètres!C19*(((1+Paramètres!C17/12)^12-1)/(Paramètres!C17/12)) -> 1690026.3 | G15: =G14+E15 -> 11653183 | H15: =Paramètres!C5*(1.02^12) -> 6975329.9
B16: 13 | C16: =C15*(1+Paramètres!C37) -> 1361570 | D16: =Paramètres!C19*12 -> 266512.35 | E16: =C16-D16 -> 1095057.6 | F16: =F15*(1+Paramètres!C17/12)^12-Paramètres!C19*(((1+Paramètres!C17/12)^12-1)/(Paramètres!C17/12)) -> 1520298.5 | G16: =G15+E16 -> 12748241 | H16: =Paramètres!C5*(1.02^13) -> 7114836.5
B17: 14 | C17: =C16*(1+Paramètres!C37) -> 1381993.5 | D17: =Paramètres!C19*12 -> 266512.35 | E17: =C17-D17 -> 1115481.2 | F17: =F16*(1+Paramètres!C17/12)^12-Paramètres!C19*(((1+Paramètres!C17/12)^12-1)/(Paramètres!C17/12)) -> 1340102.2 | G17: =G16+E17 -> 13863722 | H17: =Paramètres!C5*(1.02^14) -> 7257133.2
B18: 15 | C18: =C17*(1+Paramètres!C37) -> 1402723.4 | D18: =Paramètres!C19*12 -> 266512.35 | E18: =C18-D18 -> 1136211.1 | F18: =F17*(1+Paramètres!C17/12)^12-Paramètres!C19*(((1+Paramètres!C17/12)^12-1)/(Paramètres!C17/12)) -> 1148791.7 | G18: =G17+E18 -> 14999933 | H18: =Paramètres!C5*(1.02^15) -> 7402275.9
B19: 16 | C19: =C18*(1+Paramètres!C37) -> 1423764.3 | D19: =Paramètres!C19*12 -> 266512.35 | E19: =C19-D19 -> 1157251.9 | F19: =F18*(1+Paramètres!C17/12)^12-Paramètres!C19*(((1+Paramètres!C17/12)^12-1)/(Paramètres!C17/12)) -> 945681.73 | G19: =G18+E19 -> 16157185 | H19: =Paramètres!C5*(1.02^16) -> 7550321.4
B20: 17 | C20: =C19*(1+Paramètres!C37) -> 1445120.7 | D20: =Paramètres!C19*12 -> 266512.35 | E20: =C20-D20 -> 1178608.4 | F20: =F19*(1+Paramètres!C17/12)^12-Paramètres!C19*(((1+Paramètres!C17/12)^12-1)/(Paramètres!C17/12)) -> 730044.33 | G20: =G19+E20 -> 17335794 | H20: =Paramètres!C5*(1.02^17) -> 7701327.8
B21: 18 | C21: =C20*(1+Paramètres!C37) -> 1466797.6 | D21: =Paramètres!C19*12 -> 266512.35 | E21: =C21-D21 -> 1200285.2 | F21: =F20*(1+Paramètres!C17/12)^12-Paramètres!C19*(((1+Paramètres!C17/12)^12-1)/(Paramètres!C17/12)) -> 501106.88 | G21: =G20+E21 -> 18536079 | H21: =Paramètres!C5*(1.02^18) -> 7855354.4
B22: 19 | C22: =C21*(1+Paramètres!C37) -> 1488799.5 | D22: =Paramètres!C19*12 -> 266512.35 | E22: =C22-D22 -> 1222287.2 | F22: =F21*(1+Paramètres!C17/12)^12-Paramètres!C19*(((1+Paramètres!C17/12)^12-1)/(Paramètres!C17/12)) -> 258049.08 | G22: =G21+E22 -> 19758366 | H22: =Paramètres!C5*(1.02^19) -> 8012461.4
B23: 20 | C23: =C22*(1+Paramètres!C37) -> 1511131.5 | D23: =Paramètres!C19*12 -> 266512.35 | E23: =C23-D23 -> 1244619.2 | F23: =F22*(1+Paramètres!C17/12)^12-Paramètres!C19*(((1+Paramètres!C17/12)^12-1)/(Paramètres!C17/12)) -> 3.4924597e-09 | G23: =G22+E23 -> 21002985 | H23: =Paramètres!C5*(1.02^20) -> 8172710.7
B25: TOTAL | C25: =SUM(C4:C23) -> 26333232 | D25: =SUM(D4:D23) -> 5330247.1 | E25: =SUM(E4:E23) -> 21002985
