Workbook

Sheet 📊 Synthèse & Scoring
A1: TABLEAU DE BORD DES DUE DILIGENCES
A3: INFORMATIONS PROJET
A4: Nom du bien : | B4: RIAD MÉMOIRE EXPERTISE COMPTABLE
A5: Adresse : | B5: 75 AVENUE DE LA SOUTENANCE
A6: Ville : | B6: MARRAKECH
A7: Prix demandé (MAD) : | B7: 5 500 000 000 MAD (environ 550 000€)
A8: Date d'évaluation : | B8: 45920
A11: SCORING AUTOMATISÉ
A12: Catégorie | B12: Validé ✓ | C12: Non validé ✗ | D12: N/A | E12: Points obtenus | F12: Note /100 | G12: Points max
A13: Due Diligences Juridiques & Foncières | B13: =COUNTIF('Diligences Juridique & Foncier'!C:C,"✓ Validé") -> 18 | C13: =COUNTIF('Diligences Juridique & Foncier'!C:C,"✗ Non validé") -> 0 | D13: =COUNTIF('Diligences Juridique & Foncier'!C:C,"⊗ Non applicable") -> 3 | E13: =SUMIF('Diligences Juridique & Foncier'!C:C,"✓ Validé",'Diligences Juridique & Foncier'!E:E) -> 72.77 | F13: =IF(SUM('Diligences Juridique & Foncier'!E3:E23)=0,0,ROUND(E13/SUM('Diligences Juridique & Foncier'!E3:E23)*100,2)) -> 88.5 | G13: =SUM('Diligences Juridique & Foncier'!E3:E23) -> 82.23
A14: Due Diligences Techniques | B14: =COUNTIF('Diligences Technique'!C:C,"✓ Validé") -> 21 | C14: =COUNTIF('Diligences Technique'!C:C,"✗ Non validé") -> 2 | D14: =COUNTIF('Diligences Technique'!C:C,"⊗ Non applicable") -> 0 | E14: =SUMIF('Diligences Technique'!C:C,"✓ Validé",'Diligences Technique'!E:E) -> 84.77 | F14: =IF(SUM('Diligences Technique'!E3:E25)=0,0,ROUND(E14/SUM('Diligences Technique'!E3:E25)*100,2)) -> 91.17 | G14: =SUM('Diligences Technique'!E3:E25) -> 92.98
A15: Due Diligences Économiques | B15: =COUNTIF('Diligences Économique'!C:C,"✓ Validé") -> 14 | C15: =COUNTIF('Diligences Économique'!C:C,"✗ Non validé") -> 0 | D15: =COUNTIF('Diligences Économique'!C:C,"⊗ Non applicable") -> 0 | E15: =SUMIF('Diligences Économique'!C:C,"✓ Validé",'Diligences Économique'!E:E) -> 59.38 | F15: =IF(SUM('Diligences Économique'!E3:E16)=0,0,ROUND(E15/SUM('Diligences Économique'!E3:E16)*100,2)) -> 100 | G15: =SUM('Diligences Économique'!E3:E16) -> 59.38
A17: SCORE GLOBAL DU PROJET | E17: =SUM(E13:E15) -> 216.92 | F17: =ROUND(AVERAGE(F13:F15),2) -> 93.22 | G17: =SUM(G13:G15) -> 234.59
A19: RECOMMANDATION AUTOMATIQUE
A20: =IF(F17>=80,"✅ PROJET SÉCURISÉ - Risques maîtrisés. Acquisition recommandée.",IF(F17>=60,"⚠️ PROJET ACCEPTABLE SOUS RÉSERVES - Négocier régularisations avant signature.",IF(F17>=40,"⚠️ RISQUES SIGNIFICATIFS - Régularisations majeures requises. Ajuster le prix.","❌ PROJET À RISQUE - Risques bloquants majeurs. Acquisition déconseillée."))) -> ✅ PROJET SÉCURISÉ - Risques maîtrisés. Acquisition recommandée.

Sheet Diligences Juridique & Foncier
A1: DUE DILIGENCES JURIDIQUE & FONCIER
A2: N° | B2: Question de contrôle | C2: Statut | D2: Niveau de risque | E2: Points | F2: Commentaires / Actions
A3: 1 | B3: Le bien dispose-t-il d'un titre foncier immatriculé à la Conservation Foncière ? | C3: ✓ Validé | D3: ● Bloquant | E3: 4.98 | F3: Oui le bien dispose d'un titre foncier
A4: 2 | B4: Le numéro de titre foncier est-il clairement identifié et consultable ? | C4: ✓ Validé | D4: ● Bloquant | E4: 4.98 | F4: oui
A5: 3 | B5: La superficie inscrite correspond-elle à la superficie réelle ? | C5: ✓ Validé | D5: ● Bloquant | E5: 5 | F5: Pas d'extention réalisée depuis
A6: 4 | B6: Le plan cadastral reflète-t-il fidèlement les limites physiques ? | C6: ✓ Validé | D6: ■ Négociable | E6: 2.99 | F6: oui
A7: 5 | B7: L'immatriculation est-elle récente (<10 ans) ou ancienne ? | C7: ✓ Validé | D7: ▲ Vigilance | E7: 1.49 | F7: oui immatriculation 5 ans
A8: 6 | B8: Existe-t-il des créances inscrites ou sûretés réelles ? | C8: ✓ Validé | D8: ● Bloquant | E8: 4.98 | F8: non RAS
A9: 7 | B9: Le bien fait-il l'objet d'une saisie ou séquestre ? | C9: ✓ Validé | D9: ● Bloquant | E9: 4.98 | F9: non RAS
A10: 8 | B10: Le vendeur a-t-il des dettes fiscales/sociales risquant inscription ? | C10: ✓ Validé | D10: ▲ Vigilance | E10: 4.48 | F10: non pas de risque
A11: 9 | B11: Les taxes locales (habitation, services communaux) sont-elles à jour ? | C11: ✓ Validé | D11: ■ Négociable | E11: 2.49 | F11: oui à jour
A12: 10 | B12: Le bien est-il en pleine propriété ou en indivision familiale ? | C12: ✓ Validé | D12: ● Bloquant | E12: 4.98 | F12: en pleine propriété
A13: 11 | B13: Tous les co-indivisaires ont-ils donné leur accord formel ? | C13: ⊗ Non applicable | D13: ● Bloquant | E13: 4.98 | F13: pas d'indivision N/A
A14: 12 | B14: Le bien fait-il partie d'une copropriété avec règlement ? | C14: ⊗ Non applicable | D14: ▲ Vigilance | E14: 1.99 | F14: non c'est un Riad : individuelle N/A
... A23: 21 | B23: Le bien est-il en zone classée (médina UNESCO) ? | C23: ✓ Validé | D23: ▲ Vigilance | E23: 2.49 | F23: oui dans la Médina
A26: Commentairess
A27: Le riad est racheté à un ancien exploitant, l'intervention d'un notaire sécurise l'opération sur le plan juridique. Le titre foncier est immatriculé, identifié et consultable, la superficie est conforme, l'immatriculation date de 5 ans. Bien en pleine propriété, aucune indivision, aucune créance ni saisie, taxes à jour. Servitudes validées, accès garanti, Roukhsa valide.

Sheet Diligences Technique
A1: DUE DILIGENCES TECHNIQUE
A2: N° | B2: Question de contrôle | C2: Statut | D2: Niveau de risque | E2: Points | F2: Commentaires / Actions
A3: 1 | B3: L'état des fondations présente-t-il des signes de tassement/fissuration ? | C3: ✓ Validé | D3: ● Bloquant | E3: 5 | F3: non
A4: 2 | B4: Les murs porteurs sont-ils en bon état sans désordres structurels ? | C4: ✓ Validé | D4: ● Bloquant | E4: 5 | F4: oui
A5: 3 | B5: La charpente et couverture sont-elles saines ? | C5: ✓ Validé | D5: ■ Négociable | E5: 4.79 | F5: oui
A6: 4 | B6: L'étanchéité des terrasses/toitures est-elle conforme ? | C6: ✓ Validé | D6: ■ Négociable | E6: 4.11 | F6: oui
A7: 5 | B7: Les planchers et dalles sont-ils stables et aux normes ? | C7: ✓ Validé | D7: ■ Négociable | E7: 4.79 | F7: oui
A8: 6 | B8: Les menuiseries extérieures sont-elles en bon état et sécurisées ? | C8: ✓ Validé | D8: ▲ Vigilance | E8: 2.74 | F8: oui
A9: 7 | B9: L'installation électrique est-elle aux normes avec tableau conforme ? | C9: ✓ Validé | D9: ● Bloquant | E9: 5 | F9: oui
A10: 8 | B10: La plomberie/assainissement fonctionnent-ils sans fuites ? | C10: ✗ Non validé | D10: ■ Négociable | E10: 4.79 | F10: il y a des travaux à faire
A11: 9 | B11: Le bien est-il raccordé aux réseaux eau potable/assainissement ? | C11: ✓ Validé | D11: ● Bloquant | E11: 5 | F11: oui
A12: 10 | B12: Les équipements climatisation/chauffage sont-ils fonctionnels ? | C12: ✓ Validé | D12: ▲ Vigilance | E12: 3.42 | F12: La clim est à refaire
A13: 11 | B13: Le système d'eau chaude sanitaire est-il adapté à l'exploitation ? | C13: ✓ Validé | D13: ■ Négociable | E13: 4.11 | F13: oui
A14: 12 | B14: Le chauffage piscine (si existante) est-il fonctionnel et économe ? | C14: ✓ Validé | D14: ▲ Vigilance | E14: 2.74 | F14: oui
... A25: 23 | B25: Le bien dispose-t-il des équipements de confort attendus (wifi, coffres) ? | C25: ✓ Validé | D25: ▲ Vigilance | E25: 2.05 | F25: oui
A28: Commentairess
A29: Le riad est repris après une exploitation étrangère, la structure est saine, aucun travail lourd sur le gros œuvre n'est à prévoir. Installations réglementaires conformes (électricité, réseaux, incendie, sanitaire). Deux points à négocier dans le prix : la plomberie est défaillante (à chiffrer avant signature) et l'accessibilité PMR n'est pas conforme (impact possible sur certaines subventions). Une remise à niveau commerciale est nécessaire avant ouverture : climatisation à refaire, décoration et mobilier à remplacer. Ces postes sont anticipés et provisionnés dans le projet.

Sheet Diligences Économique
A1: 💹 ÉCONOMIQUE
A2: N° | B2: Question de contrôle | C2: Statut | D2: Niveau de risque | E2: Points | F2: Commentaires / Actions
A3: 1 | B3: La dynamique touristique de la zone est-elle en croissance ? | C3: ✓ Validé | D3: ▲ Vigilance | E3: 3.82 | F3: Oui la médina de Marrakech est très attractive
A4: 2 | B4: Le profil clientèle du quartier correspond-il au positionnement visé ? | C4: ✓ Validé | D4: ▲ Vigilance | E4: 3.82 | F4: Clientèle très variée oui
A5: 3 | B5: La saisonnalité impacte-t-elle fortement le taux d'occupation ? | C5: ✓ Validé | D5: ■ Négociable | E5: 4.58 | F5: Marrakech est très attractif toute l'année avec pic au printemps et en été
A6: 4 | B6: Les tarifs de la concurrence sont-ils cohérents avec le projet ? | C6: ✓ Validé | D6: ■ Négociable | E6: 4.58 | F6: oui
A7: 5 | B7: Le quartier bénéficie-t-il d'infrastructures touristiques développées ? | C7: ✓ Validé | D7: ▲ Vigilance | E7: 3.05 | F7: oui Marrakech est bien developper tout en gardant son authenticité
A8: 6 | B8: Le bien dispose-t-il d'une licence d'exploitation touristique valide ? | C8: ✓ Validé | D8: ● Bloquant | E8: 5 | F8: Oui
A9: 7 | B9: Le classement actuel (étoiles) est-il conforme au projet ? | C9: ✓ Validé | D9: ■ Négociable | E9: 4.58 | F9: 3 étoiles
A10: 8 | B10: Les obligations déclaratives locales sont-elles identifiées ? | C10: ✓ Validé | D10: ▲ Vigilance | E10: 2.29 | F10: oui
A11: 9 | B11: Existe-t-il des restrictions d'exploitation liées au zonage ? | C11: ✓ Validé | D11: ■ Négociable | E11: 4.58 | F11: non
A12: 10 | B12: Le bien peut-il être commercialisé sur Booking/Airbnb ? | C12: ✓ Validé | D12: ▲ Vigilance | E12: 3.82 | F12: oui
A13: 11 | B13: La capacité d'accueil (chambres) est-elle optimale ? | C13: ✓ Validé | D13: ■ Négociable | E13: 4.58 | F13: oui
A14: 12 | B14: Le taux d'occupation prévisible est-il supérieur à 60% ? | C14: ✓ Validé | D14: ■ Négociable | E14: 4 | F14: oui
... A16: 14 | B16: Les coûts travaux/mise en conformité sont-ils compatibles ? | C16: ✓ Validé | D16: ■ Négociable | E16: 5.34 | F16: Oui prévu
A20: Commentairess
A21: Le bien est repris à un exploitant étranger qui a rentabilisé son investissement en moins de 10 ans. Licence d'exploitation valide, classement 3 étoiles, commercialisation Booking/Airbnb possible, aucune restriction de zonage. Marrakech médina : attractivité toute l'année, clientèle variée, tarifs cohérents avec le marché. Taux d'occupation prévisible > 60%
