Workbook

Sheet Infos
B2: ÉTUDE FINANCIÈRE PRÉVISIONNELLE SUR 3 ANS EN MAD RIAD DU MÉMOIRE - Médina de Marrakech STRUCTURE : HOLDING + EXPLOITATION
B7: STRUCTURE JURIDIQUE RETENUE
B8: HOLDING MAROCAINE (SCI/SARL de gestion)
B9: Détient les murs du riad (actif immobilier)
B10: Emprunte 3 100 000 MAD auprès de la banque
B11: Loue le riad à la société d'exploitation
B12: Loyer = mensualité emprunt × 110%
B14: SARL D'EXPLOITATION (Monte Cristo / Riad Al Baraka)
B15: Exploite le riad (hébergement, restauration, spa…)
B16: Verse le loyer à la Holding chaque mois
B17: Encaisse le CA et paie les charges d'exploitation
B18: Résultat net soumis à l'IS Maroc (exo 5 ans possible)
B20: CHIFFRES CLÉS DU MONTAGE
B21: Coût total projet (Holding) | C21: 6,200,000 MAD
B22: Apport Holding (50%) | C22: 3,100,000 MAD
B23: Emprunt Holding 6% / 20 ans | C23: 3,100,000 MAD
B24: Mensualité emprunt | C24: 22 209 MAD/mois
B25: Loyer Holding --> Exploit. | C25: 24 430 MAD/mois (annuité ×110%)
B26: CA héberg. An1 (yield mgmt) | C26: 3 898 720 MAD
B27: Taux d'occ. moyen An1 | C27: 0.792
B29: ONGLETS
B30: ① Hypothèses Communes
B31: ② Holding CR Mensuel 3 ans
B32: ③ Exploitation CR Mensuel 3 ans
B33: ④ Exploitation Budget Trésorerie
B34: ⑤ Consolidé SIG & Rentabilité

Sheet ① Hypothèses
A1: HYPOTHÈSES COMMUNES RIAD DU MEMOIRE (MAD) HOLDING + EXPLOITATION
A3: BIEN IMMOBILIER (Holding)
A4: Prix d'acquisition du riad (MAD) | B4: 5500000 | C4: MAD | D4: Riad 8 ch. Médina Marrakech
A5: Frais d'acquisition (notaire + droits d'enregistrement etc.) | B5: 550000 | C5: MAD
A6: Travaux / rénovation | B6: 150000 | C6: MAD
A7: Coût total projet | B7: =B4+B5+B6 -> 6200000 | C7: MAD
A8: Taux de change EUR/MAD | B8: 10.8 | C8: EUR/MAD
A9: Coût total projet (EUR) | B9: =B7/B8 -> 574074.07 | C9: EUR
A11: FINANCEMENT HOLDING (emprunt bancaire marocain)
A12: Apport Holding (%) | B12: 0.5 | C12: % | D12: 50% minimum recommandé Maroc
A13: Apport Holding (MAD) | B13: =B7*B12 -> 3100000 | C13: MAD
A14: Montant emprunté (MAD) | B14: =B7-B13 -> 3100000 | C14: MAD
A15: Taux d'intérêt annuel | B15: 0.06 | C15: % | D15: Banque Populaire
A16: Durée du prêt (années) | B16: 20 | C16: ans
A17: Mensualité emprunt Holding | B17: =ROUND(B14*(B15/12)/(1-(1+B15/12)^(-B16*12)),0) -> 22209 | C17: MAD/mois
A18: Annuité emprunt Holding | B18: =B17*12 -> 266508 | C18: MAD/an
A19: Total remboursé sur 20 ans | B19: =B17*B16*12 -> 5330160 | C19: MAD
A20: Coût total du crédit | B20: =B19-B14 -> 2230160 | C20: MAD
A22: LOYER INTER-SOCIÉTÉS (Holding -> Exploitation)
A23: Marge de sécurité sur mensualité (%) | B23: 0.25 | C23: % | D23: Surplus couvre frais gestion Holding + sécurité
A24: Loyer mensuel HT (Exploit. → Holding) | B24: =ROUND(B17*(1+B23),0) -> 27761 | C24: MAD/mois
A25: Loyer annuel HT | B25: =B24*12 -> 333132 | C25: MAD/an
A26: Surplus annuel Holding (après annuité) | B26: =B25-B18 -> 66624 | C26: MAD/an
A28: YIELD MANAGEMENT & SAISONNALITÉ MARRAKECH (source : Outil 15)
A29: Nombre de chambres | B29: 8 | C29: chambres
A30: Prix Haute Saison (≥80% TO) | B30: 1500 | C30: MAD/nuit | D30: Benchmark riads Marrakech
A31: Prix Moyenne Saison (51-79%) | B31: 1200 | C31: MAD/nuit
A32: Prix Basse Saison (<=50%) | B32: 900 | C32: MAD/nuit
A34: TABLEAU SAISONNALITÉ Taux d'occupation & Prix Yield (Année 1)
A35: Mois | B35: TO Année 1 | C35: Saison | D35: Prix Yield (MAD/nuit)
A36: Janvier | B36: 0.5 | C36: =IF(B36>=0.8,"Haute Saison",IF(B36>=0.5,"Moyenne Saison","Basse Saison")) -> Moyenne Saison | D36: =IF(B36>=0.8,B30,IF(B36>=0.51,B31,B32)) -> 900
A37: Février | B37: 0.5 | C37: =IF(B37>=0.8,"Haute Saison",IF(B37>=0.5,"Moyenne Saison","Basse Saison")) -> Moyenne Saison | D37: =IF(B37>=0.8,B30,IF(B37>=0.51,B31,B32)) -> 900
A38: Mars | B38: 0.55 | C38: =IF(B38>=0.8,"Haute Saison",IF(B38>=0.5,"Moyenne Saison","Basse Saison")) -> Moyenne Saison | D38: =IF(B38>=0.8,B30,IF(B38>=0.51,B31,B32)) -> 1200
A39: Avril | B39: 0.65 | C39: =IF(B39>=0.8,"Haute Saison",IF(B39>=0.5,"Moyenne Saison","Basse Saison")) -> Moyenne Saison | D39: =IF(B39>=0.8,B30,IF(B39>=0.51,B31,B32)) -> 1200
A40: Mai | B40: 0.7 | C40: =IF(B40>=0.8,"Haute Saison",IF(B40>=0.5,"Moyenne Saison","Basse Saison")) -> Moyenne Saison | D40: =IF(B40>=0.8,B30,IF(B40>=0.51,B31,B32)) -> 1200
A41: Juin | B41: 0.85 | C41: =IF(B41>=0.8,"Haute Saison",IF(B41>=0.5,"Moyenne Saison","Basse Saison")) -> Haute Saison | D41: =IF(B41>=0.8,B30,IF(B41>=0.51,B31,B32)) -> 1500
A42: Juillet | B42: 1 | C42: =IF(B42>=0.8,"Haute Saison",IF(B42>=0.5,"Moyenne Saison","Basse Saison")) -> Haute Saison | D42: =IF(B42>=0.8,B30,IF(B42>=0.51,B31,B32)) -> 1500
A43: Août | B43: 1 | C43: =IF(B43>=0.8,"Haute Saison",IF(B43>=0.5,"Moyenne Saison","Basse Saison")) -> Haute Saison | D43: =IF(B43>=0.8,B30,IF(B43>=0.51,B31,B32)) -> 1500
A44: Septembre | B44: 1 | C44: =IF(B44>=0.8,"Haute Saison",IF(B44>=0.5,"Moyenne Saison","Basse Saison")) -> Haute Saison | D44: =IF(B44>=0.8,B30,IF(B44>=0.51,B31,B32)) -> 1500
A45: Octobre | B45: 0.8 | C45: =IF(B45>=0.8,"Haute Saison",IF(B45>=0.5,"Moyenne Saison","Basse Saison")) -> Haute Saison | D45: =IF(B45>=0.8,B30,IF(B45>=0.51,B31,B32)) -> 1500
A46: Novembre | B46: 0.6 | C46: =IF(B46>=0.8,"Haute Saison",IF(B46>=0.5,"Moyenne Saison","Basse Saison")) -> Moyenne Saison | D46: =IF(B46>=0.8,B30,IF(B46>=0.51,B31,B32)) -> 1200
A47: Décembre | B47: 0.65 | C47: =IF(B47>=0.8,"Haute Saison",IF(B47>=0.5,"Moyenne Saison","Basse Saison")) -> Moyenne Saison | D47: =IF(B47>=0.8,B30,IF(B47>=0.51,B31,B32)) -> 1200
A48: TO annuel moyen An1 | B48: =AVERAGE(B36:B47) -> 0.73333333
A50: CROISSANCES ANNUELLES
A51: Croissance TO Année 2 (vs An1) | B51: 0.01 | C51: %
A52: Croissance TO Année 3 (vs An1) | B52: 0.02 | C52: %
A53: Hausse des prix Yield An2 | B53: 0.01 | C53: %
A54: Hausse des prix Yield An3 | B54: 0.02 | C54: %
A55: Inflation charges An2 & An3 | B55: 0.02 | C55: %
A56: Augmentation salaires An2 & An3 | B56: 0.02 | C56: %
A58: REVENUS ANNEXES (Exploitation)
A59: Restauration (% CA hébergement) | B59: 0.1 | C59: % | D59: Petits-déj + dîners table d'hôtes
A60: Spa & Hammam (% CA hébergement) | B60: 0.1 | C60: %
A61: Activités & excursions (% CA héb.) | B61: 0.15 | C61: %
A63: CHARGES EXPLOITATION (SARL)
A64: Commissions OTA % CA hébergement | B64: 0.16 | C64: % | D64: Airbnb ~16%
A65: Coût marchandises restauration (%) | B65: 0.4 | C65: % | D65: % CA restauration
A66: Assurances annuelles (MAD) | B66: 45000 | C66: MAD/an
A67: Eau, électricité, gaz (MAD/mois) | B67: 15000 | C67: MAD/mois
A68: Entretien & maintenance (MAD/an) | B68: 70000 | C68: MAD/an
A69: Marketing & communication (MAD/an) | B69: 50000 | C69: MAD/an
A70: Fournitures & linge (MAD/an) | B70: 45000 | C70: MAD/an
A71: Honoraires divers (MAD/an) | B71: 65000 | C71: MAD/an
A72: Autres charges externes (MAD/an) | B72: 100000 | C72: MAD/an
A73: Impôts & taxes locaux (MAD/an) | B73: 120000 | C73: MAD/an
A75: PERSONNEL EXPLOITATION
A76: Gérant/Directeur salaire mensuel brut | B76: 8000 | C76: MAD/mois | D76: Rémunération du directeur
A77: Charges sociales dirigeant (%) | B77: 0.27 | C77: %
A78: Nombre d'employés | B78: 4 | C78: personnes | D78: Réception, ménage, cuisine, service
A79: Salaire moyen mensuel brut employé | B79: 5500 | C79: MAD/mois
A80: Charges sociales employés (%) | B80: 0.27 | C80: %
A82: INVESTISSEMENTS EXPLOITATION (SARL)
A83: Mobilier & décoration | B83: 150000 | C83: MAD
A84: Matériel cuisine | B84: 100000 | C84: MAD
A85: Informatique & PMS | B85: 25000 | C85: MAD
A86: Frais d'établissement | B86: 1800 | C86: MAD
A87: Droits d'entrée / licence | B87: 0 | C87: MAD
A88: Total investissements SARL | B88: 0 | C88: MAD
A89: Apport SARL (MAD) | B89: 100000 | C89: MAD | D89: Capital libéré
A90: Trésorerie initiale SARL | B90: 50000 | C90: MAD | D90: Compte courant associé personne physique
A92: AMORTISSEMENTS (SARL)
A93: Durée amort. mobilier (ans) | B93: 5 | C93: ans
A94: Durée amort. matériel cuisine (ans) | B94: 5 | C94: ans
A95: Durée amort. informatique (ans) | B95: 3 | C95: ans
A96: Durée amort. incorporels (ans) | B96: 5 | C96: ans
A97: Amortissement annuel SARL | B97: =ROUND(B83/B93+B84/B94+B85/B95+(B86+B87)/B96,0) -> 58693 | C97: MAD/an
A99: AMORTISSEMENTS (HOLDING)
A100: Durée amort. gros œuvre / murs (ans) | B100: 20 | C100: ans
A101: Base amortissable Holding | B101: =B4+B6+B5 -> 6200000 | C101: MAD
A102: Amortissement annuel Holding | B102: =ROUND(B101/B100,0) -> 310000 | C102: MAD/an

Sheet ② Holding CR
A1: COMPTE DE RÉSULTAT PRÉVISIONNEL HOLDING RIAD DU MÉMOIRE (MAD HT)
A2: La Holding détient les murs. Elle perçoit le loyer de la SARL d'exploitation et rembourse l'emprunt bancaire. Son résultat est la différence loyer − annuité − amortissement.
C3: ANNÉE 1 2026 | Q3: ANNÉE 2 2027 | AE3: ANNÉE 3 2028
A4: LIBELLÉS | C4: Jan | D4: Fév | E4: Mar | F4: Avr | G4: Mai | H4: Juin | I4: Juil | J4: Août | K4: Sep | L4: Oct | M4: Nov | N4: Déc | O4: TOTAL | Q4: Jan | R4: Fév | S4: Mar | T4: Avr | U4: Mai | V4: Juin | W4: Juil | X4: Août | Y4: Sep | Z4: Oct | AA4: Nov | AB4: Déc | AC4: TOTAL | AE4: Jan | AF4: Fév | AG4: Mar | AH4: Avr | AI4: Mai | AJ4: Juin | AK4: Juil | AL4: Août | AM4: Sep | AN4: Oct | AO4: Nov | AP4: Déc | AQ4: TOTAL
A5: PRODUITS (loyers perçus de la SARL d'exploitation)
A6: Loyer perçu de la SARL d'exploitation | C6: ='① Hypothèses'!B24 -> 27761 | D6: ='① Hypothèses'!B24 -> 27761 | E6: ='① Hypothèses'!B24 -> 27761 | F6: ='① Hypothèses'!B24 -> 27761 | G6: ='① Hypothèses'!B24 -> 27761 | H6: ='① Hypothèses'!B24 -> 27761 | I6: ='① Hypothèses'!B24 -> 27761 | J6: ='① Hypothèses'!B24 -> 27761 | K6: ='① Hypothèses'!B24 -> 27761 | L6: ='① Hypothèses'!B24 -> 27761 | M6: ='① Hypothèses'!B24 -> 27761 | N6: ='① Hypothèses'!B24 -> 27761 | O6: =SUM(C6,D6,E6,F6,G6,H6,I6,J6,K6,L6,M6,N6) -> 333132 | Q6: ='① Hypothèses'!B24 -> 27761 | R6: ='① Hypothèses'!B24 -> 27761 | S6: ='① Hypothèses'!B24 -> 27761 | T6: ='① Hypothèses'!B24 -> 27761 | U6: ='① Hypothèses'!B24 -> 27761 | V6: ='① Hypothèses'!B24 -> 27761 | W6: ='① Hypothèses'!B24 -> 27761 | X6: ='① Hypothèses'!B24 -> 27761 | Y6: ='① Hypothèses'!B24 -> 27761 | Z6: ='① Hypothèses'!B24 -> 27761 | AA6: ='① Hypothèses'!B24 -> 27761 | AB6: ='① Hypothèses'!B24 -> 27761 | AC6: =SUM(Q6,R6,S6,T6,U6,V6,W6,X6,Y6,Z6,AA6,AB6) -> 333132 | AE6: ='① Hypothèses'!B24 -> 27761 | AF6: ='① Hypothèses'!B24 -> 27761 | AG6: ='① Hypothèses'!B24 -> 27761 | AH6: ='① Hypothèses'!B24 -> 27761 | AI6: ='① Hypothèses'!B24 -> 27761 | AJ6: ='① Hypothèses'!B24 -> 27761 | AK6: ='① Hypothèses'!B24 -> 27761 | AL6: ='① Hypothèses'!B24 -> 27761 | AM6: ='① Hypothèses'!B24 -> 27761 | AN6: ='① Hypothèses'!B24 -> 27761 | AO6: ='① Hypothèses'!B24 -> 27761 | AP6: ='① Hypothèses'!B24 -> 27761 | AQ6: =SUM(AE6,AF6,AG6,AH6,AI6,AJ6,AK6,AL6,AM6,AN6,AO6,AP6) -> 333132
A7: TOTAL PRODUITS HOLDING | C7: =C6 -> 27761 | D7: =D6 -> 27761 | E7: =E6 -> 27761 | F7: =F6 -> 27761 | G7: =G6 -> 27761 | H7: =H6 -> 27761 | I7: =I6 -> 27761 | J7: =J6 -> 27761 | ... N7: =N6 -> 27761 | O7: =SUM(C7,D7,E7,F7,G7,H7,I7,J7,K7,L7,M7,N7) -> 333132 | Q7: =Q6 -> 27761 | R7: =R6 -> 27761 | S7: =S6 -> 27761 | T7: =T6 -> 27761 | U7: =U6 -> 27761 | V7: =V6 -> 27761 | W7: =W6 -> 27761 | X7: =X6 -> 27761 | ... AB7: =AB6 -> 27761 | AC7: =SUM(Q7,R7,S7,T7,U7,V7,W7,X7,Y7,Z7,AA7,AB7) -> 333132 | AE7: =AE6 -> 27761 | AF7: =AF6 -> 27761 | AG7: =AG6 -> 27761 | AH7: =AH6 -> 27761 | AI7: =AI6 -> 27761 | AJ7: =AJ6 -> 27761 | AK7: =AK6 -> 27761 | AL7: =AL6 -> 27761 | ... AP7: =AP6 -> 27761 | AQ7: =SUM(AE7,AF7,AG7,AH7,AI7,AJ7,AK7,AL7,AM7,AN7,AO7,AP7) -> 333132
A8: CHARGES (remboursement emprunt + amortissements)
A9: Mensualité emprunt (capital + intérêts) | C9: ='① Hypothèses'!B17 -> 22209 | D9: ='① Hypothèses'!B17 -> 22209 | E9: ='① Hypothèses'!B17 -> 22209 | F9: ='① Hypothèses'!B17 -> 22209 | G9: ='① Hypothèses'!B17 -> 22209 | H9: ='① Hypothèses'!B17 -> 22209 | I9: ='① Hypothèses'!B17 -> 22209 | J9: ='① Hypothèses'!B17 -> 22209 | K9: ='① Hypothèses'!B17 -> 22209 | L9: ='① Hypothèses'!B17 -> 22209 | M9: ='① Hypothèses'!B17 -> 22209 | N9: ='① Hypothèses'!B17 -> 22209 | O9: =SUM(C9,D9,E9,F9,G9,H9,I9,J9,K9,L9,M9,N9) -> 266508 | Q9: ='① Hypothèses'!B17 -> 22209 | R9: ='① Hypothèses'!B17 -> 22209 | S9: ='① Hypothèses'!B17 -> 22209 | T9: ='① Hypothèses'!B17 -> 22209 | U9: ='① Hypothèses'!B17 -> 22209 | V9: ='① Hypothèses'!B17 -> 22209 | W9: ='① Hypothèses'!B17 -> 22209 | X9: ='① Hypothèses'!B17 -> 22209 | Y9: ='① Hypothèses'!B17 -> 22209 | Z9: ='① Hypothèses'!B17 -> 22209 | AA9: ='① Hypothèses'!B17 -> 22209 | AB9: ='① Hypothèses'!B17 -> 22209 | AC9: =SUM(Q9,R9,S9,T9,U9,V9,W9,X9,Y9,Z9,AA9,AB9) -> 266508 | AE9: ='① Hypothèses'!B17 -> 22209 | AF9: ='① Hypothèses'!B17 -> 22209 | AG9: ='① Hypothèses'!B17 -> 22209 | AH9: ='① Hypothèses'!B17 -> 22209 | AI9: ='① Hypothèses'!B17 -> 22209 | AJ9: ='① Hypothèses'!B17 -> 22209 | AK9: ='① Hypothèses'!B17 -> 22209 | AL9: ='① Hypothèses'!B17 -> 22209 | AM9: ='① Hypothèses'!B17 -> 22209 | AN9: ='① Hypothèses'!B17 -> 22209 | AO9: ='① Hypothèses'!B17 -> 22209 | AP9: ='① Hypothèses'!B17 -> 22209 | AQ9: =SUM(AE9,AF9,AG9,AH9,AI9,AJ9,AK9,AL9,AM9,AN9,AO9,AP9) -> 266508
A10: Frais de gestion Holding (assur., admin.) | C10: 3500 | D10: 3500 | E10: 3500 | F10: 3500 | G10: 3500 | H10: 3500 | I10: 3500 | J10: 3500 | K10: 3500 | L10: 3500 | M10: 3500 | N10: 3500 | O10: =SUM(C10,D10,E10,F10,G10,H10,I10,J10,K10,L10,M10,N10) -> 42000 | Q10: =3500*1.02 -> 3570 | R10: =3500*1.02 -> 3570 | S10: =3500*1.02 -> 3570 | T10: =3500*1.02 -> 3570 | U10: =3500*1.02 -> 3570 | V10: =3500*1.02 -> 3570 | W10: =3500*1.02 -> 3570 | X10: =3500*1.02 -> 3570 | ... AB10: =3500*1.02 -> 3570 | AC10: =SUM(Q10,R10,S10,T10,U10,V10,W10,X10,Y10,Z10,AA10,AB10) -> 42840 | AE10: =3500*1.04 -> 3640 | AF10: =3500*1.04 -> 3640 | AG10: =3500*1.04 -> 3640 | AH10: =3500*1.04 -> 3640 | AI10: =3500*1.04 -> 3640 | AJ10: =3500*1.04 -> 3640 | AK10: =3500*1.04 -> 3640 | AL10: =3500*1.04 -> 3640 | ... AP10: =3500*1.04 -> 3640 | AQ10: =SUM(AE10,AF10,AG10,AH10,AI10,AJ10,AK10,AL10,AM10,AN10,AO10,AP10) -> 43680
A11: Dotation aux amortissements (murs, gros œuvre) | C11: =ROUND('① Hypothèses'!B102/12,0) -> 25833 | D11: =ROUND('① Hypothèses'!B102/12,0) -> 25833 | E11: =ROUND('① Hypothèses'!B102/12,0) -> 25833 | F11: =ROUND('① Hypothèses'!B102/12,0) -> 25833 | G11: =ROUND('① Hypothèses'!B102/12,0) -> 25833 | H11: =ROUND('① Hypothèses'!B102/12,0) -> 25833 | I11: =ROUND('① Hypothèses'!B102/12,0) -> 25833 | J11: =ROUND('① Hypothèses'!B102/12,0) -> 25833 | K11: =ROUND('① Hypothèses'!B102/12,0) -> 25833 | L11: =ROUND('① Hypothèses'!B102/12,0) -> 25833 | M11: =ROUND('① Hypothèses'!B102/12,0) -> 25833 | N11: =ROUND('① Hypothèses'!B102/12,0) -> 25833 | O11: =SUM(C11,D11,E11,F11,G11,H11,I11,J11,K11,L11,M11,N11) -> 309996 | Q11: =ROUND('① Hypothèses'!B102/12,0) -> 25833 | R11: =ROUND('① Hypothèses'!B102/12,0) -> 25833 | S11: =ROUND('① Hypothèses'!B102/12,0) -> 25833 | T11: =ROUND('① Hypothèses'!B102/12,0) -> 25833 | U11: =ROUND('① Hypothèses'!B102/12,0) -> 25833 | V11: =ROUND('① Hypothèses'!B102/12,0) -> 25833 | W11: =ROUND('① Hypothèses'!B102/12,0) -> 25833 | X11: =ROUND('① Hypothèses'!B102/12,0) -> 25833 | Y11: =ROUND('① Hypothèses'!B102/12,0) -> 25833 | Z11: =ROUND('① Hypothèses'!B102/12,0) -> 25833 | AA11: =ROUND('① Hypothèses'!B102/12,0) -> 25833 | AB11: =ROUND('① Hypothèses'!B102/12,0) -> 25833 | AC11: =SUM(Q11,R11,S11,T11,U11,V11,W11,X11,Y11,Z11,AA11,AB11) -> 309996 | AE11: =ROUND('① Hypothèses'!B102/12,0) -> 25833 | AF11: =ROUND('① Hypothèses'!B102/12,0) -> 25833 | AG11: =ROUND('① Hypothèses'!B102/12,0) -> 25833 | AH11: =ROUND('① Hypothèses'!B102/12,0) -> 25833 | AI11: =ROUND('① Hypothèses'!B102/12,0) -> 25833 | AJ11: =ROUND('① Hypothèses'!B102/12,0) -> 25833 | AK11: =ROUND('① Hypothèses'!B102/12,0) -> 25833 | AL11: =ROUND('① Hypothèses'!B102/12,0) -> 25833 | AM11: =ROUND('① Hypothèses'!B102/12,0) -> 25833 | AN11: =ROUND('① Hypothèses'!B102/12,0) -> 25833 | AO11: =ROUND('① Hypothèses'!B102/12,0) -> 25833 | AP11: =ROUND('① Hypothèses'!B102/12,0) -> 25833 | AQ11: =SUM(AE11,AF11,AG11,AH11,AI11,AJ11,AK11,AL11,AM11,AN11,AO11,AP11) -> 309996
A12: TOTAL CHARGES HOLDING | C12: =C9+C10+C11 -> 51542 | D12: =D9+D10+D11 -> 51542 | E12: =E9+E10+E11 -> 51542 | F12: =F9+F10+F11 -> 51542 | G12: =G9+G10+G11 -> 51542 | H12: =H9+H10+H11 -> 51542 | I12: =I9+I10+I11 -> 51542 | J12: =J9+J10+J11 -> 51542 | ... N12: =N9+N10+N11 -> 51542 | O12: =SUM(C12,D12,E12,F12,G12,H12,I12,J12,K12,L12,M12,N12) -> 618504 | Q12: =Q9+Q10+Q11 -> 51612 | R12: =R9+R10+R11 -> 51612 | S12: =S9+S10+S11 -> 51612 | T12: =T9+T10+T11 -> 51612 | U12: =U9+U10+U11 -> 51612 | V12: =V9+V10+V11 -> 51612 | W12: =W9+W10+W11 -> 51612 | X12: =X9+X10+X11 -> 51612 | ... AB12: =AB9+AB10+AB11 -> 51612 | AC12: =SUM(Q12,R12,S12,T12,U12,V12,W12,X12,Y12,Z12,AA12,AB12) -> 619344 | AE12: =AE9+AE10+AE11 -> 51682 | AF12: =AF9+AF10+AF11 -> 51682 | AG12: =AG9+AG10+AG11 -> 51682 | AH12: =AH9+AH10+AH11 -> 51682 | AI12: =AI9+AI10+AI11 -> 51682 | AJ12: =AJ9+AJ10+AJ11 -> 51682 | AK12: =AK9+AK10+AK11 -> 51682 | AL12: =AL9+AL10+AL11 -> 51682 | ... AP12: =AP9+AP10+AP11 -> 51682 | AQ12: =SUM(AE12,AF12,AG12,AH12,AI12,AJ12,AK12,AL12,AM12,AN12,AO12,AP12) -> 620184
A13: RÉSULTATS
A14: Surplus trésorerie mensuel (loyer - mensualité) | C14: =C6-C9-C10 -> 2052 | D14: =D6-D9-D10 -> 2052 | E14: =E6-E9-E10 -> 2052 | F14: =F6-F9-F10 -> 2052 | G14: =G6-G9-G10 -> 2052 | H14: =H6-H9-H10 -> 2052 | I14: =I6-I9-I10 -> 2052 | J14: =J6-J9-J10 -> 2052 | ... N14: =N6-N9-N10 -> 2052 | O14: =SUM(C14,D14,E14,F14,G14,H14,I14,J14,K14,L14,M14,N14) -> 24624 | Q14: =Q6-Q9-Q10 -> 1982 | R14: =R6-R9-R10 -> 1982 | S14: =S6-S9-S10 -> 1982 | T14: =T6-T9-T10 -> 1982 | U14: =U6-U9-U10 -> 1982 | V14: =V6-V9-V10 -> 1982 | W14: =W6-W9-W10 -> 1982 | X14: =X6-X9-X10 -> 1982 | ... AB14: =AB6-AB9-AB10 -> 1982 | AC14: =SUM(Q14,R14,S14,T14,U14,V14,W14,X14,Y14,Z14,AA14,AB14) -> 23784 | AE14: =AE6-AE9-AE10 -> 1912 | AF14: =AF6-AF9-AF10 -> 1912 | AG14: =AG6-AG9-AG10 -> 1912 | AH14: =AH6-AH9-AH10 -> 1912 | AI14: =AI6-AI9-AI10 -> 1912 | AJ14: =AJ6-AJ9-AJ10 -> 1912 | AK14: =AK6-AK9-AK10 -> 1912 | AL14: =AL6-AL9-AL10 -> 1912 | ... AP14: =AP6-AP9-AP10 -> 1912 | AQ14: =SUM(AE14,AF14,AG14,AH14,AI14,AJ14,AK14,AL14,AM14,AN14,AO14,AP14) -> 22944
A15: RÉSULTAT NET HOLDING (avant IS) | C15: =C7-C12 -> -23781 | D15: =D7-D12 -> -23781 | E15: =E7-E12 -> -23781 | F15: =F7-F12 -> -23781 | G15: =G7-G12 -> -23781 | H15: =H7-H12 -> -23781 | I15: =I7-I12 -> -23781 | J15: =J7-J12 -> -23781 | ... N15: =N7-N12 -> -23781 | O15: =SUM(C15,D15,E15,F15,G15,H15,I15,J15,K15,L15,M15,N15) -> -285372 | Q15: =Q7-Q12 -> -23851 | R15: =R7-R12 -> -23851 | S15: =S7-S12 -> -23851 | T15: =T7-T12 -> -23851 | U15: =U7-U12 -> -23851 | V15: =V7-V12 -> -23851 | W15: =W7-W12 -> -23851 | X15: =X7-X12 -> -23851 | ... AB15: =AB7-AB12 -> -23851 | AC15: =SUM(Q15,R15,S15,T15,U15,V15,W15,X15,Y15,Z15,AA15,AB15) -> -286212 | AE15: =AE7-AE12 -> -23921 | AF15: =AF7-AF12 -> -23921 | AG15: =AG7-AG12 -> -23921 | AH15: =AH7-AH12 -> -23921 | AI15: =AI7-AI12 -> -23921 | AJ15: =AJ7-AJ12 -> -23921 | AK15: =AK7-AK12 -> -23921 | AL15: =AL7-AL12 -> -23921 | ... AP15: =AP7-AP12 -> -23921 | AQ15: =SUM(AE15,AF15,AG15,AH15,AI15,AJ15,AK15,AL15,AM15,AN15,AO15,AP15) -> -287052

Sheet ③ Exploitation CR
A1: COMPTE DE RÉSULTAT PRÉVISIONNEL EXPLOITATION (SARL) RIAD DU MEMOIRE (MAD HT)
C3: ANNÉE 1 2026 | Q3: ANNÉE 2 2027 | AE3: ANNÉE 3 2028
A4: LIBELLÉS | C4: Jan | D4: Fév | E4: Mar | F4: Avr | G4: Mai | H4: Juin | I4: Juil | J4: Août | K4: Sep | L4: Oct | M4: Nov | N4: Déc | O4: TOTAL | Q4: Jan | R4: Fév | S4: Mar | T4: Avr | U4: Mai | V4: Juin | W4: Juil | X4: Août | Y4: Sep | Z4: Oct | AA4: Nov | AB4: Déc | AC4: TOTAL | AE4: Jan | AF4: Fév | AG4: Mar | AH4: Avr | AI4: Mai | AJ4: Juin | AK4: Juil | AL4: Août | AM4: Sep | AN4: Oct | AO4: Nov | AP4: Déc | AQ4: TOTAL
A5: PRODUITS D'EXPLOITATION
A6: CA Hébergement (yield management) | C6: =ROUND('① Hypothèses'!B29*IF('① Hypothèses'!B36>=0.8,'① Hypothèses'!B30,IF('① Hypothèses'!B36>=0.51,'① Hypothèses'!B31,'① Hypothèses'!B32))*'① Hypothèses'!B36*31,0) -> 111600 | D6: =ROUND('① Hypothèses'!B29*IF('① Hypothèses'!B37>=0.8,'① Hypothèses'!B30,IF('① Hypothèses'!B37>=0.51,'① Hypothèses'!B31,'① Hypothèses'!B32))*'① Hypothèses'!B37*28,0) -> 100800 | E6: =ROUND('① Hypothèses'!B29*IF('① Hypothèses'!B38>=0.8,'① Hypothèses'!B30,IF('① Hypothèses'!B38>=0.51,'① Hypothèses'!B31,'① Hypothèses'!B32))*'① Hypothèses'!B38*31,0) -> 163680 | F6: =ROUND('① Hypothèses'!B29*IF('① Hypothèses'!B39>=0.8,'① Hypothèses'!B30,IF('① Hypothèses'!B39>=0.51,'① Hypothèses'!B31,'① Hypothèses'!B32))*'① Hypothèses'!B39*30,0) -> 187200 | G6: =ROUND('① Hypothèses'!B29*IF('① Hypothèses'!B40>=0.8,'① Hypothèses'!B30,IF('① Hypothèses'!B40>=0.51,'① Hypothèses'!B31,'① Hypothèses'!B32))*'① Hypothèses'!B40*31,0) -> 208320 | H6: =ROUND('① Hypothèses'!B29*IF('① Hypothèses'!B41>=0.8,'① Hypothèses'!B30,IF('① Hypothèses'!B41>=0.51,'① Hypothèses'!B31,'① Hypothèses'!B32))*'① Hypothèses'!B41*30,0) -> 306000 | I6: =ROUND('① Hypothèses'!B29*IF('① Hypothèses'!B42>=0.8,'① Hypothèses'!B30,IF('① Hypothèses'!B42>=0.51,'① Hypothèses'!B31,'① Hypothèses'!B32))*'① Hypothèses'!B42*31,0) -> 372000 | J6: =ROUND('① Hypothèses'!B29*IF('① Hypothèses'!B43>=0.8,'① Hypothèses'!B30,IF('① Hypothèses'!B43>=0.51,'① Hypothèses'!B31,'① Hypothèses'!B32))*'① Hypothèses'!B43*31,0) -> 372000 | K6: =ROUND('① Hypothèses'!B29*IF('① Hypothèses'!B44>=0.8,'① Hypothèses'!B30,IF('① Hypothèses'!B44>=0.51,'① Hypothèses'!B31,'① Hypothèses'!B32))*'① Hypothèses'!B44*30,0) -> 360000 | L6: =ROUND('① Hypothèses'!B29*IF('① Hypothèses'!B45>=0.8,'① Hypothèses'!B30,IF('① Hypothèses'!B45>=0.51,'① Hypothèses'!B31,'① Hypothèses'!B32))*'① Hypothèses'!B45*31,0) -> 297600 | M6: =ROUND('① Hypothèses'!B29*IF('① Hypothèses'!B46>=0.8,'① Hypothèses'!B30,IF('① Hypothèses'!B46>=0.51,'① Hypothèses'!B31,'① Hypothèses'!B32))*'① Hypothèses'!B46*30,0) -> 172800 | N6: =ROUND('① Hypothèses'!B29*IF('① Hypothèses'!B47>=0.8,'① Hypothèses'!B30,IF('① Hypothèses'!B47>=0.51,'① Hypothèses'!B31,'① Hypothèses'!B32))*'① Hypothèses'!B47*31,0) -> 193440 | O6: =SUM(C6,D6,E6,F6,G6,H6,I6,J6,K6,L6,M6,N6) -> 2845440 | Q6: =ROUND('① Hypothèses'!B29*IF(MIN(1,'① Hypothèses'!B36+'① Hypothèses'!B51)>=0.8,'① Hypothèses'!B30*(1+'① Hypothèses'!B53),IF(MIN(1,'① Hypothèses'!B36+'① Hypothèses'!B51)>=0.51,'① Hypothèses'!B31*(1+'① Hypothèses'!B53),'① Hypothèses'!B32*(1+'① Hypothèses'!B53)))*MIN(1,'① Hypothèses'!B36+'① Hypothèses'!B51)*31,0) -> 153294 | R6: =ROUND('① Hypothèses'!B29*IF(MIN(1,'① Hypothèses'!B37+'① Hypothèses'!B51)>=0.8,'① Hypothèses'!B30*(1+'① Hypothèses'!B53),IF(MIN(1,'① Hypothèses'!B37+'① Hypothèses'!B51)>=0.51,'① Hypothèses'!B31*(1+'① Hypothèses'!B53),'① Hypothèses'!B32*(1+'① Hypothèses'!B53)))*MIN(1,'① Hypothèses'!B37+'① Hypothèses'!B51)*28,0) -> 138459 | S6: =ROUND('① Hypothèses'!B29*IF(MIN(1,'① Hypothèses'!B38+'① Hypothèses'!B51)>=0.8,'① Hypothèses'!B30*(1+'① Hypothèses'!B53),IF(MIN(1,'① Hypothèses'!B38+'① Hypothèses'!B51)>=0.51,'① Hypothèses'!B31*(1+'① Hypothèses'!B53),'① Hypothèses'!B32*(1+'① Hypothèses'!B53)))*MIN(1,'① Hypothèses'!B38+'① Hypothèses'!B51)*31,0) -> 168323 | T6: =ROUND('① Hypothèses'!B29*IF(MIN(1,'① Hypothèses'!B39+'① Hypothèses'!B51)>=0.8,'① Hypothèses'!B30*(1+'① Hypothèses'!B53),IF(MIN(1,'① Hypothèses'!B39+'① Hypothèses'!B51)>=0.51,'① Hypothèses'!B31*(1+'① Hypothèses'!B53),'① Hypothèses'!B32*(1+'① Hypothèses'!B53)))*MIN(1,'① Hypothèses'!B39+'① Hypothèses'!B51)*30,0) -> 191981 | U6: =ROUND('① Hypothèses'!B29*IF(MIN(1,'① Hypothèses'!B40+'① Hypothèses'!B51)>=0.8,'① Hypothèses'!B30*(1+'① Hypothèses'!B53),IF(MIN(1,'① Hypothèses'!B40+'① Hypothèses'!B51)>=0.51,'① Hypothèses'!B31*(1+'① Hypothèses'!B53),'① Hypothèses'!B32*(1+'① Hypothèses'!B53)))*MIN(1,'① Hypothèses'!B40+'① Hypothèses'!B51)*31,0) -> 213409 | V6: =ROUND('① Hypothèses'!B29*IF(MIN(1,'① Hypothèses'!B41+'① Hypothèses'!B51)>=0.8,'① Hypothèses'!B30*(1+'① Hypothèses'!B53),IF(MIN(1,'① Hypothèses'!B41+'① Hypothèses'!B51)>=0.51,'① Hypothèses'!B31*(1+'① Hypothèses'!B53),'① Hypothèses'!B32*(1+'① Hypothèses'!B53)))*MIN(1,'① Hypothèses'!B41+'① Hypothèses'!B51)*30,0) -> 312696 | W6: =ROUND('① Hypothèses'!B29*IF(MIN(1,'① Hypothèses'!B42+'① Hypothèses'!B51)>=0.8,'① Hypothèses'!B30*(1+'① Hypothèses'!B53),IF(MIN(1,'① Hypothèses'!B42+'① Hypothèses'!B51)>=0.51,'① Hypothèses'!B31*(1+'① Hypothèses'!B53),'① Hypothèses'!B32*(1+'① Hypothèses'!B53)))*MIN(1,'① Hypothèses'!B42+'① Hypothèses'!B51)*31,0) -> 375720 | X6: =ROUND('① Hypothèses'!B29*IF(MIN(1,'① Hypothèses'!B43+'① Hypothèses'!B51)>=0.8,'① Hypothèses'!B30*(1+'① Hypothèses'!B53),IF(MIN(1,'① Hypothèses'!B43+'① Hypothèses'!B51)>=0.51,'① Hypothèses'!B31*(1+'① Hypothèses'!B53),'① Hypothèses'!B32*(1+'① Hypothèses'!B53)))*MIN(1,'① Hypothèses'!B43+'① Hypothèses'!B51)*31,0) -> 375720 | Y6: =ROUND('① Hypothèses'!B29*IF(MIN(1,'① Hypothèses'!B44+'① Hypothèses'!B51)>=0.8,'① Hypothèses'!B30*(1+'① Hypothèses'!B53),IF(MIN(1,'① Hypothèses'!B44+'① Hypothèses'!B51)>=0.51,'① Hypothèses'!B31*(1+'① Hypothèses'!B53),'① Hypothèses'!B32*(1+'① Hypothèses'!B53)))*MIN(1,'① Hypothèses'!B44+'① Hypothèses'!B51)*30,0) -> 363600 | Z6: =ROUND('① Hypothèses'!B29*IF(MIN(1,'① Hypothèses'!B45+'① Hypothèses'!B51)>=0.8,'① Hypothèses'!B30*(1+'① Hypothèses'!B53),IF(MIN(1,'① Hypothèses'!B45+'① Hypothèses'!B51)>=0.51,'① Hypothèses'!B31*(1+'① Hypothèses'!B53),'① Hypothèses'!B32*(1+'① Hypothèses'!B53)))*MIN(1,'① Hypothèses'!B45+'① Hypothèses'!B51)*31,0) -> 304333 | AA6: =ROUND('① Hypothèses'!B29*IF(MIN(1,'① Hypothèses'!B46+'① Hypothèses'!B51)>=0.8,'① Hypothèses'!B30*(1+'① Hypothèses'!B53),IF(MIN(1,'① Hypothèses'!B46+'① Hypothèses'!B51)>=0.51,'① Hypothèses'!B31*(1+'① Hypothèses'!B53),'① Hypothèses'!B32*(1+'① Hypothèses'!B53)))*MIN(1,'① Hypothèses'!B46+'① Hypothèses'!B51)*30,0) -> 177437 | AB6: =ROUND('① Hypothèses'!B29*IF(MIN(1,'① Hypothèses'!B47+'① Hypothèses'!B51)>=0.8,'① Hypothèses'!B30*(1+'① Hypothèses'!B53),IF(MIN(1,'① Hypothèses'!B47+'① Hypothèses'!B51)>=0.51,'① Hypothèses'!B31*(1+'① Hypothèses'!B53),'① Hypothèses'!B32*(1+'① Hypothèses'!B53)))*MIN(1,'① Hypothèses'!B47+'① Hypothèses'!B51)*31,0) -> 198380 | AC6: =SUM(Q6,R6,S6,T6,U6,V6,W6,X6,Y6,Z6,AA6,AB6) -> 2973352 | AE6: =ROUND('① Hypothèses'!B29*IF(MIN(1,'① Hypothèses'!B36+'① Hypothèses'!B52)>=0.8,'① Hypothèses'!B30*(1+'① Hypothèses'!B53)*(1+'① Hypothèses'!B54),IF(MIN(1,'① Hypothèses'!B36+'① Hypothèses'!B52)>=0.51,'① Hypothèses'!B31*(1+'① Hypothèses'!B53)*(1+'① Hypothèses'!B54),'① Hypothèses'!B32*(1+'① Hypothèses'!B53)*(1+'① Hypothèses'!B54)))*MIN(1,'① Hypothèses'!B36+'① Hypothèses'!B52)*31,0) -> 159426 | AF6: =ROUND('① Hypothèses'!B29*IF(MIN(1,'① Hypothèses'!B37+'① Hypothèses'!B52)>=0.8,'① Hypothèses'!B30*(1+'① Hypothèses'!B53)*(1+'① Hypothèses'!B54),IF(MIN(1,'① Hypothèses'!B37+'① Hypothèses'!B52)>=0.51,'① Hypothèses'!B31*(1+'① Hypothèses'!B53)*(1+'① Hypothèses'!B54),'① Hypothèses'!B32*(1+'① Hypothèses'!B53)*(1+'① Hypothèses'!B54)))*MIN(1,'① Hypothèses'!B37+'① Hypothèses'!B52)*28,0) -> 143997 | AG6: =ROUND('① Hypothèses'!B29*IF(MIN(1,'① Hypothèses'!B38+'① Hypothèses'!B52)>=0.8,'① Hypothèses'!B30*(1+'① Hypothèses'!B53)*(1+'① Hypothèses'!B54),IF(MIN(1,'① Hypothèses'!B38+'① Hypothèses'!B52)>=0.51,'① Hypothèses'!B31*(1+'① Hypothèses'!B53)*(1+'① Hypothèses'!B54),'① Hypothèses'!B32*(1+'① Hypothèses'!B53)*(1+'① Hypothèses'!B54)))*MIN(1,'① Hypothèses'!B38+'① Hypothèses'!B52)*31,0) -> 174755 | AH6: =ROUND('① Hypothèses'!B29*IF(MIN(1,'① Hypothèses'!B39+'① Hypothèses'!B52)>=0.8,'① Hypothèses'!B30*(1+'① Hypothèses'!B53)*(1+'① Hypothèses'!B54),IF(MIN(1,'① Hypothèses'!B39+'① Hypothèses'!B52)>=0.51,'① Hypothèses'!B31*(1+'① Hypothèses'!B53)*(1+'① Hypothèses'!B54),'① Hypothèses'!B32*(1+'① Hypothèses'!B53)*(1+'① Hypothèses'!B54)))*MIN(1,'① Hypothèses'!B39+'① Hypothèses'!B52)*30,0) -> 198787 | AI6: =ROUND('① Hypothèses'!B29*IF(MIN(1,'① Hypothèses'!B40+'① Hypothèses'!B52)>=0.8,'① Hypothèses'!B30*(1+'① Hypothèses'!B53)*(1+'① Hypothèses'!B54),IF(MIN(1,'① Hypothèses'!B40+'① Hypothèses'!B52)>=0.51,'① Hypothèses'!B31*(1+'① Hypothèses'!B53)*(1+'① Hypothèses'!B54),'① Hypothèses'!B32*(1+'① Hypothèses'!B53)*(1+'① Hypothèses'!B54)))*MIN(1,'① Hypothèses'!B40+'① Hypothèses'!B52)*31,0) -> 220743 | AJ6: =ROUND('① Hypothèses'!B29*IF(MIN(1,'① Hypothèses'!B41+'① Hypothèses'!B52)>=0.8,'① Hypothèses'!B30*(1+'① Hypothèses'!B53)*(1+'① Hypothèses'!B54),IF(MIN(1,'① Hypothèses'!B41+'① Hypothèses'!B52)>=0.51,'① Hypothèses'!B31*(1+'① Hypothèses'!B53)*(1+'① Hypothèses'!B54),'① Hypothèses'!B32*(1+'① Hypothèses'!B53)*(1+'① Hypothèses'!B54)))*MIN(1,'① Hypothèses'!B41+'① Hypothèses'!B52)*30,0) -> 322659 | AK6: =ROUND('① Hypothèses'!B29*IF(MIN(1,'① Hypothèses'!B42+'① Hypothèses'!B52)>=0.8,'① Hypothèses'!B30*(1+'① Hypothèses'!B53)*(1+'① Hypothèses'!B54),IF(MIN(1,'① Hypothèses'!B42+'① Hypothèses'!B52)>=0.51,'① Hypothèses'!B31*(1+'① Hypothèses'!B53)*(1+'① Hypothèses'!B54),'① Hypothèses'!B32*(1+'① Hypothèses'!B53)*(1+'① Hypothèses'!B54)))*MIN(1,'① Hypothèses'!B42+'① Hypothèses'!B52)*31,0) -> 383234 | AL6: =ROUND('① Hypothèses'!B29*IF(MIN(1,'① Hypothèses'!B43+'① Hypothèses'!B52)>=0.8,'① Hypothèses'!B30*(1+'① Hypothèses'!B53)*(1+'① Hypothèses'!B54),IF(MIN(1,'① Hypothèses'!B43+'① Hypothèses'!B52)>=0.51,'① Hypothèses'!B31*(1+'① Hypothèses'!B53)*(1+'① Hypothèses'!B54),'① Hypothèses'!B32*(1+'① Hypothèses'!B53)*(1+'① Hypothèses'!B54)))*MIN(1,'① Hypothèses'!B43+'① Hypothèses'!B52)*31,0) -> 383234 | AM6: =ROUND('① Hypothèses'!B29*IF(MIN(1,'① Hypothèses'!B44+'① Hypothèses'!B52)>=0.8,'① Hypothèses'!B30*(1+'① Hypothèses'!B53)*(1+'① Hypothèses'!B54),IF(MIN(1,'① Hypothèses'!B44+'① Hypothèses'!B52)>=0.51,'① Hypothèses'!B31*(1+'① Hypothèses'!B53)*(1+'① Hypothèses'!B54),'① Hypothèses'!B32*(1+'① Hypothèses'!B53)*(1+'① Hypothèses'!B54)))*MIN(1,'① Hypothèses'!B44+'① Hypothèses'!B52)*30,0) -> 370872 | AN6: =ROUND('① Hypothèses'!B29*IF(MIN(1,'① Hypothèses'!B45+'① Hypothèses'!B52)>=0.8,'① Hypothèses'!B30*(1+'① Hypothèses'!B53)*(1+'① Hypothèses'!B54),IF(MIN(1,'① Hypothèses'!B45+'① Hypothèses'!B52)>=0.51,'① Hypothèses'!B31*(1+'① Hypothèses'!B53)*(1+'① Hypothèses'!B54),'① Hypothèses'!B32*(1+'① Hypothèses'!B53)*(1+'① Hypothèses'!B54)))*MIN(1,'① Hypothèses'!B45+'① Hypothèses'!B52)*31,0) -> 314252 | AO6: =ROUND('① Hypothèses'!B29*IF(MIN(1,'① Hypothèses'!B46+'① Hypothèses'!B52)>=0.8,'① Hypothèses'!B30*(1+'① Hypothèses'!B53)*(1+'① Hypothèses'!B54),IF(MIN(1,'① Hypothèses'!B46+'① Hypothèses'!B52)>=0.51,'① Hypothèses'!B31*(1+'① Hypothèses'!B53)*(1+'① Hypothèses'!B54),'① Hypothèses'!B32*(1+'① Hypothèses'!B53)*(1+'① Hypothèses'!B54)))*MIN(1,'① Hypothèses'!B46+'① Hypothèses'!B52)*30,0) -> 183953 | AP6: =ROUND('① Hypothèses'!B29*IF(MIN(1,'① Hypothèses'!B47+'① Hypothèses'!B52)>=0.8,'① Hypothèses'!B30*(1+'① Hypothèses'!B53)*(1+'① Hypothèses'!B54),IF(MIN(1,'① Hypothèses'!B47+'① Hypothèses'!B52)>=0.51,'① Hypothèses'!B31*(1+'① Hypothèses'!B53)*(1+'① Hypothèses'!B54),'① Hypothèses'!B32*(1+'① Hypothèses'!B53)*(1+'① Hypothèses'!B54)))*MIN(1,'① Hypothèses'!B47+'① Hypothèses'!B52)*31,0) -> 205414 | AQ6: =SUM(AE6,AF6,AG6,AH6,AI6,AJ6,AK6,AL6,AM6,AN6,AO6,AP6) -> 3061326
A7: CA Restauration & petits-déjeuners | C7: =ROUND(C6*'① Hypothèses'!B59,0) -> 11160 | D7: =ROUND(D6*'① Hypothèses'!B59,0) -> 10080 | E7: =ROUND(E6*'① Hypothèses'!B59,0) -> 16368 | F7: =ROUND(F6*'① Hypothèses'!B59,0) -> 18720 | G7: =ROUND(G6*'① Hypothèses'!B59,0) -> 20832 | H7: =ROUND(H6*'① Hypothèses'!B59,0) -> 30600 | I7: =ROUND(I6*'① Hypothèses'!B59,0) -> 37200 | J7: =ROUND(J6*'① Hypothèses'!B59,0) -> 37200 | K7: =ROUND(K6*'① Hypothèses'!B59,0) -> 36000 | L7: =ROUND(L6*'① Hypothèses'!B59,0) -> 29760 | M7: =ROUND(M6*'① Hypothèses'!B59,0) -> 17280 | N7: =ROUND(N6*'① Hypothèses'!B59,0) -> 19344 | O7: =SUM(C7,D7,E7,F7,G7,H7,I7,J7,K7,L7,M7,N7) -> 284544 | Q7: =ROUND(Q6*'① Hypothèses'!B59,0) -> 15329 | R7: =ROUND(R6*'① Hypothèses'!B59,0) -> 13846 | S7: =ROUND(S6*'① Hypothèses'!B59,0) -> 16832 | T7: =ROUND(T6*'① Hypothèses'!B59,0) -> 19198 | U7: =ROUND(U6*'① Hypothèses'!B59,0) -> 21341 | V7: =ROUND(V6*'① Hypothèses'!B59,0) -> 31270 | W7: =ROUND(W6*'① Hypothèses'!B59,0) -> 37572 | X7: =ROUND(X6*'① Hypothèses'!B59,0) -> 37572 | Y7: =ROUND(Y6*'① Hypothèses'!B59,0) -> 36360 | Z7: =ROUND(Z6*'① Hypothèses'!B59,0) -> 30433 | AA7: =ROUND(AA6*'① Hypothèses'!B59,0) -> 17744 | AB7: =ROUND(AB6*'① Hypothèses'!B59,0) -> 19838 | AC7: =SUM(Q7,R7,S7,T7,U7,V7,W7,X7,Y7,Z7,AA7,AB7) -> 297335 | AE7: =ROUND(AE6*'① Hypothèses'!B59,0) -> 15943 | AF7: =ROUND(AF6*'① Hypothèses'!B59,0) -> 14400 | AG7: =ROUND(AG6*'① Hypothèses'!B59,0) -> 17476 | AH7: =ROUND(AH6*'① Hypothèses'!B59,0) -> 19879 | AI7: =ROUND(AI6*'① Hypothèses'!B59,0) -> 22074 | AJ7: =ROUND(AJ6*'① Hypothèses'!B59,0) -> 32266 | AK7: =ROUND(AK6*'① Hypothèses'!B59,0) -> 38323 | AL7: =ROUND(AL6*'① Hypothèses'!B59,0) -> 38323 | AM7: =ROUND(AM6*'① Hypothèses'!B59,0) -> 37087 | AN7: =ROUND(AN6*'① Hypothèses'!B59,0) -> 31425 | AO7: =ROUND(AO6*'① Hypothèses'!B59,0) -> 18395 | AP7: =ROUND(AP6*'① Hypothèses'!B59,0) -> 20541 | AQ7: =SUM(AE7,AF7,AG7,AH7,AI7,AJ7,AK7,AL7,AM7,AN7,AO7,AP7) -> 306132
A8: CA Spa & Hammam | C8: 0 | D8: 0 | E8: 0 | F8: 0 | G8: 0 | H8: 0 | I8: 0 | J8: 0 | K8: 0 | L8: 0 | M8: 0 | N8: 0 | O8: =SUM(C8,D8,E8,F8,G8,H8,I8,J8,K8,L8,M8,N8) -> 0 | Q8: =ROUND(Q6*'① Hypothèses'!B60,0) -> 15329 | R8: =ROUND(R6*'① Hypothèses'!B60,0) -> 13846 | S8: =ROUND(S6*'① Hypothèses'!B60,0) -> 16832 | T8: =ROUND(T6*'① Hypothèses'!B60,0) -> 19198 | U8: =ROUND(U6*'① Hypothèses'!B60,0) -> 21341 | V8: =ROUND(V6*'① Hypothèses'!B60,0) -> 31270 | W8: =ROUND(W6*'① Hypothèses'!B60,0) -> 37572 | X8: =ROUND(X6*'① Hypothèses'!B60,0) -> 37572 | Y8: =ROUND(Y6*'① Hypothèses'!B60,0) -> 36360 | Z8: =ROUND(Z6*'① Hypothèses'!B60,0) -> 30433 | AA8: =ROUND(AA6*'① Hypothèses'!B60,0) -> 17744 | AB8: =ROUND(AB6*'① Hypothèses'!B60,0) -> 19838 | AC8: =SUM(Q8,R8,S8,T8,U8,V8,W8,X8,Y8,Z8,AA8,AB8) -> 297335 | AE8: =ROUND(AE6*'① Hypothèses'!B60,0) -> 15943 | AF8: =ROUND(AF6*'① Hypothèses'!B60,0) -> 14400 | AG8: =ROUND(AG6*'① Hypothèses'!B60,0) -> 17476 | AH8: =ROUND(AH6*'① Hypothèses'!B60,0) -> 19879 | AI8: =ROUND(AI6*'① Hypothèses'!B60,0) -> 22074 | AJ8: =ROUND(AJ6*'① Hypothèses'!B60,0) -> 32266 | AK8: =ROUND(AK6*'① Hypothèses'!B60,0) -> 38323 | AL8: =ROUND(AL6*'① Hypothèses'!B60,0) -> 38323 | AM8: =ROUND(AM6*'① Hypothèses'!B60,0) -> 37087 | AN8: =ROUND(AN6*'① Hypothèses'!B60,0) -> 31425 | AO8: =ROUND(AO6*'① Hypothèses'!B60,0) -> 18395 | AP8: =ROUND(AP6*'① Hypothèses'!B60,0) -> 20541 | AQ8: =SUM(AE8,AF8,AG8,AH8,AI8,AJ8,AK8,AL8,AM8,AN8,AO8,AP8) -> 306132
A9: CA Activités & Excursions | C9: 0 | D9: 0 | E9: 0 | F9: 0 | G9: 0 | H9: 0 | O9: =SUM(C9,D9,E9,F9,G9,H9,I9,J9,K9,L9,M9,N9) -> 0 | Q9: =ROUND(Q6*'① Hypothèses'!B61,0) -> 22994 | R9: =ROUND(R6*'① Hypothèses'!B61,0) -> 20769 | S9: =ROUND(S6*'① Hypothèses'!B61,0) -> 25248 | T9: =ROUND(T6*'① Hypothèses'!B61,0) -> 28797 | U9: =ROUND(U6*'① Hypothèses'!B61,0) -> 32011 | V9: =ROUND(V6*'① Hypothèses'!B61,0) -> 46904 | W9: =ROUND(W6*'① Hypothèses'!B61,0) -> 56358 | X9: =ROUND(X6*'① Hypothèses'!B61,0) -> 56358 | Y9: =ROUND(Y6*'① Hypothèses'!B61,0) -> 54540 | Z9: =ROUND(Z6*'① Hypothèses'!B61,0) -> 45650 | AA9: =ROUND(AA6*'① Hypothèses'!B61,0) -> 26616 | AB9: =ROUND(AB6*'① Hypothèses'!B61,0) -> 29757 | AC9: =SUM(Q9,R9,S9,T9,U9,V9,W9,X9,Y9,Z9,AA9,AB9) -> 446002 | AE9: =ROUND(AE6*'① Hypothèses'!B61,0) -> 23914 | AF9: =ROUND(AF6*'① Hypothèses'!B61,0) -> 21600 | AG9: =ROUND(AG6*'① Hypothèses'!B61,0) -> 26213 | AH9: =ROUND(AH6*'① Hypothèses'!B61,0) -> 29818 | AI9: =ROUND(AI6*'① Hypothèses'!B61,0) -> 33111 | AJ9: =ROUND(AJ6*'① Hypothèses'!B61,0) -> 48399 | AK9: =ROUND(AK6*'① Hypothèses'!B61,0) -> 57485 | AL9: =ROUND(AL6*'① Hypothèses'!B61,0) -> 57485 | AM9: =ROUND(AM6*'① Hypothèses'!B61,0) -> 55631 | AN9: =ROUND(AN6*'① Hypothèses'!B61,0) -> 47138 | AO9: =ROUND(AO6*'① Hypothèses'!B61,0) -> 27593 | AP9: =ROUND(AP6*'① Hypothèses'!B61,0) -> 30812 | AQ9: =SUM(AE9,AF9,AG9,AH9,AI9,AJ9,AK9,AL9,AM9,AN9,AO9,AP9) -> 459199
A10: CA Séminaires & Événements [supprimé] | C10: 0 | D10: 0 | E10: 0 | F10: 0 | G10: 0 | H10: 0 | I10: 0 | J10: 0 | K10: 0 | L10: 0 | M10: 0 | N10: 0 | O10: 0 | Q10: 0 | R10: 0 | S10: 0 | T10: 0 | U10: 0 | V10: 0 | W10: 0 | X10: 0 | Y10: 0 | Z10: 0 | AA10: 0 | AB10: 0 | AC10: 0 | AE10: 0 | AF10: 0 | AG10: 0 | AH10: 0 | AI10: 0 | AJ10: 0 | AK10: 0 | AL10: 0 | AM10: 0 | AN10: 0 | AO10: 0 | AP10: 0 | AQ10: 0
A11: TOTAL PRODUITS D'EXPLOITATION | C11: =C6+C7+C8+C9+C10 -> 122760 | D11: =D6+D7+D8+D9+D10 -> 110880 | E11: =E6+E7+E8+E9+E10 -> 180048 | F11: =F6+F7+F8+F9+F10 -> 205920 | G11: =G6+G7+G8+G9+G10 -> 229152 | H11: =H6+H7+H8+H9+H10 -> 336600 | I11: =I6+I7+I8+I9+I10 -> 409200 | J11: =J6+J7+J8+J9+J10 -> 409200 | ... N11: =N6+N7+N8+N9+N10 -> 212784 | O11: =SUM(C11,D11,E11,F11,G11,H11,I11,J11,K11,L11,M11,N11) -> 3129984 | Q11: =Q6+Q7+Q8+Q9+Q10 -> 206946 | R11: =R6+R7+R8+R9+R10 -> 186920 | S11: =S6+S7+S8+S9+S10 -> 227235 | T11: =T6+T7+T8+T9+T10 -> 259174 | U11: =U6+U7+U8+U9+U10 -> 288102 | V11: =V6+V7+V8+V9+V10 -> 422140 | W11: =W6+W7+W8+W9+W10 -> 507222 | X11: =X6+X7+X8+X9+X10 -> 507222 | ... AB11: =AB6+AB7+AB8+AB9+AB10 -> 267813 | AC11: =SUM(Q11,R11,S11,T11,U11,V11,W11,X11,Y11,Z11,AA11,AB11) -> 4014024 | AE11: =AE6+AE7+AE8+AE9+AE10 -> 215226 | AF11: =AF6+AF7+AF8+AF9+AF10 -> 194397 | AG11: =AG6+AG7+AG8+AG9+AG10 -> 235920 | AH11: =AH6+AH7+AH8+AH9+AH10 -> 268363 | AI11: =AI6+AI7+AI8+AI9+AI10 -> 298002 | AJ11: =AJ6+AJ7+AJ8+AJ9+AJ10 -> 435590 | AK11: =AK6+AK7+AK8+AK9+AK10 -> 517365 | AL11: =AL6+AL7+AL8+AL9+AL10 -> 517365 | ... AP11: =AP6+AP7+AP8+AP9+AP10 -> 277308 | AQ11: =SUM(AE11,AF11,AG11,AH11,AI11,AJ11,AK11,AL11,AM11,AN11,AO11,AP11) -> 4132789
A12: CHARGES D'EXPLOITATION
A13: Commissions OTA (Booking, Airbnb) | C13: =ROUND(C6*'① Hypothèses'!B64,0) -> 17856 | D13: =ROUND(D6*'① Hypothèses'!B64,0) -> 16128 | E13: =ROUND(E6*'① Hypothèses'!B64,0) -> 26189 | F13: =ROUND(F6*'① Hypothèses'!B64,0) -> 29952 | G13: =ROUND(G6*'① Hypothèses'!B64,0) -> 33331 | H13: =ROUND(H6*'① Hypothèses'!B64,0) -> 48960 | I13: =ROUND(I6*'① Hypothèses'!B64,0) -> 59520 | J13: =ROUND(J6*'① Hypothèses'!B64,0) -> 59520 | K13: =ROUND(K6*'① Hypothèses'!B64,0) -> 57600 | L13: =ROUND(L6*'① Hypothèses'!B64,0) -> 47616 | M13: =ROUND(M6*'① Hypothèses'!B64,0) -> 27648 | N13: =ROUND(N6*'① Hypothèses'!B64,0) -> 30950 | O13: =SUM(C13,D13,E13,F13,G13,H13,I13,J13,K13,L13,M13,N13) -> 455270 | Q13: =ROUND(Q6*'① Hypothèses'!B64,0) -> 24527 | R13: =ROUND(R6*'① Hypothèses'!B64,0) -> 22153 | S13: =ROUND(S6*'① Hypothèses'!B64,0) -> 26932 | T13: =ROUND(T6*'① Hypothèses'!B64,0) -> 30717 | U13: =ROUND(U6*'① Hypothèses'!B64,0) -> 34145 | V13: =ROUND(V6*'① Hypothèses'!B64,0) -> 50031 | W13: =ROUND(W6*'① Hypothèses'!B64,0) -> 60115 | X13: =ROUND(X6*'① Hypothèses'!B64,0) -> 60115 | Y13: =ROUND(Y6*'① Hypothèses'!B64,0) -> 58176 | Z13: =ROUND(Z6*'① Hypothèses'!B64,0) -> 48693 | AA13: =ROUND(AA6*'① Hypothèses'!B64,0) -> 28390 | AB13: =ROUND(AB6*'① Hypothèses'!B64,0) -> 31741 | AC13: =SUM(Q13,R13,S13,T13,U13,V13,W13,X13,Y13,Z13,AA13,AB13) -> 475735 | AE13: =ROUND(AE6*'① Hypothèses'!B64,0) -> 25508 | AF13: =ROUND(AF6*'① Hypothèses'!B64,0) -> 23040 | AG13: =ROUND(AG6*'① Hypothèses'!B64,0) -> 27961 | AH13: =ROUND(AH6*'① Hypothèses'!B64,0) -> 31806 | AI13: =ROUND(AI6*'① Hypothèses'!B64,0) -> 35319 | AJ13: =ROUND(AJ6*'① Hypothèses'!B64,0) -> 51625 | AK13: =ROUND(AK6*'① Hypothèses'!B64,0) -> 61317 | AL13: =ROUND(AL6*'① Hypothèses'!B64,0) -> 61317 | AM13: =ROUND(AM6*'① Hypothèses'!B64,0) -> 59340 | AN13: =ROUND(AN6*'① Hypothèses'!B64,0) -> 50280 | AO13: =ROUND(AO6*'① Hypothèses'!B64,0) -> 29432 | AP13: =ROUND(AP6*'① Hypothèses'!B64,0) -> 32866 | AQ13: =SUM(AE13,AF13,AG13,AH13,AI13,AJ13,AK13,AL13,AM13,AN13,AO13,AP13) -> 489811
A14: Achats marchandises restauration | C14: =ROUND(C7*'① Hypothèses'!B65,0) -> 4464 | D14: =ROUND(D7*'① Hypothèses'!B65,0) -> 4032 | E14: =ROUND(E7*'① Hypothèses'!B65,0) -> 6547 | F14: =ROUND(F7*'① Hypothèses'!B65,0) -> 7488 | G14: =ROUND(G7*'① Hypothèses'!B65,0) -> 8333 | H14: =ROUND(H7*'① Hypothèses'!B65,0) -> 12240 | I14: =ROUND(I7*'① Hypothèses'!B65,0) -> 14880 | J14: =ROUND(J7*'① Hypothèses'!B65,0) -> 14880 | K14: =ROUND(K7*'① Hypothèses'!B65,0) -> 14400 | L14: =ROUND(L7*'① Hypothèses'!B65,0) -> 11904 | M14: =ROUND(M7*'① Hypothèses'!B65,0) -> 6912 | N14: =ROUND(N7*'① Hypothèses'!B65,0) -> 7738 | O14: =SUM(C14,D14,E14,F14,G14,H14,I14,J14,K14,L14,M14,N14) -> 113818 | Q14: =ROUND(Q7*'① Hypothèses'!B65,0) -> 6132 | R14: =ROUND(R7*'① Hypothèses'!B65,0) -> 5538 | S14: =ROUND(S7*'① Hypothèses'!B65,0) -> 6733 | T14: =ROUND(T7*'① Hypothèses'!B65,0) -> 7679 | U14: =ROUND(U7*'① Hypothèses'!B65,0) -> 8536 | V14: =ROUND(V7*'① Hypothèses'!B65,0) -> 12508 | W14: =ROUND(W7*'① Hypothèses'!B65,0) -> 15029 | X14: =ROUND(X7*'① Hypothèses'!B65,0) -> 15029 | Y14: =ROUND(Y7*'① Hypothèses'!B65,0) -> 14544 | Z14: =ROUND(Z7*'① Hypothèses'!B65,0) -> 12173 | AA14: =ROUND(AA7*'① Hypothèses'!B65,0) -> 7098 | AB14: =ROUND(AB7*'① Hypothèses'!B65,0) -> 7935 | AC14: =SUM(Q14,R14,S14,T14,U14,V14,W14,X14,Y14,Z14,AA14,AB14) -> 118934 | AE14: =ROUND(AE7*'① Hypothèses'!B65,0) -> 6377 | AF14: =ROUND(AF7*'① Hypothèses'!B65,0) -> 5760 | AG14: =ROUND(AG7*'① Hypothèses'!B65,0) -> 6990 | AH14: =ROUND(AH7*'① Hypothèses'!B65,0) -> 7952 | AI14: =ROUND(AI7*'① Hypothèses'!B65,0) -> 8830 | AJ14: =ROUND(AJ7*'① Hypothèses'!B65,0) -> 12906 | AK14: =ROUND(AK7*'① Hypothèses'!B65,0) -> 15329 | AL14: =ROUND(AL7*'① Hypothèses'!B65,0) -> 15329 | AM14: =ROUND(AM7*'① Hypothèses'!B65,0) -> 14835 | AN14: =ROUND(AN7*'① Hypothèses'!B65,0) -> 12570 | AO14: =ROUND(AO7*'① Hypothèses'!B65,0) -> 7358 | AP14: =ROUND(AP7*'① Hypothèses'!B65,0) -> 8216 | AQ14: =SUM(AE14,AF14,AG14,AH14,AI14,AJ14,AK14,AL14,AM14,AN14,AO14,AP14) -> 122452
A15: Loyer versé à la Holding (bail commercial) | C15: ='① Hypothèses'!B24 -> 27761 | D15: ='① Hypothèses'!B24 -> 27761 | E15: ='① Hypothèses'!B24 -> 27761 | F15: ='① Hypothèses'!B24 -> 27761 | G15: ='① Hypothèses'!B24 -> 27761 | H15: ='① Hypothèses'!B24 -> 27761 | I15: ='① Hypothèses'!B24 -> 27761 | J15: ='① Hypothèses'!B24 -> 27761 | K15: ='① Hypothèses'!B24 -> 27761 | L15: ='① Hypothèses'!B24 -> 27761 | M15: ='① Hypothèses'!B24 -> 27761 | N15: ='① Hypothèses'!B24 -> 27761 | O15: =SUM(C15,D15,E15,F15,G15,H15,I15,J15,K15,L15,M15,N15) -> 333132 | Q15: ='① Hypothèses'!B24 -> 27761 | R15: ='① Hypothèses'!B24 -> 27761 | S15: ='① Hypothèses'!B24 -> 27761 | T15: ='① Hypothèses'!B24 -> 27761 | U15: ='① Hypothèses'!B24 -> 27761 | V15: ='① Hypothèses'!B24 -> 27761 | W15: ='① Hypothèses'!B24 -> 27761 | X15: ='① Hypothèses'!B24 -> 27761 | Y15: ='① Hypothèses'!B24 -> 27761 | Z15: ='① Hypothèses'!B24 -> 27761 | AA15: ='① Hypothèses'!B24 -> 27761 | AB15: ='① Hypothèses'!B24 -> 27761 | AC15: =SUM(Q15,R15,S15,T15,U15,V15,W15,X15,Y15,Z15,AA15,AB15) -> 333132 | AE15: ='① Hypothèses'!B24 -> 27761 | AF15: ='① Hypothèses'!B24 -> 27761 | AG15: ='① Hypothèses'!B24 -> 27761 | AH15: ='① Hypothèses'!B24 -> 27761 | AI15: ='① Hypothèses'!B24 -> 27761 | AJ15: ='① Hypothèses'!B24 -> 27761 | AK15: ='① Hypothèses'!B24 -> 27761 | AL15: ='① Hypothèses'!B24 -> 27761 | AM15: ='① Hypothèses'!B24 -> 27761 | AN15: ='① Hypothèses'!B24 -> 27761 | AO15: ='① Hypothèses'!B24 -> 27761 | AP15: ='① Hypothèses'!B24 -> 27761 | AQ15: =SUM(AE15,AF15,AG15,AH15,AI15,AJ15,AK15,AL15,AM15,AN15,AO15,AP15) -> 333132
A16: Assurances | C16: =ROUND('① Hypothèses'!B66/12,0) -> 3750 | D16: =ROUND('① Hypothèses'!B66/12,0) -> 3750 | E16: =ROUND('① Hypothèses'!B66/12,0) -> 3750 | F16: =ROUND('① Hypothèses'!B66/12,0) -> 3750 | G16: =ROUND('① Hypothèses'!B66/12,0) -> 3750 | H16: =ROUND('① Hypothèses'!B66/12,0) -> 3750 | I16: =ROUND('① Hypothèses'!B66/12,0) -> 3750 | J16: =ROUND('① Hypothèses'!B66/12,0) -> 3750 | K16: =ROUND('① Hypothèses'!B66/12,0) -> 3750 | L16: =ROUND('① Hypothèses'!B66/12,0) -> 3750 | M16: =ROUND('① Hypothèses'!B66/12,0) -> 3750 | N16: =ROUND('① Hypothèses'!B66/12,0) -> 3750 | O16: =SUM(C16,D16,E16,F16,G16,H16,I16,J16,K16,L16,M16,N16) -> 45000 | Q16: =ROUND('① Hypothèses'!B66/12*(1+'① Hypothèses'!B55),0) -> 3825 | R16: =ROUND('① Hypothèses'!B66/12*(1+'① Hypothèses'!B55),0) -> 3825 | S16: =ROUND('① Hypothèses'!B66/12*(1+'① Hypothèses'!B55),0) -> 3825 | T16: =ROUND('① Hypothèses'!B66/12*(1+'① Hypothèses'!B55),0) -> 3825 | U16: =ROUND('① Hypothèses'!B66/12*(1+'① Hypothèses'!B55),0) -> 3825 | V16: =ROUND('① Hypothèses'!B66/12*(1+'① Hypothèses'!B55),0) -> 3825 | W16: =ROUND('① Hypothèses'!B66/12*(1+'① Hypothèses'!B55),0) -> 3825 | X16: =ROUND('① Hypothèses'!B66/12*(1+'① Hypothèses'!B55),0) -> 3825 | Y16: =ROUND('① Hypothèses'!B66/12*(1+'① Hypothèses'!B55),0) -> 3825 | Z16: =ROUND('① Hypothèses'!B66/12*(1+'① Hypothèses'!B55),0) -> 3825 | AA16: =ROUND('① Hypothèses'!B66/12*(1+'① Hypothèses'!B55),0) -> 3825 | AB16: =ROUND('① Hypothèses'!B66/12*(1+'① Hypothèses'!B55),0) -> 3825 | AC16: =SUM(Q16,R16,S16,T16,U16,V16,W16,X16,Y16,Z16,AA16,AB16) -> 45900 | AE16: =ROUND('① Hypothèses'!B66/12*(1+'① Hypothèses'!B55)^2,0) -> 3902 | AF16: =ROUND('① Hypothèses'!B66/12*(1+'① Hypothèses'!B55)^2,0) -> 3902 | AG16: =ROUND('① Hypothèses'!B66/12*(1+'① Hypothèses'!B55)^2,0) -> 3902 | AH16: =ROUND('① Hypothèses'!B66/12*(1+'① Hypothèses'!B55)^2,0) -> 3902 | AI16: =ROUND('① Hypothèses'!B66/12*(1+'① Hypothèses'!B55)^2,0) -> 3902 | AJ16: =ROUND('① Hypothèses'!B66/12*(1+'① Hypothèses'!B55)^2,0) -> 3902 | AK16: =ROUND('① Hypothèses'!B66/12*(1+'① Hypothèses'!B55)^2,0) -> 3902 | AL16: =ROUND('① Hypothèses'!B66/12*(1+'① Hypothèses'!B55)^2,0) -> 3902 | AM16: =ROUND('① Hypothèses'!B66/12*(1+'① Hypothèses'!B55)^2,0) -> 3902 | AN16: =ROUND('① Hypothèses'!B66/12*(1+'① Hypothèses'!B55)^2,0) -> 3902 | AO16: =ROUND('① Hypothèses'!B66/12*(1+'① Hypothèses'!B55)^2,0) -> 3902 | AP16: =ROUND('① Hypothèses'!B66/12*(1+'① Hypothèses'!B55)^2,0) -> 3902 | AQ16: =SUM(AE16,AF16,AG16,AH16,AI16,AJ16,AK16,AL16,AM16,AN16,AO16,AP16) -> 46824
A17: Eau, électricité, gaz | C17: =ROUND('① Hypothèses'!B67,0) -> 15000 | D17: =ROUND('① Hypothèses'!B67,0) -> 15000 | E17: =ROUND('① Hypothèses'!B67,0) -> 15000 | F17: =ROUND('① Hypothèses'!B67,0) -> 15000 | G17: =ROUND('① Hypothèses'!B67,0) -> 15000 | H17: =ROUND('① Hypothèses'!B67,0) -> 15000 | I17: =ROUND('① Hypothèses'!B67,0) -> 15000 | J17: =ROUND('① Hypothèses'!B67,0) -> 15000 | K17: =ROUND('① Hypothèses'!B67,0) -> 15000 | L17: =ROUND('① Hypothèses'!B67,0) -> 15000 | M17: =ROUND('① Hypothèses'!B67,0) -> 15000 | N17: =ROUND('① Hypothèses'!B67,0) -> 15000 | O17: =SUM(C17,D17,E17,F17,G17,H17,I17,J17,K17,L17,M17,N17) -> 180000 | Q17: =ROUND('① Hypothèses'!B67*(1+'① Hypothèses'!B55),0) -> 15300 | R17: =ROUND('① Hypothèses'!B67*(1+'① Hypothèses'!B55),0) -> 15300 | S17: =ROUND('① Hypothèses'!B67*(1+'① Hypothèses'!B55),0) -> 15300 | T17: =ROUND('① Hypothèses'!B67*(1+'① Hypothèses'!B55),0) -> 15300 | U17: =ROUND('① Hypothèses'!B67*(1+'① Hypothèses'!B55),0) -> 15300 | V17: =ROUND('① Hypothèses'!B67*(1+'① Hypothèses'!B55),0) -> 15300 | W17: =ROUND('① Hypothèses'!B67*(1+'① Hypothèses'!B55),0) -> 15300 | X17: =ROUND('① Hypothèses'!B67*(1+'① Hypothèses'!B55),0) -> 15300 | Y17: =ROUND('① Hypothèses'!B67*(1+'① Hypothèses'!B55),0) -> 15300 | Z17: =ROUND('① Hypothèses'!B67*(1+'① Hypothèses'!B55),0) -> 15300 | AA17: =ROUND('① Hypothèses'!B67*(1+'① Hypothèses'!B55),0) -> 15300 | AB17: =ROUND('① Hypothèses'!B67*(1+'① Hypothèses'!B55),0) -> 15300 | AC17: =SUM(Q17,R17,S17,T17,U17,V17,W17,X17,Y17,Z17,AA17,AB17) -> 183600 | AE17: =ROUND('① Hypothèses'!B67*(1+'① Hypothèses'!B55)^2,0) -> 15606 | AF17: =ROUND('① Hypothèses'!B67*(1+'① Hypothèses'!B55)^2,0) -> 15606 | AG17: =ROUND('① Hypothèses'!B67*(1+'① Hypothèses'!B55)^2,0) -> 15606 | AH17: =ROUND('① Hypothèses'!B67*(1+'① Hypothèses'!B55)^2,0) -> 15606 | AI17: =ROUND('① Hypothèses'!B67*(1+'① Hypothèses'!B55)^2,0) -> 15606 | AJ17: =ROUND('① Hypothèses'!B67*(1+'① Hypothèses'!B55)^2,0) -> 15606 | AK17: =ROUND('① Hypothèses'!B67*(1+'① Hypothèses'!B55)^2,0) -> 15606 | AL17: =ROUND('① Hypothèses'!B67*(1+'① Hypothèses'!B55)^2,0) -> 15606 | AM17: =ROUND('① Hypothèses'!B67*(1+'① Hypothèses'!B55)^2,0) -> 15606 | AN17: =ROUND('① Hypothèses'!B67*(1+'① Hypothèses'!B55)^2,0) -> 15606 | AO17: =ROUND('① Hypothèses'!B67*(1+'① Hypothèses'!B55)^2,0) -> 15606 | AP17: =ROUND('① Hypothèses'!B67*(1+'① Hypothèses'!B55)^2,0) -> 15606 | AQ17: =SUM(AE17,AF17,AG17,AH17,AI17,AJ17,AK17,AL17,AM17,AN17,AO17,AP17) -> 187272
A18: Entretien & maintenance | C18: =ROUND('① Hypothèses'!B68/12,0) -> 5833 | D18: =ROUND('① Hypothèses'!B68/12,0) -> 5833 | E18: =ROUND('① Hypothèses'!B68/12,0) -> 5833 | F18: =ROUND('① Hypothèses'!B68/12,0) -> 5833 | G18: =ROUND('① Hypothèses'!B68/12,0) -> 5833 | H18: =ROUND('① Hypothèses'!B68/12,0) -> 5833 | I18: =ROUND('① Hypothèses'!B68/12,0) -> 5833 | J18: =ROUND('① Hypothèses'!B68/12,0) -> 5833 | K18: =ROUND('① Hypothèses'!B68/12,0) -> 5833 | L18: =ROUND('① Hypothèses'!B68/12,0) -> 5833 | M18: =ROUND('① Hypothèses'!B68/12,0) -> 5833 | N18: =ROUND('① Hypothèses'!B68/12,0) -> 5833 | O18: =SUM(C18,D18,E18,F18,G18,H18,I18,J18,K18,L18,M18,N18) -> 69996 | Q18: =ROUND('① Hypothèses'!B68/12*(1+'① Hypothèses'!B55),0) -> 5950 | R18: =ROUND('① Hypothèses'!B68/12*(1+'① Hypothèses'!B55),0) -> 5950 | S18: =ROUND('① Hypothèses'!B68/12*(1+'① Hypothèses'!B55),0) -> 5950 | T18: =ROUND('① Hypothèses'!B68/12*(1+'① Hypothèses'!B55),0) -> 5950 | U18: =ROUND('① Hypothèses'!B68/12*(1+'① Hypothèses'!B55),0) -> 5950 | V18: =ROUND('① Hypothèses'!B68/12*(1+'① Hypothèses'!B55),0) -> 5950 | W18: =ROUND('① Hypothèses'!B68/12*(1+'① Hypothèses'!B55),0) -> 5950 | X18: =ROUND('① Hypothèses'!B68/12*(1+'① Hypothèses'!B55),0) -> 5950 | Y18: =ROUND('① Hypothèses'!B68/12*(1+'① Hypothèses'!B55),0) -> 5950 | Z18: =ROUND('① Hypothèses'!B68/12*(1+'① Hypothèses'!B55),0) -> 5950 | AA18: =ROUND('① Hypothèses'!B68/12*(1+'① Hypothèses'!B55),0) -> 5950 | AB18: =ROUND('① Hypothèses'!B68/12*(1+'① Hypothèses'!B55),0) -> 5950 | AC18: =SUM(Q18,R18,S18,T18,U18,V18,W18,X18,Y18,Z18,AA18,AB18) -> 71400 | AE18: =ROUND('① Hypothèses'!B68/12*(1+'① Hypothèses'!B55)^2,0) -> 6069 | AF18: =ROUND('① Hypothèses'!B68/12*(1+'① Hypothèses'!B55)^2,0) -> 6069 | AG18: =ROUND('① Hypothèses'!B68/12*(1+'① Hypothèses'!B55)^2,0) -> 6069 | AH18: =ROUND('① Hypothèses'!B68/12*(1+'① Hypothèses'!B55)^2,0) -> 6069 | AI18: =ROUND('① Hypothèses'!B68/12*(1+'① Hypothèses'!B55)^2,0) -> 6069 | AJ18: =ROUND('① Hypothèses'!B68/12*(1+'① Hypothèses'!B55)^2,0) -> 6069 | AK18: =ROUND('① Hypothèses'!B68/12*(1+'① Hypothèses'!B55)^2,0) -> 6069 | AL18: =ROUND('① Hypothèses'!B68/12*(1+'① Hypothèses'!B55)^2,0) -> 6069 | AM18: =ROUND('① Hypothèses'!B68/12*(1+'① Hypothèses'!B55)^2,0) -> 6069 | AN18: =ROUND('① Hypothèses'!B68/12*(1+'① Hypothèses'!B55)^2,0) -> 6069 | AO18: =ROUND('① Hypothèses'!B68/12*(1+'① Hypothèses'!B55)^2,0) -> 6069 | AP18: =ROUND('① Hypothèses'!B68/12*(1+'① Hypothèses'!B55)^2,0) -> 6069 | AQ18: =SUM(AE18,AF18,AG18,AH18,AI18,AJ18,AK18,AL18,AM18,AN18,AO18,AP18) -> 72828
A19: Marketing & communication | C19: =ROUND('① Hypothèses'!B69/12,0) -> 4167 | D19: =ROUND('① Hypothèses'!B69/12,0) -> 4167 | E19: =ROUND('① Hypothèses'!B69/12,0) -> 4167 | F19: =ROUND('① Hypothèses'!B69/12,0) -> 4167 | G19: =ROUND('① Hypothèses'!B69/12,0) -> 4167 | H19: =ROUND('① Hypothèses'!B69/12,0) -> 4167 | I19: =ROUND('① Hypothèses'!B69/12,0) -> 4167 | J19: =ROUND('① Hypothèses'!B69/12,0) -> 4167 | K19: =ROUND('① Hypothèses'!B69/12,0) -> 4167 | L19: =ROUND('① Hypothèses'!B69/12,0) -> 4167 | M19: =ROUND('① Hypothèses'!B69/12,0) -> 4167 | N19: =ROUND('① Hypothèses'!B69/12,0) -> 4167 | O19: =SUM(C19,D19,E19,F19,G19,H19,I19,J19,K19,L19,M19,N19) -> 50004 | Q19: =ROUND('① Hypothèses'!B69/12*(1+'① Hypothèses'!B55),0) -> 4250 | R19: =ROUND('① Hypothèses'!B69/12*(1+'① Hypothèses'!B55),0) -> 4250 | S19: =ROUND('① Hypothèses'!B69/12*(1+'① Hypothèses'!B55),0) -> 4250 | T19: =ROUND('① Hypothèses'!B69/12*(1+'① Hypothèses'!B55),0) -> 4250 | U19: =ROUND('① Hypothèses'!B69/12*(1+'① Hypothèses'!B55),0) -> 4250 | V19: =ROUND('① Hypothèses'!B69/12*(1+'① Hypothèses'!B55),0) -> 4250 | W19: =ROUND('① Hypothèses'!B69/12*(1+'① Hypothèses'!B55),0) -> 4250 | X19: =ROUND('① Hypothèses'!B69/12*(1+'① Hypothèses'!B55),0) -> 4250 | Y19: =ROUND('① Hypothèses'!B69/12*(1+'① Hypothèses'!B55),0) -> 4250 | Z19: =ROUND('① Hypothèses'!B69/12*(1+'① Hypothèses'!B55),0) -> 4250 | AA19: =ROUND('① Hypothèses'!B69/12*(1+'① Hypothèses'!B55),0) -> 4250 | AB19: =ROUND('① Hypothèses'!B69/12*(1+'① Hypothèses'!B55),0) -> 4250 | AC19: =SUM(Q19,R19,S19,T19,U19,V19,W19,X19,Y19,Z19,AA19,AB19) -> 51000 | AE19: =ROUND('① Hypothèses'!B69/12*(1+'① Hypothèses'!B55)^2,0) -> 4335 | AF19: =ROUND('① Hypothèses'!B69/12*(1+'① Hypothèses'!B55)^2,0) -> 4335 | AG19: =ROUND('① Hypothèses'!B69/12*(1+'① Hypothèses'!B55)^2,0) -> 4335 | AH19: =ROUND('① Hypothèses'!B69/12*(1+'① Hypothèses'!B55)^2,0) -> 4335 | AI19: =ROUND('① Hypothèses'!B69/12*(1+'① Hypothèses'!B55)^2,0) -> 4335 | AJ19: =ROUND('① Hypothèses'!B69/12*(1+'① Hypothèses'!B55)^2,0) -> 4335 | AK19: =ROUND('① Hypothèses'!B69/12*(1+'① Hypothèses'!B55)^2,0) -> 4335 | AL19: =ROUND('① Hypothèses'!B69/12*(1+'① Hypothèses'!B55)^2,0) -> 4335 | AM19: =ROUND('① Hypothèses'!B69/12*(1+'① Hypothèses'!B55)^2,0) -> 4335 | AN19: =ROUND('① Hypothèses'!B69/12*(1+'① Hypothèses'!B55)^2,0) -> 4335 | AO19: =ROUND('① Hypothèses'!B69/12*(1+'① Hypothèses'!B55)^2,0) -> 4335 | AP19: =ROUND('① Hypothèses'!B69/12*(1+'① Hypothèses'!B55)^2,0) -> 4335 | AQ19: =SUM(AE19,AF19,AG19,AH19,AI19,AJ19,AK19,AL19,AM19,AN19,AO19,AP19) -> 52020
A20: Fournitures & linge | C20: =ROUND('① Hypothèses'!B70/12,0) -> 3750 | D20: =ROUND('① Hypothèses'!B70/12,0) -> 3750 | E20: =ROUND('① Hypothèses'!B70/12,0) -> 3750 | F20: =ROUND('① Hypothèses'!B70/12,0) -> 3750 | G20: =ROUND('① Hypothèses'!B70/12,0) -> 3750 | H20: =ROUND('① Hypothèses'!B70/12,0) -> 3750 | I20: =ROUND('① Hypothèses'!B70/12,0) -> 3750 | J20: =ROUND('① Hypothèses'!B70/12,0) -> 3750 | K20: =ROUND('① Hypothèses'!B70/12,0) -> 3750 | L20: =ROUND('① Hypothèses'!B70/12,0) -> 3750 | M20: =ROUND('① Hypothèses'!B70/12,0) -> 3750 | N20: =ROUND('① Hypothèses'!B70/12,0) -> 3750 | O20: =SUM(C20,D20,E20,F20,G20,H20,I20,J20,K20,L20,M20,N20) -> 45000 | Q20: =ROUND('① Hypothèses'!B70/12*(1+'① Hypothèses'!B55),0) -> 3825 | R20: =ROUND('① Hypothèses'!B70/12*(1+'① Hypothèses'!B55),0) -> 3825 | S20: =ROUND('① Hypothèses'!B70/12*(1+'① Hypothèses'!B55),0) -> 3825 | T20: =ROUND('① Hypothèses'!B70/12*(1+'① Hypothèses'!B55),0) -> 3825 | U20: =ROUND('① Hypothèses'!B70/12*(1+'① Hypothèses'!B55),0) -> 3825 | V20: =ROUND('① Hypothèses'!B70/12*(1+'① Hypothèses'!B55),0) -> 3825 | W20: =ROUND('① Hypothèses'!B70/12*(1+'① Hypothèses'!B55),0) -> 3825 | X20: =ROUND('① Hypothèses'!B70/12*(1+'① Hypothèses'!B55),0) -> 3825 | Y20: =ROUND('① Hypothèses'!B70/12*(1+'① Hypothèses'!B55),0) -> 3825 | Z20: =ROUND('① Hypothèses'!B70/12*(1+'① Hypothèses'!B55),0) -> 3825 | AA20: =ROUND('① Hypothèses'!B70/12*(1+'① Hypothèses'!B55),0) -> 3825 | AB20: =ROUND('① Hypothèses'!B70/12*(1+'① Hypothèses'!B55),0) -> 3825 | AC20: =SUM(Q20,R20,S20,T20,U20,V20,W20,X20,Y20,Z20,AA20,AB20) -> 45900 | AE20: =ROUND('① Hypothèses'!B70/12*(1+'① Hypothèses'!B55)^2,0) -> 3902 | AF20: =ROUND('① Hypothèses'!B70/12*(1+'① Hypothèses'!B55)^2,0) -> 3902 | AG20: =ROUND('① Hypothèses'!B70/12*(1+'① Hypothèses'!B55)^2,0) -> 3902 | AH20: =ROUND('① Hypothèses'!B70/12*(1+'① Hypothèses'!B55)^2,0) -> 3902 | AI20: =ROUND('① Hypothèses'!B70/12*(1+'① Hypothèses'!B55)^2,0) -> 3902 | AJ20: =ROUND('① Hypothèses'!B70/12*(1+'① Hypothèses'!B55)^2,0) -> 3902 | AK20: =ROUND('① Hypothèses'!B70/12*(1+'① Hypothèses'!B55)^2,0) -> 3902 | AL20: =ROUND('① Hypothèses'!B70/12*(1+'① Hypothèses'!B55)^2,0) -> 3902 | AM20: =ROUND('① Hypothèses'!B70/12*(1+'① Hypothèses'!B55)^2,0) -> 3902 | AN20: =ROUND('① Hypothèses'!B70/12*(1+'① Hypothèses'!B55)^2,0) -> 3902 | AO20: =ROUND('① Hypothèses'!B70/12*(1+'① Hypothèses'!B55)^2,0) -> 3902 | AP20: =ROUND('① Hypothèses'!B70/12*(1+'① Hypothèses'!B55)^2,0) -> 3902 | AQ20: =SUM(AE20,AF20,AG20,AH20,AI20,AJ20,AK20,AL20,AM20,AN20,AO20,AP20) -> 46824
A21: Expert-comptable | C21: =ROUND('① Hypothèses'!B71/12,0) -> 5417 | D21: =ROUND('① Hypothèses'!B71/12,0) -> 5417 | E21: =ROUND('① Hypothèses'!B71/12,0) -> 5417 | F21: =ROUND('① Hypothèses'!B71/12,0) -> 5417 | G21: =ROUND('① Hypothèses'!B71/12,0) -> 5417 | H21: =ROUND('① Hypothèses'!B71/12,0) -> 5417 | I21: =ROUND('① Hypothèses'!B71/12,0) -> 5417 | J21: =ROUND('① Hypothèses'!B71/12,0) -> 5417 | K21: =ROUND('① Hypothèses'!B71/12,0) -> 5417 | L21: =ROUND('① Hypothèses'!B71/12,0) -> 5417 | M21: =ROUND('① Hypothèses'!B71/12,0) -> 5417 | N21: =ROUND('① Hypothèses'!B71/12,0) -> 5417 | O21: =SUM(C21,D21,E21,F21,G21,H21,I21,J21,K21,L21,M21,N21) -> 65004 | Q21: =ROUND('① Hypothèses'!B71/12,0) -> 5417 | R21: =ROUND('① Hypothèses'!B71/12,0) -> 5417 | S21: =ROUND('① Hypothèses'!B71/12,0) -> 5417 | T21: =ROUND('① Hypothèses'!B71/12,0) -> 5417 | U21: =ROUND('① Hypothèses'!B71/12,0) -> 5417 | V21: =ROUND('① Hypothèses'!B71/12,0) -> 5417 | W21: =ROUND('① Hypothèses'!B71/12,0) -> 5417 | X21: =ROUND('① Hypothèses'!B71/12,0) -> 5417 | Y21: =ROUND('① Hypothèses'!B71/12,0) -> 5417 | Z21: =ROUND('① Hypothèses'!B71/12,0) -> 5417 | AA21: =ROUND('① Hypothèses'!B71/12,0) -> 5417 | AB21: =ROUND('① Hypothèses'!B71/12,0) -> 5417 | AC21: =SUM(Q21,R21,S21,T21,U21,V21,W21,X21,Y21,Z21,AA21,AB21) -> 65004 | AE21: =ROUND('① Hypothèses'!B71/12,0) -> 5417 | AF21: =ROUND('① Hypothèses'!B71/12,0) -> 5417 | AG21: =ROUND('① Hypothèses'!B71/12,0) -> 5417 | AH21: =ROUND('① Hypothèses'!B71/12,0) -> 5417 | AI21: =ROUND('① Hypothèses'!B71/12,0) -> 5417 | AJ21: =ROUND('① Hypothèses'!B71/12,0) -> 5417 | AK21: =ROUND('① Hypothèses'!B71/12,0) -> 5417 | AL21: =ROUND('① Hypothèses'!B71/12,0) -> 5417 | AM21: =ROUND('① Hypothèses'!B71/12,0) -> 5417 | AN21: =ROUND('① Hypothèses'!B71/12,0) -> 5417 | AO21: =ROUND('① Hypothèses'!B71/12,0) -> 5417 | AP21: =ROUND('① Hypothèses'!B71/12,0) -> 5417 | AQ21: =SUM(AE21,AF21,AG21,AH21,AI21,AJ21,AK21,AL21,AM21,AN21,AO21,AP21) -> 65004
A22: Autres charges externes | C22: =ROUND('① Hypothèses'!B72/12,0) -> 8333 | D22: =ROUND('① Hypothèses'!B72/12,0) -> 8333 | E22: =ROUND('① Hypothèses'!B72/12,0) -> 8333 | F22: =ROUND('① Hypothèses'!B72/12,0) -> 8333 | G22: =ROUND('① Hypothèses'!B72/12,0) -> 8333 | H22: =ROUND('① Hypothèses'!B72/12,0) -> 8333 | I22: =ROUND('① Hypothèses'!B72/12,0) -> 8333 | J22: =ROUND('① Hypothèses'!B72/12,0) -> 8333 | K22: =ROUND('① Hypothèses'!B72/12,0) -> 8333 | L22: =ROUND('① Hypothèses'!B72/12,0) -> 8333 | M22: =ROUND('① Hypothèses'!B72/12,0) -> 8333 | N22: =ROUND('① Hypothèses'!B72/12,0) -> 8333 | O22: =SUM(C22,D22,E22,F22,G22,H22,I22,J22,K22,L22,M22,N22) -> 99996 | Q22: =ROUND('① Hypothèses'!B72/12*(1+'① Hypothèses'!B55),0) -> 8500 | R22: =ROUND('① Hypothèses'!B72/12*(1+'① Hypothèses'!B55),0) -> 8500 | S22: =ROUND('① Hypothèses'!B72/12*(1+'① Hypothèses'!B55),0) -> 8500 | T22: =ROUND('① Hypothèses'!B72/12*(1+'① Hypothèses'!B55),0) -> 8500 | U22: =ROUND('① Hypothèses'!B72/12*(1+'① Hypothèses'!B55),0) -> 8500 | V22: =ROUND('① Hypothèses'!B72/12*(1+'① Hypothèses'!B55),0) -> 8500 | W22: =ROUND('① Hypothèses'!B72/12*(1+'① Hypothèses'!B55),0) -> 8500 | X22: =ROUND('① Hypothèses'!B72/12*(1+'① Hypothèses'!B55),0) -> 8500 | Y22: =ROUND('① Hypothèses'!B72/12*(1+'① Hypothèses'!B55),0) -> 8500 | Z22: =ROUND('① Hypothèses'!B72/12*(1+'① Hypothèses'!B55),0) -> 8500 | AA22: =ROUND('① Hypothèses'!B72/12*(1+'① Hypothèses'!B55),0) -> 8500 | AB22: =ROUND('① Hypothèses'!B72/12*(1+'① Hypothèses'!B55),0) -> 8500 | AC22: =SUM(Q22,R22,S22,T22,U22,V22,W22,X22,Y22,Z22,AA22,AB22) -> 102000 | AE22: =ROUND('① Hypothèses'!B72/12*(1+'① Hypothèses'!B55)^2,0) -> 8670 | AF22: =ROUND('① Hypothèses'!B72/12*(1+'① Hypothèses'!B55)^2,0) -> 8670 | AG22: =ROUND('① Hypothèses'!B72/12*(1+'① Hypothèses'!B55)^2,0) -> 8670 | AH22: =ROUND('① Hypothèses'!B72/12*(1+'① Hypothèses'!B55)^2,0) -> 8670 | AI22: =ROUND('① Hypothèses'!B72/12*(1+'① Hypothèses'!B55)^2,0) -> 8670 | AJ22: =ROUND('① Hypothèses'!B72/12*(1+'① Hypothèses'!B55)^2,0) -> 8670 | AK22: =ROUND('① Hypothèses'!B72/12*(1+'① Hypothèses'!B55)^2,0) -> 8670 | AL22: =ROUND('① Hypothèses'!B72/12*(1+'① Hypothèses'!B55)^2,0) -> 8670 | AM22: =ROUND('① Hypothèses'!B72/12*(1+'① Hypothèses'!B55)^2,0) -> 8670 | AN22: =ROUND('① Hypothèses'!B72/12*(1+'① Hypothèses'!B55)^2,0) -> 8670 | AO22: =ROUND('① Hypothèses'!B72/12*(1+'① Hypothèses'!B55)^2,0) -> 8670 | AP22: =ROUND('① Hypothèses'!B72/12*(1+'① Hypothèses'!B55)^2,0) -> 8670 | AQ22: =SUM(AE22,AF22,AG22,AH22,AI22,AJ22,AK22,AL22,AM22,AN22,AO22,AP22) -> 104040
A23: Impôts & taxes locaux | C23: =ROUND('① Hypothèses'!B73/12,0) -> 10000 | D23: =ROUND('① Hypothèses'!B73/12,0) -> 10000 | E23: =ROUND('① Hypothèses'!B73/12,0) -> 10000 | F23: =ROUND('① Hypothèses'!B73/12,0) -> 10000 | G23: =ROUND('① Hypothèses'!B73/12,0) -> 10000 | H23: =ROUND('① Hypothèses'!B73/12,0) -> 10000 | I23: =ROUND('① Hypothèses'!B73/12,0) -> 10000 | J23: =ROUND('① Hypothèses'!B73/12,0) -> 10000 | K23: =ROUND('① Hypothèses'!B73/12,0) -> 10000 | L23: =ROUND('① Hypothèses'!B73/12,0) -> 10000 | M23: =ROUND('① Hypothèses'!B73/12,0) -> 10000 | N23: =ROUND('① Hypothèses'!B73/12,0) -> 10000 | O23: =SUM(C23,D23,E23,F23,G23,H23,I23,J23,K23,L23,M23,N23) -> 120000 | Q23: =ROUND('① Hypothèses'!B73/12,0) -> 10000 | R23: =ROUND('① Hypothèses'!B73/12,0) -> 10000 | S23: =ROUND('① Hypothèses'!B73/12,0) -> 10000 | T23: =ROUND('① Hypothèses'!B73/12,0) -> 10000 | U23: =ROUND('① Hypothèses'!B73/12,0) -> 10000 | V23: =ROUND('① Hypothèses'!B73/12,0) -> 10000 | W23: =ROUND('① Hypothèses'!B73/12,0) -> 10000 | X23: =ROUND('① Hypothèses'!B73/12,0) -> 10000 | Y23: =ROUND('① Hypothèses'!B73/12,0) -> 10000 | Z23: =ROUND('① Hypothèses'!B73/12,0) -> 10000 | AA23: =ROUND('① Hypothèses'!B73/12,0) -> 10000 | AB23: =ROUND('① Hypothèses'!B73/12,0) -> 10000 | AC23: =SUM(Q23,R23,S23,T23,U23,V23,W23,X23,Y23,Z23,AA23,AB23) -> 120000 | AE23: =ROUND('① Hypothèses'!B73/12,0) -> 10000 | AF23: =ROUND('① Hypothèses'!B73/12,0) -> 10000 | AG23: =ROUND('① Hypothèses'!B73/12,0) -> 10000 | AH23: =ROUND('① Hypothèses'!B73/12,0) -> 10000 | AI23: =ROUND('① Hypothèses'!B73/12,0) -> 10000 | AJ23: =ROUND('① Hypothèses'!B73/12,0) -> 10000 | AK23: =ROUND('① Hypothèses'!B73/12,0) -> 10000 | AL23: =ROUND('① Hypothèses'!B73/12,0) -> 10000 | AM23: =ROUND('① Hypothèses'!B73/12,0) -> 10000 | AN23: =ROUND('① Hypothèses'!B73/12,0) -> 10000 | AO23: =ROUND('① Hypothèses'!B73/12,0) -> 10000 | AP23: =ROUND('① Hypothèses'!B73/12,0) -> 10000 | AQ23: =SUM(AE23,AF23,AG23,AH23,AI23,AJ23,AK23,AL23,AM23,AN23,AO23,AP23) -> 120000
A24: TOTAL CHARGES EXTERNES | C24: =C13+C14+C15+C16+C17+C18+C19+C20+C21+C22+C23 -> 106331 | D24: =D13+D14+D15+D16+D17+D18+D19+D20+D21+D22+D23 -> 104171 | E24: =E13+E14+E15+E16+E17+E18+E19+E20+E21+E22+E23 -> 116747 | F24: =F13+F14+F15+F16+F17+F18+F19+F20+F21+F22+F23 -> 121451 | G24: =G13+G14+G15+G16+G17+G18+G19+G20+G21+G22+G23 -> 125675 | H24: =H13+H14+H15+H16+H17+H18+H19+H20+H21+H22+H23 -> 145211 | I24: =I13+I14+I15+I16+I17+I18+I19+I20+I21+I22+I23 -> 158411 | J24: =J13+J14+J15+J16+J17+J18+J19+J20+J21+J22+J23 -> 158411 | ... N24: =N13+N14+N15+N16+N17+N18+N19+N20+N21+N22+N23 -> 122699 | O24: =SUM(C24,D24,E24,F24,G24,H24,I24,J24,K24,L24,M24,N24) -> 1577220 | Q24: =Q13+Q14+Q15+Q16+Q17+Q18+Q19+Q20+Q21+Q22+Q23 -> 115487 | R24: =R13+R14+R15+R16+R17+R18+R19+R20+R21+R22+R23 -> 112519 | S24: =S13+S14+S15+S16+S17+S18+S19+S20+S21+S22+S23 -> 118493 | T24: =T13+T14+T15+T16+T17+T18+T19+T20+T21+T22+T23 -> 123224 | U24: =U13+U14+U15+U16+U17+U18+U19+U20+U21+U22+U23 -> 127509 | V24: =V13+V14+V15+V16+V17+V18+V19+V20+V21+V22+V23 -> 147367 | W24: =W13+W14+W15+W16+W17+W18+W19+W20+W21+W22+W23 -> 159972 | X24: =X13+X14+X15+X16+X17+X18+X19+X20+X21+X22+X23 -> 159972 | ... AB24: =AB13+AB14+AB15+AB16+AB17+AB18+AB19+AB20+AB21+AB22+AB23 -> 124504 | AC24: =SUM(Q24,R24,S24,T24,U24,V24,W24,X24,Y24,Z24,AA24,AB24) -> 1612605 | AE24: =AE13+AE14+AE15+AE16+AE17+AE18+AE19+AE20+AE21+AE22+AE23 -> 117547 | AF24: =AF13+AF14+AF15+AF16+AF17+AF18+AF19+AF20+AF21+AF22+AF23 -> 114462 | AG24: =AG13+AG14+AG15+AG16+AG17+AG18+AG19+AG20+AG21+AG22+AG23 -> 120613 | AH24: =AH13+AH14+AH15+AH16+AH17+AH18+AH19+AH20+AH21+AH22+AH23 -> 125420 | AI24: =AI13+AI14+AI15+AI16+AI17+AI18+AI19+AI20+AI21+AI22+AI23 -> 129811 | AJ24: =AJ13+AJ14+AJ15+AJ16+AJ17+AJ18+AJ19+AJ20+AJ21+AJ22+AJ23 -> 150193 | AK24: =AK13+AK14+AK15+AK16+AK17+AK18+AK19+AK20+AK21+AK22+AK23 -> 162308 | AL24: =AL13+AL14+AL15+AL16+AL17+AL18+AL19+AL20+AL21+AL22+AL23 -> 162308 | ... AP24: =AP13+AP14+AP15+AP16+AP17+AP18+AP19+AP20+AP21+AP22+AP23 -> 126744 | AQ24: =SUM(AE24,AF24,AG24,AH24,AI24,AJ24,AK24,AL24,AM24,AN24,AO24,AP24) -> 1640207
A25: RÉMUNÉRATIONS & CHARGES SOCIALES
A26: Salaires bruts employés | C26: =ROUND(2*'① Hypothèses'!B79,0) -> 11000 | D26: =ROUND(2*'① Hypothèses'!B79,0) -> 11000 | E26: =ROUND(3*'① Hypothèses'!B79,0) -> 16500 | F26: =ROUND(3*'① Hypothèses'!B79,0) -> 16500 | G26: =ROUND('① Hypothèses'!B78*'① Hypothèses'!B79,0) -> 22000 | H26: =ROUND('① Hypothèses'!B78*'① Hypothèses'!B79,0) -> 22000 | I26: =ROUND('① Hypothèses'!B78*'① Hypothèses'!B79,0) -> 22000 | J26: =ROUND('① Hypothèses'!B78*'① Hypothèses'!B79,0) -> 22000 | K26: =ROUND('① Hypothèses'!B78*'① Hypothèses'!B79,0) -> 22000 | L26: =ROUND('① Hypothèses'!B78*'① Hypothèses'!B79,0) -> 22000 | M26: =ROUND('① Hypothèses'!B78*'① Hypothèses'!B79,0) -> 22000 | N26: =ROUND('① Hypothèses'!B78*'① Hypothèses'!B79,0) -> 22000 | O26: =SUM(C26,D26,E26,F26,G26,H26,I26,J26,K26,L26,M26,N26) -> 231000 | Q26: =ROUND('① Hypothèses'!B78*'① Hypothèses'!B79*(1+'① Hypothèses'!B56),0) -> 22440 | R26: =ROUND('① Hypothèses'!B78*'① Hypothèses'!B79*(1+'① Hypothèses'!B56),0) -> 22440 | S26: =ROUND('① Hypothèses'!B78*'① Hypothèses'!B79*(1+'① Hypothèses'!B56),0) -> 22440 | T26: =ROUND('① Hypothèses'!B78*'① Hypothèses'!B79*(1+'① Hypothèses'!B56),0) -> 22440 | U26: =ROUND('① Hypothèses'!B78*'① Hypothèses'!B79*(1+'① Hypothèses'!B56),0) -> 22440 | V26: =ROUND('① Hypothèses'!B78*'① Hypothèses'!B79*(1+'① Hypothèses'!B56),0) -> 22440 | W26: =ROUND('① Hypothèses'!B78*'① Hypothèses'!B79*(1+'① Hypothèses'!B56),0) -> 22440 | X26: =ROUND('① Hypothèses'!B78*'① Hypothèses'!B79*(1+'① Hypothèses'!B56),0) -> 22440 | Y26: =ROUND('① Hypothèses'!B78*'① Hypothèses'!B79*(1+'① Hypothèses'!B56),0) -> 22440 | Z26: =ROUND('① Hypothèses'!B78*'① Hypothèses'!B79*(1+'① Hypothèses'!B56),0) -> 22440 | AA26: =ROUND('① Hypothèses'!B78*'① Hypothèses'!B79*(1+'① Hypothèses'!B56),0) -> 22440 | AB26: =ROUND('① Hypothèses'!B78*'① Hypothèses'!B79*(1+'① Hypothèses'!B56),0) -> 22440 | AC26: =SUM(Q26,R26,S26,T26,U26,V26,W26,X26,Y26,Z26,AA26,AB26) -> 269280 | AE26: =ROUND('① Hypothèses'!B78*'① Hypothèses'!B79*(1+'① Hypothèses'!B56)^2,0) -> 22889 | AF26: =ROUND('① Hypothèses'!B78*'① Hypothèses'!B79*(1+'① Hypothèses'!B56)^2,0) -> 22889 | AG26: =ROUND('① Hypothèses'!B78*'① Hypothèses'!B79*(1+'① Hypothèses'!B56)^2,0) -> 22889 | AH26: =ROUND('① Hypothèses'!B78*'① Hypothèses'!B79*(1+'① Hypothèses'!B56)^2,0) -> 22889 | AI26: =ROUND('① Hypothèses'!B78*'① Hypothèses'!B79*(1+'① Hypothèses'!B56)^2,0) -> 22889 | AJ26: =ROUND('① Hypothèses'!B78*'① Hypothèses'!B79*(1+'① Hypothèses'!B56)^2,0) -> 22889 | AK26: =ROUND('① Hypothèses'!B78*'① Hypothèses'!B79*(1+'① Hypothèses'!B56)^2,0) -> 22889 | AL26: =ROUND('① Hypothèses'!B78*'① Hypothèses'!B79*(1+'① Hypothèses'!B56)^2,0) -> 22889 | AM26: =ROUND('① Hypothèses'!B78*'① Hypothèses'!B79*(1+'① Hypothèses'!B56)^2,0) -> 22889 | AN26: =ROUND('① Hypothèses'!B78*'① Hypothèses'!B79*(1+'① Hypothèses'!B56)^2,0) -> 22889 | AO26: =ROUND('① Hypothèses'!B78*'① Hypothèses'!B79*(1+'① Hypothèses'!B56)^2,0) -> 22889 | AP26: =ROUND('① Hypothèses'!B78*'① Hypothèses'!B79*(1+'① Hypothèses'!B56)^2,0) -> 22889 | AQ26: =SUM(AE26,AF26,AG26,AH26,AI26,AJ26,AK26,AL26,AM26,AN26,AO26,AP26) -> 274668
A27: Charges sociales employés | C27: =ROUND(C26*'① Hypothèses'!B80,0) -> 2970 | D27: =ROUND(D26*'① Hypothèses'!B80,0) -> 2970 | E27: =ROUND(E26*'① Hypothèses'!B80,0) -> 4455 | F27: =ROUND(F26*'① Hypothèses'!B80,0) -> 4455 | G27: =ROUND(G26*'① Hypothèses'!B80,0) -> 5940 | H27: =ROUND(H26*'① Hypothèses'!B80,0) -> 5940 | I27: =ROUND(I26*'① Hypothèses'!B80,0) -> 5940 | J27: =ROUND(J26*'① Hypothèses'!B80,0) -> 5940 | K27: =ROUND(K26*'① Hypothèses'!B80,0) -> 5940 | L27: =ROUND(L26*'① Hypothèses'!B80,0) -> 5940 | M27: =ROUND(M26*'① Hypothèses'!B80,0) -> 5940 | N27: =ROUND(N26*'① Hypothèses'!B80,0) -> 5940 | O27: =SUM(C27,D27,E27,F27,G27,H27,I27,J27,K27,L27,M27,N27) -> 62370 | Q27: =ROUND(Q26*'① Hypothèses'!B80,0) -> 6059 | R27: =ROUND(R26*'① Hypothèses'!B80,0) -> 6059 | S27: =ROUND(S26*'① Hypothèses'!B80,0) -> 6059 | T27: =ROUND(T26*'① Hypothèses'!B80,0) -> 6059 | U27: =ROUND(U26*'① Hypothèses'!B80,0) -> 6059 | V27: =ROUND(V26*'① Hypothèses'!B80,0) -> 6059 | W27: =ROUND(W26*'① Hypothèses'!B80,0) -> 6059 | X27: =ROUND(X26*'① Hypothèses'!B80,0) -> 6059 | Y27: =ROUND(Y26*'① Hypothèses'!B80,0) -> 6059 | Z27: =ROUND(Z26*'① Hypothèses'!B80,0) -> 6059 | AA27: =ROUND(AA26*'① Hypothèses'!B80,0) -> 6059 | AB27: =ROUND(AB26*'① Hypothèses'!B80,0) -> 6059 | AC27: =SUM(Q27,R27,S27,T27,U27,V27,W27,X27,Y27,Z27,AA27,AB27) -> 72708 | AE27: =ROUND(AE26*'① Hypothèses'!B80,0) -> 6180 | AF27: =ROUND(AF26*'① Hypothèses'!B80,0) -> 6180 | AG27: =ROUND(AG26*'① Hypothèses'!B80,0) -> 6180 | AH27: =ROUND(AH26*'① Hypothèses'!B80,0) -> 6180 | AI27: =ROUND(AI26*'① Hypothèses'!B80,0) -> 6180 | AJ27: =ROUND(AJ26*'① Hypothèses'!B80,0) -> 6180 | AK27: =ROUND(AK26*'① Hypothèses'!B80,0) -> 6180 | AL27: =ROUND(AL26*'① Hypothèses'!B80,0) -> 6180 | AM27: =ROUND(AM26*'① Hypothèses'!B80,0) -> 6180 | AN27: =ROUND(AN26*'① Hypothèses'!B80,0) -> 6180 | AO27: =ROUND(AO26*'① Hypothèses'!B80,0) -> 6180 | AP27: =ROUND(AP26*'① Hypothèses'!B80,0) -> 6180 | AQ27: =SUM(AE27,AF27,AG27,AH27,AI27,AJ27,AK27,AL27,AM27,AN27,AO27,AP27) -> 74160
A28: Rémunération gérant | G28: =ROUND('① Hypothèses'!B76,0) -> 8000 | H28: =ROUND('① Hypothèses'!B76,0) -> 8000 | I28: =ROUND('① Hypothèses'!B76,0) -> 8000 | J28: =ROUND('① Hypothèses'!B76,0) -> 8000 | K28: =ROUND('① Hypothèses'!B76,0) -> 8000 | L28: =ROUND('① Hypothèses'!B76,0) -> 8000 | M28: =ROUND('① Hypothèses'!B76,0) -> 8000 | N28: =ROUND('① Hypothèses'!B76,0) -> 8000 | O28: =SUM(C28,D28,E28,F28,G28,H28,I28,J28,K28,L28,M28,N28) -> 64000 | Q28: =ROUND('① Hypothèses'!B76*(1+'① Hypothèses'!B56),0) -> 8160 | R28: =ROUND('① Hypothèses'!B76*(1+'① Hypothèses'!B56),0) -> 8160 | S28: =ROUND('① Hypothèses'!B76*(1+'① Hypothèses'!B56),0) -> 8160 | T28: =ROUND('① Hypothèses'!B76*(1+'① Hypothèses'!B56),0) -> 8160 | U28: =ROUND('① Hypothèses'!B76*(1+'① Hypothèses'!B56),0) -> 8160 | V28: =ROUND('① Hypothèses'!B76*(1+'① Hypothèses'!B56),0) -> 8160 | W28: =ROUND('① Hypothèses'!B76*(1+'① Hypothèses'!B56),0) -> 8160 | X28: =ROUND('① Hypothèses'!B76*(1+'① Hypothèses'!B56),0) -> 8160 | Y28: =ROUND('① Hypothèses'!B76*(1+'① Hypothèses'!B56),0) -> 8160 | Z28: =ROUND('① Hypothèses'!B76*(1+'① Hypothèses'!B56),0) -> 8160 | AA28: =ROUND('① Hypothèses'!B76*(1+'① Hypothèses'!B56),0) -> 8160 | AB28: =ROUND('① Hypothèses'!B76*(1+'① Hypothèses'!B56),0) -> 8160 | AC28: =SUM(Q28,R28,S28,T28,U28,V28,W28,X28,Y28,Z28,AA28,AB28) -> 97920 | AE28: =ROUND('① Hypothèses'!B76*(1+'① Hypothèses'!B56)^2,0) -> 8323 | AF28: =ROUND('① Hypothèses'!B76*(1+'① Hypothèses'!B56)^2,0) -> 8323 | AG28: =ROUND('① Hypothèses'!B76*(1+'① Hypothèses'!B56)^2,0) -> 8323 | AH28: =ROUND('① Hypothèses'!B76*(1+'① Hypothèses'!B56)^2,0) -> 8323 | AI28: =ROUND('① Hypothèses'!B76*(1+'① Hypothèses'!B56)^2,0) -> 8323 | AJ28: =ROUND('① Hypothèses'!B76*(1+'① Hypothèses'!B56)^2,0) -> 8323 | AK28: =ROUND('① Hypothèses'!B76*(1+'① Hypothèses'!B56)^2,0) -> 8323 | AL28: =ROUND('① Hypothèses'!B76*(1+'① Hypothèses'!B56)^2,0) -> 8323 | AM28: =ROUND('① Hypothèses'!B76*(1+'① Hypothèses'!B56)^2,0) -> 8323 | AN28: =ROUND('① Hypothèses'!B76*(1+'① Hypothèses'!B56)^2,0) -> 8323 | AO28: =ROUND('① Hypothèses'!B76*(1+'① Hypothèses'!B56)^2,0) -> 8323 | AP28: =ROUND('① Hypothèses'!B76*(1+'① Hypothèses'!B56)^2,0) -> 8323 | AQ28: =SUM(AE28,AF28,AG28,AH28,AI28,AJ28,AK28,AL28,AM28,AN28,AO28,AP28) -> 99876
A29: Charges sociales gérant | C29: =ROUND(C28*'① Hypothèses'!B77,0) -> 0 | D29: =ROUND(D28*'① Hypothèses'!B77,0) -> 0 | E29: =ROUND(E28*'① Hypothèses'!B77,0) -> 0 | F29: =ROUND(F28*'① Hypothèses'!B77,0) -> 0 | G29: =ROUND(G28*'① Hypothèses'!B77,0) -> 2160 | H29: =ROUND(H28*'① Hypothèses'!B77,0) -> 2160 | I29: =ROUND(I28*'① Hypothèses'!B77,0) -> 2160 | J29: =ROUND(J28*'① Hypothèses'!B77,0) -> 2160 | K29: =ROUND(K28*'① Hypothèses'!B77,0) -> 2160 | L29: =ROUND(L28*'① Hypothèses'!B77,0) -> 2160 | M29: =ROUND(M28*'① Hypothèses'!B77,0) -> 2160 | N29: =ROUND(N28*'① Hypothèses'!B77,0) -> 2160 | O29: =SUM(C29,D29,E29,F29,G29,H29,I29,J29,K29,L29,M29,N29) -> 17280 | Q29: =ROUND(Q28*'① Hypothèses'!B77,0) -> 2203 | R29: =ROUND(R28*'① Hypothèses'!B77,0) -> 2203 | S29: =ROUND(S28*'① Hypothèses'!B77,0) -> 2203 | T29: =ROUND(T28*'① Hypothèses'!B77,0) -> 2203 | U29: =ROUND(U28*'① Hypothèses'!B77,0) -> 2203 | V29: =ROUND(V28*'① Hypothèses'!B77,0) -> 2203 | W29: =ROUND(W28*'① Hypothèses'!B77,0) -> 2203 | X29: =ROUND(X28*'① Hypothèses'!B77,0) -> 2203 | Y29: =ROUND(Y28*'① Hypothèses'!B77,0) -> 2203 | Z29: =ROUND(Z28*'① Hypothèses'!B77,0) -> 2203 | AA29: =ROUND(AA28*'① Hypothèses'!B77,0) -> 2203 | AB29: =ROUND(AB28*'① Hypothèses'!B77,0) -> 2203 | AC29: =SUM(Q29,R29,S29,T29,U29,V29,W29,X29,Y29,Z29,AA29,AB29) -> 26436 | AE29: =ROUND(AE28*'① Hypothèses'!B77,0) -> 2247 | AF29: =ROUND(AF28*'① Hypothèses'!B77,0) -> 2247 | AG29: =ROUND(AG28*'① Hypothèses'!B77,0) -> 2247 | AH29: =ROUND(AH28*'① Hypothèses'!B77,0) -> 2247 | AI29: =ROUND(AI28*'① Hypothèses'!B77,0) -> 2247 | AJ29: =ROUND(AJ28*'① Hypothèses'!B77,0) -> 2247 | AK29: =ROUND(AK28*'① Hypothèses'!B77,0) -> 2247 | AL29: =ROUND(AL28*'① Hypothèses'!B77,0) -> 2247 | AM29: =ROUND(AM28*'① Hypothèses'!B77,0) -> 2247 | AN29: =ROUND(AN28*'① Hypothèses'!B77,0) -> 2247 | AO29: =ROUND(AO28*'① Hypothèses'!B77,0) -> 2247 | AP29: =ROUND(AP28*'① Hypothèses'!B77,0) -> 2247 | AQ29: =SUM(AE29,AF29,AG29,AH29,AI29,AJ29,AK29,AL29,AM29,AN29,AO29,AP29) -> 26964
A30: TOTAL RÉMUNÉRATIONS | C30: =C26+C27+C28+C29 -> 13970 | D30: =D26+D27+D28+D29 -> 13970 | E30: =E26+E27+E28+E29 -> 20955 | F30: =F26+F27+F28+F29 -> 20955 | G30: =G26+G27+G28+G29 -> 38100 | H30: =H26+H27+H28+H29 -> 38100 | I30: =I26+I27+I28+I29 -> 38100 | J30: =J26+J27+J28+J29 -> 38100 | ... N30: =N26+N27+N28+N29 -> 38100 | O30: =SUM(C30,D30,E30,F30,G30,H30,I30,J30,K30,L30,M30,N30) -> 374650 | Q30: =Q26+Q27+Q28+Q29 -> 38862 | R30: =R26+R27+R28+R29 -> 38862 | S30: =S26+S27+S28+S29 -> 38862 | T30: =T26+T27+T28+T29 -> 38862 | U30: =U26+U27+U28+U29 -> 38862 | V30: =V26+V27+V28+V29 -> 38862 | W30: =W26+W27+W28+W29 -> 38862 | X30: =X26+X27+X28+X29 -> 38862 | ... AB30: =AB26+AB27+AB28+AB29 -> 38862 | AC30: =SUM(Q30,R30,S30,T30,U30,V30,W30,X30,Y30,Z30,AA30,AB30) -> 466344 | AE30: =AE26+AE27+AE28+AE29 -> 39639 | AF30: =AF26+AF27+AF28+AF29 -> 39639 | AG30: =AG26+AG27+AG28+AG29 -> 39639 | AH30: =AH26+AH27+AH28+AH29 -> 39639 | AI30: =AI26+AI27+AI28+AI29 -> 39639 | AJ30: =AJ26+AJ27+AJ28+AJ29 -> 39639 | AK30: =AK26+AK27+AK28+AK29 -> 39639 | AL30: =AL26+AL27+AL28+AL29 -> 39639 | ... AP30: =AP26+AP27+AP28+AP29 -> 39639 | AQ30: =SUM(AE30,AF30,AG30,AH30,AI30,AJ30,AK30,AL30,AM30,AN30,AO30,AP30) -> 475668
A31: DOTATIONS AUX AMORTISSEMENTS
A32: Dotations aux amortissements SARL | C32: =ROUND('① Hypothèses'!B97/12,0) -> 4891 | D32: =ROUND('① Hypothèses'!B97/12,0) -> 4891 | E32: =ROUND('① Hypothèses'!B97/12,0) -> 4891 | F32: =ROUND('① Hypothèses'!B97/12,0) -> 4891 | G32: =ROUND('① Hypothèses'!B97/12,0) -> 4891 | H32: =ROUND('① Hypothèses'!B97/12,0) -> 4891 | I32: =ROUND('① Hypothèses'!B97/12,0) -> 4891 | J32: =ROUND('① Hypothèses'!B97/12,0) -> 4891 | K32: =ROUND('① Hypothèses'!B97/12,0) -> 4891 | L32: =ROUND('① Hypothèses'!B97/12,0) -> 4891 | M32: =ROUND('① Hypothèses'!B97/12,0) -> 4891 | N32: =ROUND('① Hypothèses'!B97/12,0) -> 4891 | O32: =SUM(C32,D32,E32,F32,G32,H32,I32,J32,K32,L32,M32,N32) -> 58692 | Q32: =ROUND('① Hypothèses'!B97/12,0) -> 4891 | R32: =ROUND('① Hypothèses'!B97/12,0) -> 4891 | S32: =ROUND('① Hypothèses'!B97/12,0) -> 4891 | T32: =ROUND('① Hypothèses'!B97/12,0) -> 4891 | U32: =ROUND('① Hypothèses'!B97/12,0) -> 4891 | V32: =ROUND('① Hypothèses'!B97/12,0) -> 4891 | W32: =ROUND('① Hypothèses'!B97/12,0) -> 4891 | X32: =ROUND('① Hypothèses'!B97/12,0) -> 4891 | Y32: =ROUND('① Hypothèses'!B97/12,0) -> 4891 | Z32: =ROUND('① Hypothèses'!B97/12,0) -> 4891 | AA32: =ROUND('① Hypothèses'!B97/12,0) -> 4891 | AB32: =ROUND('① Hypothèses'!B97/12,0) -> 4891 | AC32: =SUM(Q32,R32,S32,T32,U32,V32,W32,X32,Y32,Z32,AA32,AB32) -> 58692 | AE32: =ROUND('① Hypothèses'!B97/12,0) -> 4891 | AF32: =ROUND('① Hypothèses'!B97/12,0) -> 4891 | AG32: =ROUND('① Hypothèses'!B97/12,0) -> 4891 | AH32: =ROUND('① Hypothèses'!B97/12,0) -> 4891 | AI32: =ROUND('① Hypothèses'!B97/12,0) -> 4891 | AJ32: =ROUND('① Hypothèses'!B97/12,0) -> 4891 | AK32: =ROUND('① Hypothèses'!B97/12,0) -> 4891 | AL32: =ROUND('① Hypothèses'!B97/12,0) -> 4891 | AM32: =ROUND('① Hypothèses'!B97/12,0) -> 4891 | AN32: =ROUND('① Hypothèses'!B97/12,0) -> 4891 | AO32: =ROUND('① Hypothèses'!B97/12,0) -> 4891 | AP32: =ROUND('① Hypothèses'!B97/12,0) -> 4891 | AQ32: =SUM(AE32,AF32,AG32,AH32,AI32,AJ32,AK32,AL32,AM32,AN32,AO32,AP32) -> 58692
A33: RÉSULTATS
A34: MARGE BRUTE | C34: =C11-C13-C14-C15 -> 72679 | D34: =D11-D13-D14 -> 90720 | E34: =E11-E13-E14 -> 147312 | F34: =F11-F13-F14 -> 168480 | G34: =G11-G13-G14 -> 187488 | H34: =H11-H13-H14 -> 275400 | I34: =I11-I13-I14 -> 334800 | J34: =J11-J13-J14 -> 334800 | K34: =K11-K13-K14 -> 324000 | ... N34: =N11-N13-N14 -> 174096 | O34: =SUM(C34,D34,E34,F34,G34,H34,I34,J34,K34,L34,M34,N34) -> 2533135 | Q34: =Q11-Q13-Q14 -> 176287 | R34: =R11-R13-R14 -> 159229 | S34: =S11-S13-S14 -> 193570 | T34: =T11-T13-T14 -> 220778 | U34: =U11-U13-U14 -> 245421 | V34: =V11-V13-V14 -> 359601 | W34: =W11-W13-W14 -> 432078 | X34: =X11-X13-X14 -> 432078 | ... AB34: =AB11-AB13-AB14 -> 228137 | AC34: =SUM(Q34,R34,S34,T34,U34,V34,W34,X34,Y34,Z34,AA34,AB34) -> 3419355 | AE34: =AE11-AE13-AE14 -> 183341 | AF34: =AF11-AF13-AF14 -> 165597 | AG34: =AG11-AG13-AG14 -> 200969 | AH34: =AH11-AH13-AH14 -> 228605 | AI34: =AI11-AI13-AI14 -> 253853 | AJ34: =AJ11-AJ13-AJ14 -> 371059 | AK34: =AK11-AK13-AK14 -> 440719 | AL34: =AL11-AL13-AL14 -> 440719 | ... AP34: =AP11-AP13-AP14 -> 236226 | AQ34: =SUM(AE34,AF34,AG34,AH34,AI34,AJ34,AK34,AL34,AM34,AN34,AO34,AP34) -> 3520526
A35: EXCÉDENT BRUT D'EXPLOITATION (EBE) | C35: =C11-C24-C30 -> 2459 | D35: =D11-D24-D30 -> -7261 | E35: =E11-E24-E30 -> 42346 | F35: =F11-F24-F30 -> 63514 | G35: =G11-G24-G30 -> 65377 | H35: =H11-H24-H30 -> 153289 | I35: =I11-I24-I30 -> 212689 | J35: =J11-J24-J30 -> 212689 | ... N35: =N11-N24-N30 -> 51985 | O35: =SUM(C35,D35,E35,F35,G35,H35,I35,J35,K35,L35,M35,N35) -> 1178114 | Q35: =Q11-Q24-Q30 -> 52597 | R35: =R11-R24-R30 -> 35539 | S35: =S11-S24-S30 -> 69880 | T35: =T11-T24-T30 -> 97088 | U35: =U11-U24-U30 -> 121731 | V35: =V11-V24-V30 -> 235911 | W35: =W11-W24-W30 -> 308388 | X35: =X11-X24-X30 -> 308388 | ... AB35: =AB11-AB24-AB30 -> 104447 | AC35: =SUM(Q35,R35,S35,T35,U35,V35,W35,X35,Y35,Z35,AA35,AB35) -> 1935075 | AE35: =AE11-AE24-AE30 -> 58040 | AF35: =AF11-AF24-AF30 -> 40296 | AG35: =AG11-AG24-AG30 -> 75668 | AH35: =AH11-AH24-AH30 -> 103304 | AI35: =AI11-AI24-AI30 -> 128552 | AJ35: =AJ11-AJ24-AJ30 -> 245758 | AK35: =AK11-AK24-AK30 -> 315418 | AL35: =AL11-AL24-AL30 -> 315418 | ... AP35: =AP11-AP24-AP30 -> 110925 | AQ35: =SUM(AE35,AF35,AG35,AH35,AI35,AJ35,AK35,AL35,AM35,AN35,AO35,AP35) -> 2016914
A36: RÉSULTAT D'EXPLOITATION (REX) | C36: =C35-C32 -> -2432 | D36: =D35-D32 -> -12152 | E36: =E35-E32 -> 37455 | F36: =F35-F32 -> 58623 | G36: =G35-G32 -> 60486 | H36: =H35-H32 -> 148398 | I36: =I35-I32 -> 207798 | J36: =J35-J32 -> 207798 | ... N36: =N35-N32 -> 47094 | O36: =SUM(C36,D36,E36,F36,G36,H36,I36,J36,K36,L36,M36,N36) -> 1119422 | Q36: =Q35-Q32 -> 47706 | R36: =R35-R32 -> 30648 | S36: =S35-S32 -> 64989 | T36: =T35-T32 -> 92197 | U36: =U35-U32 -> 116840 | V36: =V35-V32 -> 231020 | W36: =W35-W32 -> 303497 | X36: =X35-X32 -> 303497 | ... AB36: =AB35-AB32 -> 99556 | AC36: =SUM(Q36,R36,S36,T36,U36,V36,W36,X36,Y36,Z36,AA36,AB36) -> 1876383 | AE36: =AE35-AE32 -> 53149 | AF36: =AF35-AF32 -> 35405 | AG36: =AG35-AG32 -> 70777 | AH36: =AH35-AH32 -> 98413 | AI36: =AI35-AI32 -> 123661 | AJ36: =AJ35-AJ32 -> 240867 | AK36: =AK35-AK32 -> 310527 | AL36: =AL35-AL32 -> 310527 | ... AP36: =AP35-AP32 -> 106034 | AQ36: =SUM(AE36,AF36,AG36,AH36,AI36,AJ36,AK36,AL36,AM36,AN36,AO36,AP36) -> 1958222
A37: RÉSULTAT NET (exonération IS 5 ans) | C37: =C11-C24-C30-C32 -> -2432 | D37: =D11-D24-D30-D32 -> -12152 | E37: =E11-E24-E30-E32 -> 37455 | F37: =F11-F24-F30-F32 -> 58623 | G37: =G11-G24-G30-G32 -> 60486 | H37: =H11-H24-H30-H32 -> 148398 | I37: =I11-I24-I30-I32 -> 207798 | J37: =J11-J24-J30-J32 -> 207798 | ... N37: =N11-N24-N30-N32 -> 47094 | O37: =SUM(C37,D37,E37,F37,G37,H37,I37,J37,K37,L37,M37,N37) -> 1119422 | Q37: =Q11-Q24-Q30-Q32 -> 47706 | R37: =R11-R24-R30-R32 -> 30648 | S37: =S11-S24-S30-S32 -> 64989 | T37: =T11-T24-T30-T32 -> 92197 | U37: =U11-U24-U30-U32 -> 116840 | V37: =V11-V24-V30-V32 -> 231020 | W37: =W11-W24-W30-W32 -> 303497 | X37: =X11-X24-X30-X32 -> 303497 | ... AB37: =AB11-AB24-AB30-AB32 -> 99556 | AC37: =SUM(Q37,R37,S37,T37,U37,V37,W37,X37,Y37,Z37,AA37,AB37) -> 1876383 | AE37: =AE36 -> 53149 | AF37: =AF36 -> 35405 | AG37: =AG36 -> 70777 | AH37: =AH36 -> 98413 | AI37: =AI36 -> 123661 | AJ37: =AJ36 -> 240867 | AK37: =AK36 -> 310527 | AL37: =AL36 -> 310527 | ... AP37: =AP36 -> 106034 | AQ37: =SUM(AE37,AF37,AG37,AH37,AI37,AJ37,AK37,AL37,AM37,AN37,AO37,AP37) -> 1958222
A38: ⚠ Exonération IS Maroc applicable pendant 5 ans pour la partie du CA en devises = pour ce cas intégralité du CA en devises étrangères donc pas d'IS

Sheet ④ Exploitation Trésorerie
A1: BUDGET PRÉVISIONNEL DE TRÉSORERIE EXPLOITATION SARL RIAD DU MEMOIRE (MAD HT)
A2: Les flux d'encaissement sont basés sur les CA du CR | Le loyer Holding est décaissé chaque mois | Mois 1 An1 : apport initial + investissements
C3: ANNÉE 1 2026 | Q3: ANNÉE 2 2027 | AE3: ANNÉE 3 2028
A4: LIBELLÉS | C4: Jan | D4: Fév | E4: Mar | F4: Avr | G4: Mai | H4: Juin | I4: Juil | J4: Août | K4: Sep | L4: Oct | M4: Nov | N4: Déc | O4: TOTAL | Q4: Jan | R4: Fév | S4: Mar | T4: Avr | U4: Mai | V4: Juin | W4: Juil | X4: Août | Y4: Sep | Z4: Oct | AA4: Nov | AB4: Déc | AC4: TOTAL | AE4: Jan | AF4: Fév | AG4: Mar | AH4: Avr | AI4: Mai | AJ4: Juin | AK4: Juil | AL4: Août | AM4: Sep | AN4: Oct | AO4: Nov | AP4: Déc | AQ4: TOTAL
A5: ENCAISSEMENTS
A6: Apport initial SARL + investissements (Mois 1) | C6: ='① Hypothèses'!B89+'① Hypothèses'!B88 -> 100000 | D6: 0 | E6: 0 | F6: 0 | G6: 0 | H6: 0 | I6: 0 | J6: 0 | K6: 0 | L6: 0 | M6: 0 | N6: 0 | O6: =SUM(C6,D6,E6,F6,G6,H6,I6,J6,K6,L6,M6,N6) -> 100000 | Q6: 0 | R6: 0 | S6: 0 | T6: 0 | U6: 0 | V6: 0 | W6: 0 | X6: 0 | Y6: 0 | Z6: 0 | AA6: 0 | AB6: 0 | AC6: =SUM(Q6,R6,S6,T6,U6,V6,W6,X6,Y6,Z6,AA6,AB6) -> 0 | AE6: 0 | AF6: 0 | AG6: 0 | AH6: 0 | AI6: 0 | AJ6: 0 | AK6: 0 | AL6: 0 | AM6: 0 | AN6: 0 | AO6: 0 | AP6: 0 | AQ6: =SUM(AE6,AF6,AG6,AH6,AI6,AJ6,AK6,AL6,AM6,AN6,AO6,AP6) -> 0
A7: Recettes hébergement | C7: ='③ Exploitation CR'!C6 -> 111600 | D7: ='③ Exploitation CR'!D6 -> 100800 | E7: ='③ Exploitation CR'!E6 -> 163680 | F7: ='③ Exploitation CR'!F6 -> 187200 | G7: ='③ Exploitation CR'!G6 -> 208320 | H7: ='③ Exploitation CR'!H6 -> 306000 | I7: ='③ Exploitation CR'!I6 -> 372000 | J7: ='③ Exploitation CR'!J6 -> 372000 | ... N7: ='③ Exploitation CR'!N6 -> 193440 | O7: =SUM(C7,D7,E7,F7,G7,H7,I7,J7,K7,L7,M7,N7) -> 2845440 | Q7: ='③ Exploitation CR'!Q6 -> 153294 | R7: ='③ Exploitation CR'!R6 -> 138459 | S7: ='③ Exploitation CR'!S6 -> 168323 | T7: ='③ Exploitation CR'!T6 -> 191981 | U7: ='③ Exploitation CR'!U6 -> 213409 | V7: ='③ Exploitation CR'!V6 -> 312696 | W7: ='③ Exploitation CR'!W6 -> 375720 | X7: ='③ Exploitation CR'!X6 -> 375720 | ... AB7: ='③ Exploitation CR'!AB6 -> 198380 | AC7: =SUM(Q7,R7,S7,T7,U7,V7,W7,X7,Y7,Z7,AA7,AB7) -> 2973352 | AE7: ='③ Exploitation CR'!AE6 -> 159426 | AF7: ='③ Exploitation CR'!AF6 -> 143997 | AG7: ='③ Exploitation CR'!AG6 -> 174755 | AH7: ='③ Exploitation CR'!AH6 -> 198787 | AI7: ='③ Exploitation CR'!AI6 -> 220743 | AJ7: ='③ Exploitation CR'!AJ6 -> 322659 | AK7: ='③ Exploitation CR'!AK6 -> 383234 | AL7: ='③ Exploitation CR'!AL6 -> 383234 | ... AP7: ='③ Exploitation CR'!AP6 -> 205414 | AQ7: =SUM(AE7,AF7,AG7,AH7,AI7,AJ7,AK7,AL7,AM7,AN7,AO7,AP7) -> 3061326
A8: Recettes restauration | C8: ='③ Exploitation CR'!C7 -> 11160 | D8: ='③ Exploitation CR'!D7 -> 10080 | E8: ='③ Exploitation CR'!E7 -> 16368 | F8: ='③ Exploitation CR'!F7 -> 18720 | G8: ='③ Exploitation CR'!G7 -> 20832 | H8: ='③ Exploitation CR'!H7 -> 30600 | I8: ='③ Exploitation CR'!I7 -> 37200 | J8: ='③ Exploitation CR'!J7 -> 37200 | ... N8: ='③ Exploitation CR'!N7 -> 19344 | O8: =SUM(C8,D8,E8,F8,G8,H8,I8,J8,K8,L8,M8,N8) -> 284544 | Q8: ='③ Exploitation CR'!Q7 -> 15329 | R8: ='③ Exploitation CR'!R7 -> 13846 | S8: ='③ Exploitation CR'!S7 -> 16832 | T8: ='③ Exploitation CR'!T7 -> 19198 | U8: ='③ Exploitation CR'!U7 -> 21341 | V8: ='③ Exploitation CR'!V7 -> 31270 | W8: ='③ Exploitation CR'!W7 -> 37572 | X8: ='③ Exploitation CR'!X7 -> 37572 | ... AB8: ='③ Exploitation CR'!AB7 -> 19838 | AC8: =SUM(Q8,R8,S8,T8,U8,V8,W8,X8,Y8,Z8,AA8,AB8) -> 297335 | AE8: ='③ Exploitation CR'!AE7 -> 15943 | AF8: ='③ Exploitation CR'!AF7 -> 14400 | AG8: ='③ Exploitation CR'!AG7 -> 17476 | AH8: ='③ Exploitation CR'!AH7 -> 19879 | AI8: ='③ Exploitation CR'!AI7 -> 22074 | AJ8: ='③ Exploitation CR'!AJ7 -> 32266 | AK8: ='③ Exploitation CR'!AK7 -> 38323 | AL8: ='③ Exploitation CR'!AL7 -> 38323 | ... AP8: ='③ Exploitation CR'!AP7 -> 20541 | AQ8: =SUM(AE8,AF8,AG8,AH8,AI8,AJ8,AK8,AL8,AM8,AN8,AO8,AP8) -> 306132
A9: Recettes spa & hammam | C9: ='③ Exploitation CR'!C8 -> 0 | D9: ='③ Exploitation CR'!D8 -> 0 | E9: ='③ Exploitation CR'!E8 -> 0 | F9: ='③ Exploitation CR'!F8 -> 0 | G9: ='③ Exploitation CR'!G8 -> 0 | H9: ='③ Exploitation CR'!H8 -> 0 | I9: ='③ Exploitation CR'!I8 -> 0 | J9: ='③ Exploitation CR'!J8 -> 0 | ... N9: ='③ Exploitation CR'!N8 -> 0 | O9: =SUM(C9,D9,E9,F9,G9,H9,I9,J9,K9,L9,M9,N9) -> 0 | Q9: ='③ Exploitation CR'!Q8 -> 15329 | R9: ='③ Exploitation CR'!R8 -> 13846 | S9: ='③ Exploitation CR'!S8 -> 16832 | T9: ='③ Exploitation CR'!T8 -> 19198 | U9: ='③ Exploitation CR'!U8 -> 21341 | V9: ='③ Exploitation CR'!V8 -> 31270 | W9: ='③ Exploitation CR'!W8 -> 37572 | X9: ='③ Exploitation CR'!X8 -> 37572 | ... AB9: ='③ Exploitation CR'!AB8 -> 19838 | AC9: =SUM(Q9,R9,S9,T9,U9,V9,W9,X9,Y9,Z9,AA9,AB9) -> 297335 | AE9: ='③ Exploitation CR'!AE8 -> 15943 | AF9: ='③ Exploitation CR'!AF8 -> 14400 | AG9: ='③ Exploitation CR'!AG8 -> 17476 | AH9: ='③ Exploitation CR'!AH8 -> 19879 | AI9: ='③ Exploitation CR'!AI8 -> 22074 | AJ9: ='③ Exploitation CR'!AJ8 -> 32266 | AK9: ='③ Exploitation CR'!AK8 -> 38323 | AL9: ='③ Exploitation CR'!AL8 -> 38323 | ... AP9: ='③ Exploitation CR'!AP8 -> 20541 | AQ9: =SUM(AE9,AF9,AG9,AH9,AI9,AJ9,AK9,AL9,AM9,AN9,AO9,AP9) -> 306132
A10: Recettes activités & excursions | C10: ='③ Exploitation CR'!C9 -> 0 | D10: ='③ Exploitation CR'!D9 -> 0 | E10: ='③ Exploitation CR'!E9 -> 0 | F10: ='③ Exploitation CR'!F9 -> 0 | G10: ='③ Exploitation CR'!G9 -> 0 | H10: ='③ Exploitation CR'!H9 -> 0 | I10: ='③ Exploitation CR'!I9 -> 0 | J10: ='③ Exploitation CR'!J9 -> 0 | ... N10: ='③ Exploitation CR'!N9 -> 0 | O10: =SUM(C10,D10,E10,F10,G10,H10,I10,J10,K10,L10,M10,N10) -> 0 | Q10: ='③ Exploitation CR'!Q9 -> 22994 | R10: ='③ Exploitation CR'!R9 -> 20769 | S10: ='③ Exploitation CR'!S9 -> 25248 | T10: ='③ Exploitation CR'!T9 -> 28797 | U10: ='③ Exploitation CR'!U9 -> 32011 | V10: ='③ Exploitation CR'!V9 -> 46904 | W10: ='③ Exploitation CR'!W9 -> 56358 | X10: ='③ Exploitation CR'!X9 -> 56358 | ... AB10: ='③ Exploitation CR'!AB9 -> 29757 | AC10: =SUM(Q10,R10,S10,T10,U10,V10,W10,X10,Y10,Z10,AA10,AB10) -> 446002 | AE10: ='③ Exploitation CR'!AE9 -> 23914 | AF10: ='③ Exploitation CR'!AF9 -> 21600 | AG10: ='③ Exploitation CR'!AG9 -> 26213 | AH10: ='③ Exploitation CR'!AH9 -> 29818 | AI10: ='③ Exploitation CR'!AI9 -> 33111 | AJ10: ='③ Exploitation CR'!AJ9 -> 48399 | AK10: ='③ Exploitation CR'!AK9 -> 57485 | AL10: ='③ Exploitation CR'!AL9 -> 57485 | ... AP10: ='③ Exploitation CR'!AP9 -> 30812 | AQ10: =SUM(AE10,AF10,AG10,AH10,AI10,AJ10,AK10,AL10,AM10,AN10,AO10,AP10) -> 459199
A11: CA Séminaires [supprimé] | C11: 0 | D11: 0 | E11: 0 | F11: 0 | G11: 0 | H11: 0 | I11: 0 | J11: 0 | K11: 0 | L11: 0 | M11: 0 | N11: 0 | O11: 0 | Q11: 0 | R11: 0 | S11: 0 | T11: 0 | U11: 0 | V11: 0 | W11: 0 | X11: 0 | Y11: 0 | Z11: 0 | AA11: 0 | AB11: 0 | AC11: 0 | AE11: 0 | AF11: 0 | AG11: 0 | AH11: 0 | AI11: 0 | AJ11: 0 | AK11: 0 | AL11: 0 | AM11: 0 | AN11: 0 | AO11: 0 | AP11: 0 | AQ11: 0
A12: TOTAL ENCAISSEMENTS | C12: =C6+C7+C8+C9+C10+C11 -> 222760 | D12: =D6+D7+D8+D9+D10+D11 -> 110880 | E12: =E6+E7+E8+E9+E10+E11 -> 180048 | F12: =F6+F7+F8+F9+F10+F11 -> 205920 | G12: =G6+G7+G8+G9+G10+G11 -> 229152 | H12: =H6+H7+H8+H9+H10+H11 -> 336600 | I12: =I6+I7+I8+I9+I10+I11 -> 409200 | J12: =J6+J7+J8+J9+J10+J11 -> 409200 | ... N12: =N6+N7+N8+N9+N10+N11 -> 212784 | O12: =SUM(C12,D12,E12,F12,G12,H12,I12,J12,K12,L12,M12,N12) -> 3229984 | Q12: =Q6+Q7+Q8+Q9+Q10+Q11 -> 206946 | R12: =R6+R7+R8+R9+R10+R11 -> 186920 | S12: =S6+S7+S8+S9+S10+S11 -> 227235 | T12: =T6+T7+T8+T9+T10+T11 -> 259174 | U12: =U6+U7+U8+U9+U10+U11 -> 288102 | V12: =V6+V7+V8+V9+V10+V11 -> 422140 | W12: =W6+W7+W8+W9+W10+W11 -> 507222 | X12: =X6+X7+X8+X9+X10+X11 -> 507222 | ... AB12: =AB6+AB7+AB8+AB9+AB10+AB11 -> 267813 | AC12: =SUM(Q12,R12,S12,T12,U12,V12,W12,X12,Y12,Z12,AA12,AB12) -> 4014024 | AE12: =AE6+AE7+AE8+AE9+AE10+AE11 -> 215226 | AF12: =AF6+AF7+AF8+AF9+AF10+AF11 -> 194397 | AG12: =AG6+AG7+AG8+AG9+AG10+AG11 -> 235920 | AH12: =AH6+AH7+AH8+AH9+AH10+AH11 -> 268363 | AI12: =AI6+AI7+AI8+AI9+AI10+AI11 -> 298002 | AJ12: =AJ6+AJ7+AJ8+AJ9+AJ10+AJ11 -> 435590 | AK12: =AK6+AK7+AK8+AK9+AK10+AK11 -> 517365 | AL12: =AL6+AL7+AL8+AL9+AL10+AL11 -> 517365 | ... AP12: =AP6+AP7+AP8+AP9+AP10+AP11 -> 277308 | AQ12: =SUM(AE12,AF12,AG12,AH12,AI12,AJ12,AK12,AL12,AM12,AN12,AO12,AP12) -> 4132789
A13: DÉCAISSEMENTS
A14: Commissions OTA | C14: ='③ Exploitation CR'!C13 -> 17856 | D14: ='③ Exploitation CR'!D13 -> 16128 | E14: ='③ Exploitation CR'!E13 -> 26189 | F14: ='③ Exploitation CR'!F13 -> 29952 | G14: ='③ Exploitation CR'!G13 -> 33331 | H14: ='③ Exploitation CR'!H13 -> 48960 | I14: ='③ Exploitation CR'!I13 -> 59520 | J14: ='③ Exploitation CR'!J13 -> 59520 | ... N14: ='③ Exploitation CR'!N13 -> 30950 | O14: =SUM(C14,D14,E14,F14,G14,H14,I14,J14,K14,L14,M14,N14) -> 455270 | Q14: ='③ Exploitation CR'!Q13 -> 24527 | R14: ='③ Exploitation CR'!R13 -> 22153 | S14: ='③ Exploitation CR'!S13 -> 26932 | T14: ='③ Exploitation CR'!T13 -> 30717 | U14: ='③ Exploitation CR'!U13 -> 34145 | V14: ='③ Exploitation CR'!V13 -> 50031 | W14: ='③ Exploitation CR'!W13 -> 60115 | X14: ='③ Exploitation CR'!X13 -> 60115 | ... AB14: ='③ Exploitation CR'!AB13 -> 31741 | AC14: =SUM(Q14,R14,S14,T14,U14,V14,W14,X14,Y14,Z14,AA14,AB14) -> 475735 | AE14: ='③ Exploitation CR'!AE13 -> 25508 | AF14: ='③ Exploitation CR'!AF13 -> 23040 | AG14: ='③ Exploitation CR'!AG13 -> 27961 | AH14: ='③ Exploitation CR'!AH13 -> 31806 | AI14: ='③ Exploitation CR'!AI13 -> 35319 | AJ14: ='③ Exploitation CR'!AJ13 -> 51625 | AK14: ='③ Exploitation CR'!AK13 -> 61317 | AL14: ='③ Exploitation CR'!AL13 -> 61317 | ... AP14: ='③ Exploitation CR'!AP13 -> 32866 | AQ14: =SUM(AE14,AF14,AG14,AH14,AI14,AJ14,AK14,AL14,AM14,AN14,AO14,AP14) -> 489811
A15: Achats marchandises restauration | C15: ='③ Exploitation CR'!C14 -> 4464 | D15: ='③ Exploitation CR'!D14 -> 4032 | E15: ='③ Exploitation CR'!E14 -> 6547 | F15: ='③ Exploitation CR'!F14 -> 7488 | G15: ='③ Exploitation CR'!G14 -> 8333 | H15: ='③ Exploitation CR'!H14 -> 12240 | I15: ='③ Exploitation CR'!I14 -> 14880 | J15: ='③ Exploitation CR'!J14 -> 14880 | ... N15: ='③ Exploitation CR'!N14 -> 7738 | O15: =SUM(C15,D15,E15,F15,G15,H15,I15,J15,K15,L15,M15,N15) -> 113818 | Q15: ='③ Exploitation CR'!Q14 -> 6132 | R15: ='③ Exploitation CR'!R14 -> 5538 | S15: ='③ Exploitation CR'!S14 -> 6733 | T15: ='③ Exploitation CR'!T14 -> 7679 | U15: ='③ Exploitation CR'!U14 -> 8536 | V15: ='③ Exploitation CR'!V14 -> 12508 | W15: ='③ Exploitation CR'!W14 -> 15029 | X15: ='③ Exploitation CR'!X14 -> 15029 | ... AB15: ='③ Exploitation CR'!AB14 -> 7935 | AC15: =SUM(Q15,R15,S15,T15,U15,V15,W15,X15,Y15,Z15,AA15,AB15) -> 118934 | AE15: ='③ Exploitation CR'!AE14 -> 6377 | AF15: ='③ Exploitation CR'!AF14 -> 5760 | AG15: ='③ Exploitation CR'!AG14 -> 6990 | AH15: ='③ Exploitation CR'!AH14 -> 7952 | AI15: ='③ Exploitation CR'!AI14 -> 8830 | AJ15: ='③ Exploitation CR'!AJ14 -> 12906 | AK15: ='③ Exploitation CR'!AK14 -> 15329 | AL15: ='③ Exploitation CR'!AL14 -> 15329 | ... AP15: ='③ Exploitation CR'!AP14 -> 8216 | AQ15: =SUM(AE15,AF15,AG15,AH15,AI15,AJ15,AK15,AL15,AM15,AN15,AO15,AP15) -> 122452
A16: Loyer versé à la Holding | C16: ='① Hypothèses'!B24 -> 27761 | D16: ='① Hypothèses'!B24 -> 27761 | E16: ='① Hypothèses'!B24 -> 27761 | F16: ='① Hypothèses'!B24 -> 27761 | G16: ='① Hypothèses'!B24 -> 27761 | H16: ='① Hypothèses'!B24 -> 27761 | I16: ='① Hypothèses'!B24 -> 27761 | J16: ='① Hypothèses'!B24 -> 27761 | K16: ='① Hypothèses'!B24 -> 27761 | L16: ='① Hypothèses'!B24 -> 27761 | M16: ='① Hypothèses'!B24 -> 27761 | N16: ='① Hypothèses'!B24 -> 27761 | O16: =SUM(C16,D16,E16,F16,G16,H16,I16,J16,K16,L16,M16,N16) -> 333132 | Q16: ='① Hypothèses'!B24 -> 27761 | R16: ='① Hypothèses'!B24 -> 27761 | S16: ='① Hypothèses'!B24 -> 27761 | T16: ='① Hypothèses'!B24 -> 27761 | U16: ='① Hypothèses'!B24 -> 27761 | V16: ='① Hypothèses'!B24 -> 27761 | W16: ='① Hypothèses'!B24 -> 27761 | X16: ='① Hypothèses'!B24 -> 27761 | Y16: ='① Hypothèses'!B24 -> 27761 | Z16: ='① Hypothèses'!B24 -> 27761 | AA16: ='① Hypothèses'!B24 -> 27761 | AB16: ='① Hypothèses'!B24 -> 27761 | AC16: =SUM(Q16,R16,S16,T16,U16,V16,W16,X16,Y16,Z16,AA16,AB16) -> 333132 | AE16: ='① Hypothèses'!B24 -> 27761 | AF16: ='① Hypothèses'!B24 -> 27761 | AG16: ='① Hypothèses'!B24 -> 27761 | AH16: ='① Hypothèses'!B24 -> 27761 | AI16: ='① Hypothèses'!B24 -> 27761 | AJ16: ='① Hypothèses'!B24 -> 27761 | AK16: ='① Hypothèses'!B24 -> 27761 | AL16: ='① Hypothèses'!B24 -> 27761 | AM16: ='① Hypothèses'!B24 -> 27761 | AN16: ='① Hypothèses'!B24 -> 27761 | AO16: ='① Hypothèses'!B24 -> 27761 | AP16: ='① Hypothèses'!B24 -> 27761 | AQ16: =SUM(AE16,AF16,AG16,AH16,AI16,AJ16,AK16,AL16,AM16,AN16,AO16,AP16) -> 333132
A17: Assurances | C17: ='③ Exploitation CR'!C16 -> 3750 | D17: ='③ Exploitation CR'!D16 -> 3750 | E17: ='③ Exploitation CR'!E16 -> 3750 | F17: ='③ Exploitation CR'!F16 -> 3750 | G17: ='③ Exploitation CR'!G16 -> 3750 | H17: ='③ Exploitation CR'!H16 -> 3750 | I17: ='③ Exploitation CR'!I16 -> 3750 | J17: ='③ Exploitation CR'!J16 -> 3750 | ... N17: ='③ Exploitation CR'!N16 -> 3750 | O17: =SUM(C17,D17,E17,F17,G17,H17,I17,J17,K17,L17,M17,N17) -> 45000 | Q17: ='③ Exploitation CR'!Q16 -> 3825 | R17: ='③ Exploitation CR'!R16 -> 3825 | S17: ='③ Exploitation CR'!S16 -> 3825 | T17: ='③ Exploitation CR'!T16 -> 3825 | U17: ='③ Exploitation CR'!U16 -> 3825 | V17: ='③ Exploitation CR'!V16 -> 3825 | W17: ='③ Exploitation CR'!W16 -> 3825 | X17: ='③ Exploitation CR'!X16 -> 3825 | ... AB17: ='③ Exploitation CR'!AB16 -> 3825 | AC17: =SUM(Q17,R17,S17,T17,U17,V17,W17,X17,Y17,Z17,AA17,AB17) -> 45900 | AE17: ='③ Exploitation CR'!AE16 -> 3902 | AF17: ='③ Exploitation CR'!AF16 -> 3902 | AG17: ='③ Exploitation CR'!AG16 -> 3902 | AH17: ='③ Exploitation CR'!AH16 -> 3902 | AI17: ='③ Exploitation CR'!AI16 -> 3902 | AJ17: ='③ Exploitation CR'!AJ16 -> 3902 | AK17: ='③ Exploitation CR'!AK16 -> 3902 | AL17: ='③ Exploitation CR'!AL16 -> 3902 | ... AP17: ='③ Exploitation CR'!AP16 -> 3902 | AQ17: =SUM(AE17,AF17,AG17,AH17,AI17,AJ17,AK17,AL17,AM17,AN17,AO17,AP17) -> 46824
A18: Eau, électricité, gaz | C18: ='③ Exploitation CR'!C17 -> 15000 | D18: ='③ Exploitation CR'!D17 -> 15000 | E18: ='③ Exploitation CR'!E17 -> 15000 | F18: ='③ Exploitation CR'!F17 -> 15000 | G18: ='③ Exploitation CR'!G17 -> 15000 | H18: ='③ Exploitation CR'!H17 -> 15000 | I18: ='③ Exploitation CR'!I17 -> 15000 | J18: ='③ Exploitation CR'!J17 -> 15000 | ... N18: ='③ Exploitation CR'!N17 -> 15000 | O18: =SUM(C18,D18,E18,F18,G18,H18,I18,J18,K18,L18,M18,N18) -> 180000 | Q18: ='③ Exploitation CR'!Q17 -> 15300 | R18: ='③ Exploitation CR'!R17 -> 15300 | S18: ='③ Exploitation CR'!S17 -> 15300 | T18: ='③ Exploitation CR'!T17 -> 15300 | U18: ='③ Exploitation CR'!U17 -> 15300 | V18: ='③ Exploitation CR'!V17 -> 15300 | W18: ='③ Exploitation CR'!W17 -> 15300 | X18: ='③ Exploitation CR'!X17 -> 15300 | ... AB18: ='③ Exploitation CR'!AB17 -> 15300 | AC18: =SUM(Q18,R18,S18,T18,U18,V18,W18,X18,Y18,Z18,AA18,AB18) -> 183600 | AE18: ='③ Exploitation CR'!AE17 -> 15606 | AF18: ='③ Exploitation CR'!AF17 -> 15606 | AG18: ='③ Exploitation CR'!AG17 -> 15606 | AH18: ='③ Exploitation CR'!AH17 -> 15606 | AI18: ='③ Exploitation CR'!AI17 -> 15606 | AJ18: ='③ Exploitation CR'!AJ17 -> 15606 | AK18: ='③ Exploitation CR'!AK17 -> 15606 | AL18: ='③ Exploitation CR'!AL17 -> 15606 | ... AP18: ='③ Exploitation CR'!AP17 -> 15606 | AQ18: =SUM(AE18,AF18,AG18,AH18,AI18,AJ18,AK18,AL18,AM18,AN18,AO18,AP18) -> 187272
A19: Entretien & maintenance | C19: ='③ Exploitation CR'!C18 -> 5833 | D19: ='③ Exploitation CR'!D18 -> 5833 | E19: ='③ Exploitation CR'!E18 -> 5833 | F19: ='③ Exploitation CR'!F18 -> 5833 | G19: ='③ Exploitation CR'!G18 -> 5833 | H19: ='③ Exploitation CR'!H18 -> 5833 | I19: ='③ Exploitation CR'!I18 -> 5833 | J19: ='③ Exploitation CR'!J18 -> 5833 | ... N19: ='③ Exploitation CR'!N18 -> 5833 | O19: =SUM(C19,D19,E19,F19,G19,H19,I19,J19,K19,L19,M19,N19) -> 69996 | Q19: ='③ Exploitation CR'!Q18 -> 5950 | R19: ='③ Exploitation CR'!R18 -> 5950 | S19: ='③ Exploitation CR'!S18 -> 5950 | T19: ='③ Exploitation CR'!T18 -> 5950 | U19: ='③ Exploitation CR'!U18 -> 5950 | V19: ='③ Exploitation CR'!V18 -> 5950 | W19: ='③ Exploitation CR'!W18 -> 5950 | X19: ='③ Exploitation CR'!X18 -> 5950 | ... AB19: ='③ Exploitation CR'!AB18 -> 5950 | AC19: =SUM(Q19,R19,S19,T19,U19,V19,W19,X19,Y19,Z19,AA19,AB19) -> 71400 | AE19: ='③ Exploitation CR'!AE18 -> 6069 | AF19: ='③ Exploitation CR'!AF18 -> 6069 | AG19: ='③ Exploitation CR'!AG18 -> 6069 | AH19: ='③ Exploitation CR'!AH18 -> 6069 | AI19: ='③ Exploitation CR'!AI18 -> 6069 | AJ19: ='③ Exploitation CR'!AJ18 -> 6069 | AK19: ='③ Exploitation CR'!AK18 -> 6069 | AL19: ='③ Exploitation CR'!AL18 -> 6069 | ... AP19: ='③ Exploitation CR'!AP18 -> 6069 | AQ19: =SUM(AE19,AF19,AG19,AH19,AI19,AJ19,AK19,AL19,AM19,AN19,AO19,AP19) -> 72828
A20: Marketing & communication | C20: ='③ Exploitation CR'!C19 -> 4167 | D20: ='③ Exploitation CR'!D19 -> 4167 | E20: ='③ Exploitation CR'!E19 -> 4167 | F20: ='③ Exploitation CR'!F19 -> 4167 | G20: ='③ Exploitation CR'!G19 -> 4167 | H20: ='③ Exploitation CR'!H19 -> 4167 | I20: ='③ Exploitation CR'!I19 -> 4167 | J20: ='③ Exploitation CR'!J19 -> 4167 | ... N20: ='③ Exploitation CR'!N19 -> 4167 | O20: =SUM(C20,D20,E20,F20,G20,H20,I20,J20,K20,L20,M20,N20) -> 50004 | Q20: ='③ Exploitation CR'!Q19 -> 4250 | R20: ='③ Exploitation CR'!R19 -> 4250 | S20: ='③ Exploitation CR'!S19 -> 4250 | T20: ='③ Exploitation CR'!T19 -> 4250 | U20: ='③ Exploitation CR'!U19 -> 4250 | V20: ='③ Exploitation CR'!V19 -> 4250 | W20: ='③ Exploitation CR'!W19 -> 4250 | X20: ='③ Exploitation CR'!X19 -> 4250 | ... AB20: ='③ Exploitation CR'!AB19 -> 4250 | AC20: =SUM(Q20,R20,S20,T20,U20,V20,W20,X20,Y20,Z20,AA20,AB20) -> 51000 | AE20: ='③ Exploitation CR'!AE19 -> 4335 | AF20: ='③ Exploitation CR'!AF19 -> 4335 | AG20: ='③ Exploitation CR'!AG19 -> 4335 | AH20: ='③ Exploitation CR'!AH19 -> 4335 | AI20: ='③ Exploitation CR'!AI19 -> 4335 | AJ20: ='③ Exploitation CR'!AJ19 -> 4335 | AK20: ='③ Exploitation CR'!AK19 -> 4335 | AL20: ='③ Exploitation CR'!AL19 -> 4335 | ... AP20: ='③ Exploitation CR'!AP19 -> 4335 | AQ20: =SUM(AE20,AF20,AG20,AH20,AI20,AJ20,AK20,AL20,AM20,AN20,AO20,AP20) -> 52020
A21: Fournitures & linge | C21: ='③ Exploitation CR'!C20 -> 3750 | D21: ='③ Exploitation CR'!D20 -> 3750 | E21: ='③ Exploitation CR'!E20 -> 3750 | F21: ='③ Exploitation CR'!F20 -> 3750 | G21: ='③ Exploitation CR'!G20 -> 3750 | H21: ='③ Exploitation CR'!H20 -> 3750 | I21: ='③ Exploitation CR'!I20 -> 3750 | J21: ='③ Exploitation CR'!J20 -> 3750 | ... N21: ='③ Exploitation CR'!N20 -> 3750 | O21: =SUM(C21,D21,E21,F21,G21,H21,I21,J21,K21,L21,M21,N21) -> 45000 | Q21: ='③ Exploitation CR'!Q20 -> 3825 | R21: ='③ Exploitation CR'!R20 -> 3825 | S21: ='③ Exploitation CR'!S20 -> 3825 | T21: ='③ Exploitation CR'!T20 -> 3825 | U21: ='③ Exploitation CR'!U20 -> 3825 | V21: ='③ Exploitation CR'!V20 -> 3825 | W21: ='③ Exploitation CR'!W20 -> 3825 | X21: ='③ Exploitation CR'!X20 -> 3825 | ... AB21: ='③ Exploitation CR'!AB20 -> 3825 | AC21: =SUM(Q21,R21,S21,T21,U21,V21,W21,X21,Y21,Z21,AA21,AB21) -> 45900 | AE21: ='③ Exploitation CR'!AE20 -> 3902 | AF21: ='③ Exploitation CR'!AF20 -> 3902 | AG21: ='③ Exploitation CR'!AG20 -> 3902 | AH21: ='③ Exploitation CR'!AH20 -> 3902 | AI21: ='③ Exploitation CR'!AI20 -> 3902 | AJ21: ='③ Exploitation CR'!AJ20 -> 3902 | AK21: ='③ Exploitation CR'!AK20 -> 3902 | AL21: ='③ Exploitation CR'!AL20 -> 3902 | ... AP21: ='③ Exploitation CR'!AP20 -> 3902 | AQ21: =SUM(AE21,AF21,AG21,AH21,AI21,AJ21,AK21,AL21,AM21,AN21,AO21,AP21) -> 46824
A22: Expert-comptable | C22: ='③ Exploitation CR'!C21 -> 5417 | D22: ='③ Exploitation CR'!D21 -> 5417 | E22: ='③ Exploitation CR'!E21 -> 5417 | F22: ='③ Exploitation CR'!F21 -> 5417 | G22: ='③ Exploitation CR'!G21 -> 5417 | H22: ='③ Exploitation CR'!H21 -> 5417 | I22: ='③ Exploitation CR'!I21 -> 5417 | J22: ='③ Exploitation CR'!J21 -> 5417 | ... N22: ='③ Exploitation CR'!N21 -> 5417 | O22: =SUM(C22,D22,E22,F22,G22,H22,I22,J22,K22,L22,M22,N22) -> 65004 | Q22: ='③ Exploitation CR'!Q21 -> 5417 | R22: ='③ Exploitation CR'!R21 -> 5417 | S22: ='③ Exploitation CR'!S21 -> 5417 | T22: ='③ Exploitation CR'!T21 -> 5417 | U22: ='③ Exploitation CR'!U21 -> 5417 | V22: ='③ Exploitation CR'!V21 -> 5417 | W22: ='③ Exploitation CR'!W21 -> 5417 | X22: ='③ Exploitation CR'!X21 -> 5417 | ... AB22: ='③ Exploitation CR'!AB21 -> 5417 | AC22: =SUM(Q22,R22,S22,T22,U22,V22,W22,X22,Y22,Z22,AA22,AB22) -> 65004 | AE22: ='③ Exploitation CR'!AE21 -> 5417 | AF22: ='③ Exploitation CR'!AF21 -> 5417 | AG22: ='③ Exploitation CR'!AG21 -> 5417 | AH22: ='③ Exploitation CR'!AH21 -> 5417 | AI22: ='③ Exploitation CR'!AI21 -> 5417 | AJ22: ='③ Exploitation CR'!AJ21 -> 5417 | AK22: ='③ Exploitation CR'!AK21 -> 5417 | AL22: ='③ Exploitation CR'!AL21 -> 5417 | ... AP22: ='③ Exploitation CR'!AP21 -> 5417 | AQ22: =SUM(AE22,AF22,AG22,AH22,AI22,AJ22,AK22,AL22,AM22,AN22,AO22,AP22) -> 65004
A23: Autres charges | C23: ='③ Exploitation CR'!C22 -> 8333 | D23: ='③ Exploitation CR'!D22 -> 8333 | E23: ='③ Exploitation CR'!E22 -> 8333 | F23: ='③ Exploitation CR'!F22 -> 8333 | G23: ='③ Exploitation CR'!G22 -> 8333 | H23: ='③ Exploitation CR'!H22 -> 8333 | I23: ='③ Exploitation CR'!I22 -> 8333 | J23: ='③ Exploitation CR'!J22 -> 8333 | ... N23: ='③ Exploitation CR'!N22 -> 8333 | O23: =SUM(C23,D23,E23,F23,G23,H23,I23,J23,K23,L23,M23,N23) -> 99996 | Q23: ='③ Exploitation CR'!Q22 -> 8500 | R23: ='③ Exploitation CR'!R22 -> 8500 | S23: ='③ Exploitation CR'!S22 -> 8500 | T23: ='③ Exploitation CR'!T22 -> 8500 | U23: ='③ Exploitation CR'!U22 -> 8500 | V23: ='③ Exploitation CR'!V22 -> 8500 | W23: ='③ Exploitation CR'!W22 -> 8500 | X23: ='③ Exploitation CR'!X22 -> 8500 | ... AB23: ='③ Exploitation CR'!AB22 -> 8500 | AC23: =SUM(Q23,R23,S23,T23,U23,V23,W23,X23,Y23,Z23,AA23,AB23) -> 102000 | AE23: ='③ Exploitation CR'!AE22 -> 8670 | AF23: ='③ Exploitation CR'!AF22 -> 8670 | AG23: ='③ Exploitation CR'!AG22 -> 8670 | AH23: ='③ Exploitation CR'!AH22 -> 8670 | AI23: ='③ Exploitation CR'!AI22 -> 8670 | AJ23: ='③ Exploitation CR'!AJ22 -> 8670 | AK23: ='③ Exploitation CR'!AK22 -> 8670 | AL23: ='③ Exploitation CR'!AL22 -> 8670 | ... AP23: ='③ Exploitation CR'!AP22 -> 8670 | AQ23: =SUM(AE23,AF23,AG23,AH23,AI23,AJ23,AK23,AL23,AM23,AN23,AO23,AP23) -> 104040
A24: Impôts & taxes | C24: ='③ Exploitation CR'!C23 -> 10000 | D24: ='③ Exploitation CR'!D23 -> 10000 | E24: ='③ Exploitation CR'!E23 -> 10000 | F24: ='③ Exploitation CR'!F23 -> 10000 | G24: ='③ Exploitation CR'!G23 -> 10000 | H24: ='③ Exploitation CR'!H23 -> 10000 | I24: ='③ Exploitation CR'!I23 -> 10000 | J24: ='③ Exploitation CR'!J23 -> 10000 | ... N24: ='③ Exploitation CR'!N23 -> 10000 | O24: =SUM(C24,D24,E24,F24,G24,H24,I24,J24,K24,L24,M24,N24) -> 120000 | Q24: ='③ Exploitation CR'!Q23 -> 10000 | R24: ='③ Exploitation CR'!R23 -> 10000 | S24: ='③ Exploitation CR'!S23 -> 10000 | T24: ='③ Exploitation CR'!T23 -> 10000 | U24: ='③ Exploitation CR'!U23 -> 10000 | V24: ='③ Exploitation CR'!V23 -> 10000 | W24: ='③ Exploitation CR'!W23 -> 10000 | X24: ='③ Exploitation CR'!X23 -> 10000 | ... AB24: ='③ Exploitation CR'!AB23 -> 10000 | AC24: =SUM(Q24,R24,S24,T24,U24,V24,W24,X24,Y24,Z24,AA24,AB24) -> 120000 | AE24: ='③ Exploitation CR'!AE23 -> 10000 | AF24: ='③ Exploitation CR'!AF23 -> 10000 | AG24: ='③ Exploitation CR'!AG23 -> 10000 | AH24: ='③ Exploitation CR'!AH23 -> 10000 | AI24: ='③ Exploitation CR'!AI23 -> 10000 | AJ24: ='③ Exploitation CR'!AJ23 -> 10000 | AK24: ='③ Exploitation CR'!AK23 -> 10000 | AL24: ='③ Exploitation CR'!AL23 -> 10000 | ... AP24: ='③ Exploitation CR'!AP23 -> 10000 | AQ24: =SUM(AE24,AF24,AG24,AH24,AI24,AJ24,AK24,AL24,AM24,AN24,AO24,AP24) -> 120000
A25: Salaires & charges sociales (employés + gérant) | C25: ='③ Exploitation CR'!C26+'③ Exploitation CR'!C27+'③ Exploitation CR'!C28+'③ Exploitation CR'!C29 -> 13970 | D25: ='③ Exploitation CR'!D26+'③ Exploitation CR'!D27+'③ Exploitation CR'!D28+'③ Exploitation CR'!D29 -> 13970 | E25: ='③ Exploitation CR'!E26+'③ Exploitation CR'!E27+'③ Exploitation CR'!E28+'③ Exploitation CR'!E29 -> 20955 | F25: ='③ Exploitation CR'!F26+'③ Exploitation CR'!F27+'③ Exploitation CR'!F28+'③ Exploitation CR'!F29 -> 20955 | G25: ='③ Exploitation CR'!G26+'③ Exploitation CR'!G27+'③ Exploitation CR'!G28+'③ Exploitation CR'!G29 -> 38100 | H25: ='③ Exploitation CR'!H26+'③ Exploitation CR'!H27+'③ Exploitation CR'!H28+'③ Exploitation CR'!H29 -> 38100 | I25: ='③ Exploitation CR'!I26+'③ Exploitation CR'!I27+'③ Exploitation CR'!I28+'③ Exploitation CR'!I29 -> 38100 | J25: ='③ Exploitation CR'!J26+'③ Exploitation CR'!J27+'③ Exploitation CR'!J28+'③ Exploitation CR'!J29 -> 38100 | ... N25: ='③ Exploitation CR'!N26+'③ Exploitation CR'!N27+'③ Exploitation CR'!N28+'③ Exploitation CR'!N29 -> 38100 | O25: =SUM(C25,D25,E25,F25,G25,H25,I25,J25,K25,L25,M25,N25) -> 374650 | Q25: ='③ Exploitation CR'!Q26+'③ Exploitation CR'!Q27+'③ Exploitation CR'!Q28+'③ Exploitation CR'!Q29 -> 38862 | R25: ='③ Exploitation CR'!R26+'③ Exploitation CR'!R27+'③ Exploitation CR'!R28+'③ Exploitation CR'!R29 -> 38862 | S25: ='③ Exploitation CR'!S26+'③ Exploitation CR'!S27+'③ Exploitation CR'!S28+'③ Exploitation CR'!S29 -> 38862 | T25: ='③ Exploitation CR'!T26+'③ Exploitation CR'!T27+'③ Exploitation CR'!T28+'③ Exploitation CR'!T29 -> 38862 | U25: ='③ Exploitation CR'!U26+'③ Exploitation CR'!U27+'③ Exploitation CR'!U28+'③ Exploitation CR'!U29 -> 38862 | V25: ='③ Exploitation CR'!V26+'③ Exploitation CR'!V27+'③ Exploitation CR'!V28+'③ Exploitation CR'!V29 -> 38862 | W25: ='③ Exploitation CR'!W26+'③ Exploitation CR'!W27+'③ Exploitation CR'!W28+'③ Exploitation CR'!W29 -> 38862 | X25: ='③ Exploitation CR'!X26+'③ Exploitation CR'!X27+'③ Exploitation CR'!X28+'③ Exploitation CR'!X29 -> 38862 | ... AB25: ='③ Exploitation CR'!AB26+'③ Exploitation CR'!AB27+'③ Exploitation CR'!AB28+'③ Exploitation CR'!AB29 -> 38862 | AC25: =SUM(Q25,R25,S25,T25,U25,V25,W25,X25,Y25,Z25,AA25,AB25) -> 466344 | AE25: ='③ Exploitation CR'!AE26+'③ Exploitation CR'!AE27+'③ Exploitation CR'!AE28+'③ Exploitation CR'!AE29 -> 39639 | AF25: ='③ Exploitation CR'!AF26+'③ Exploitation CR'!AF27+'③ Exploitation CR'!AF28+'③ Exploitation CR'!AF29 -> 39639 | AG25: ='③ Exploitation CR'!AG26+'③ Exploitation CR'!AG27+'③ Exploitation CR'!AG28+'③ Exploitation CR'!AG29 -> 39639 | AH25: ='③ Exploitation CR'!AH26+'③ Exploitation CR'!AH27+'③ Exploitation CR'!AH28+'③ Exploitation CR'!AH29 -> 39639 | AI25: ='③ Exploitation CR'!AI26+'③ Exploitation CR'!AI27+'③ Exploitation CR'!AI28+'③ Exploitation CR'!AI29 -> 39639 | AJ25: ='③ Exploitation CR'!AJ26+'③ Exploitation CR'!AJ27+'③ Exploitation CR'!AJ28+'③ Exploitation CR'!AJ29 -> 39639 | AK25: ='③ Exploitation CR'!AK26+'③ Exploitation CR'!AK27+'③ Exploitation CR'!AK28+'③ Exploitation CR'!AK29 -> 39639 | AL25: ='③ Exploitation CR'!AL26+'③ Exploitation CR'!AL27+'③ Exploitation CR'!AL28+'③ Exploitation CR'!AL29 -> 39639 | ... AP25: ='③ Exploitation CR'!AP26+'③ Exploitation CR'!AP27+'③ Exploitation CR'!AP28+'③ Exploitation CR'!AP29 -> 39639 | AQ25: =SUM(AE25,AF25,AG25,AH25,AI25,AJ25,AK25,AL25,AM25,AN25,AO25,AP25) -> 475668
A26: TOTAL DÉCAISSEMENTS | C26: =C14+C15+C16+C17+C18+C19+C20+C21+C22+C23+C24+C25 -> 120301 | D26: =D14+D15+D16+D17+D18+D19+D20+D21+D22+D23+D24+D25 -> 118141 | E26: =E14+E15+E16+E17+E18+E19+E20+E21+E22+E23+E24+E25 -> 137702 | F26: =F14+F15+F16+F17+F18+F19+F20+F21+F22+F23+F24+F25 -> 142406 | G26: =G14+G15+G16+G17+G18+G19+G20+G21+G22+G23+G24+G25 -> 163775 | H26: =H14+H15+H16+H17+H18+H19+H20+H21+H22+H23+H24+H25 -> 183311 | I26: =I14+I15+I16+I17+I18+I19+I20+I21+I22+I23+I24+I25 -> 196511 | J26: =J14+J15+J16+J17+J18+J19+J20+J21+J22+J23+J24+J25 -> 196511 | ... N26: =N14+N15+N16+N17+N18+N19+N20+N21+N22+N23+N24+N25 -> 160799 | O26: =SUM(C26,D26,E26,F26,G26,H26,I26,J26,K26,L26,M26,N26) -> 1951870 | Q26: =Q14+Q15+Q16+Q17+Q18+Q19+Q20+Q21+Q22+Q23+Q24+Q25 -> 154349 | R26: =R14+R15+R16+R17+R18+R19+R20+R21+R22+R23+R24+R25 -> 151381 | S26: =S14+S15+S16+S17+S18+S19+S20+S21+S22+S23+S24+S25 -> 157355 | T26: =T14+T15+T16+T17+T18+T19+T20+T21+T22+T23+T24+T25 -> 162086 | U26: =U14+U15+U16+U17+U18+U19+U20+U21+U22+U23+U24+U25 -> 166371 | V26: =V14+V15+V16+V17+V18+V19+V20+V21+V22+V23+V24+V25 -> 186229 | W26: =W14+W15+W16+W17+W18+W19+W20+W21+W22+W23+W24+W25 -> 198834 | X26: =X14+X15+X16+X17+X18+X19+X20+X21+X22+X23+X24+X25 -> 198834 | ... AB26: =AB14+AB15+AB16+AB17+AB18+AB19+AB20+AB21+AB22+AB23+AB24+AB25 -> 163366 | AC26: =SUM(Q26,R26,S26,T26,U26,V26,W26,X26,Y26,Z26,AA26,AB26) -> 2078949 | AE26: =AE14+AE15+AE16+AE17+AE18+AE19+AE20+AE21+AE22+AE23+AE24+AE25 -> 157186 | AF26: =AF14+AF15+AF16+AF17+AF18+AF19+AF20+AF21+AF22+AF23+AF24+AF25 -> 154101 | AG26: =AG14+AG15+AG16+AG17+AG18+AG19+AG20+AG21+AG22+AG23+AG24+AG25 -> 160252 | AH26: =AH14+AH15+AH16+AH17+AH18+AH19+AH20+AH21+AH22+AH23+AH24+AH25 -> 165059 | AI26: =AI14+AI15+AI16+AI17+AI18+AI19+AI20+AI21+AI22+AI23+AI24+AI25 -> 169450 | AJ26: =AJ14+AJ15+AJ16+AJ17+AJ18+AJ19+AJ20+AJ21+AJ22+AJ23+AJ24+AJ25 -> 189832 | AK26: =AK14+AK15+AK16+AK17+AK18+AK19+AK20+AK21+AK22+AK23+AK24+AK25 -> 201947 | AL26: =AL14+AL15+AL16+AL17+AL18+AL19+AL20+AL21+AL22+AL23+AL24+AL25 -> 201947 | ... AP26: =AP14+AP15+AP16+AP17+AP18+AP19+AP20+AP21+AP22+AP23+AP24+AP25 -> 166383 | AQ26: =SUM(AE26,AF26,AG26,AH26,AI26,AJ26,AK26,AL26,AM26,AN26,AO26,AP26) -> 2115875
A27: SOLDES DE TRÉSORERIE
A28: SOLDE DU MOIS | C28: =C12-C26 -> 102459 | D28: =D12-D26 -> -7261 | E28: =E12-E26 -> 42346 | F28: =F12-F26 -> 63514 | G28: =G12-G26 -> 65377 | H28: =H12-H26 -> 153289 | I28: =I12-I26 -> 212689 | J28: =J12-J26 -> 212689 | ... N28: =N12-N26 -> 51985 | O28: =SUM(C28,D28,E28,F28,G28,H28,I28,J28,K28,L28,M28,N28) -> 1278114 | Q28: =Q12-Q26 -> 52597 | R28: =R12-R26 -> 35539 | S28: =S12-S26 -> 69880 | T28: =T12-T26 -> 97088 | U28: =U12-U26 -> 121731 | V28: =V12-V26 -> 235911 | W28: =W12-W26 -> 308388 | X28: =X12-X26 -> 308388 | ... AB28: =AB12-AB26 -> 104447 | AC28: =SUM(Q28,R28,S28,T28,U28,V28,W28,X28,Y28,Z28,AA28,AB28) -> 1935075 | AE28: =AE12-AE26 -> 58040 | AF28: =AF12-AF26 -> 40296 | AG28: =AG12-AG26 -> 75668 | AH28: =AH12-AH26 -> 103304 | AI28: =AI12-AI26 -> 128552 | AJ28: =AJ12-AJ26 -> 245758 | AK28: =AK12-AK26 -> 315418 | AL28: =AL12-AL26 -> 315418 | ... AP28: =AP12-AP26 -> 110925 | AQ28: =SUM(AE28,AF28,AG28,AH28,AI28,AJ28,AK28,AL28,AM28,AN28,AO28,AP28) -> 2016914
A29: Solde précédent (report) | C29: ='① Hypothèses'!B90 -> 50000 | D29: =C28+C29 -> 152459 | E29: =D28+D29 -> 145198 | F29: =E28+E29 -> 187544 | G29: =F28+F29 -> 251058 | H29: =G28+G29 -> 316435 | I29: =H28+H29 -> 469724 | J29: =I28+I29 -> 682413 | K29: =J28+J29 -> 895102 | ... O29: =N28+N29 -> 1328114 | Q29: =N28+N29 -> 1328114 | R29: =Q28+Q29 -> 1380711 | S29: =R28+R29 -> 1416250 | T29: =S28+S29 -> 1486130 | U29: =T28+T29 -> 1583218 | V29: =U28+U29 -> 1704949 | W29: =V28+V29 -> 1940860 | X29: =W28+W29 -> 2249248 | Y29: =X28+X29 -> 2557636 | ... AC29: =AB28+AB29 -> 3263189 | AE29: =AB28+AB29 -> 3263189 | AF29: =AE28+AE29 -> 3321229 | AG29: =AF28+AF29 -> 3361525 | AH29: =AG28+AG29 -> 3437193 | AI29: =AH28+AH29 -> 3540497 | AJ29: =AI28+AI29 -> 3669049 | AK29: =AJ28+AJ29 -> 3914807 | AL29: =AK28+AK29 -> 4230225 | AM29: =AL28+AL29 -> 4545643 | ... AQ29: =AP28+AP29 -> 5280103
A30: SOLDE CUMULÉ DE TRÉSORERIE | C30: =C28+C29 -> 152459 | D30: =D28+D29 -> 145198 | E30: =E28+E29 -> 187544 | F30: =F28+F29 -> 251058 | G30: =G28+G29 -> 316435 | H30: =H28+H29 -> 469724 | I30: =I28+I29 -> 682413 | J30: =J28+J29 -> 895102 | ... N30: =N28+N29 -> 1328114 | O30: =SUM(C30,D30,E30,F30,G30,H30,I30,J30,K30,L30,M30,N30) -> 8043887 | Q30: =Q28+Q29 -> 1380711 | R30: =R28+R29 -> 1416250 | S30: =S28+S29 -> 1486130 | T30: =T28+T29 -> 1583218 | U30: =U28+U29 -> 1704949 | V30: =V28+V29 -> 1940860 | W30: =W28+W29 -> 2249248 | X30: =X28+X29 -> 2557636 | ... AB30: =AB28+AB29 -> 3263189 | AC30: =SUM(Q30,R30,S30,T30,U30,V30,W30,X30,Y30,Z30,AA30,AB30) -> 26671398 | AE30: =AE28+AE29 -> 3321229 | AF30: =AF28+AF29 -> 3361525 | AG30: =AG28+AG29 -> 3437193 | AH30: =AH28+AH29 -> 3540497 | AI30: =AI28+AI29 -> 3669049 | AJ30: =AJ28+AJ29 -> 3914807 | AK30: =AK28+AK29 -> 4230225 | AL30: =AL28+AL29 -> 4545643 | ... AP30: =AP28+AP29 -> 5280103 | AQ30: =SUM(AE30,AF30,AG30,AH30,AI30,AJ30,AK30,AL30,AM30,AN30,AO30,AP30) -> 50399226

Sheet ⑤ SIG
A1: CONSOLIDÉ SOLDES INTERMÉDIAIRES DE GESTION & RENTABILITÉ RIAD DU MÉMOIRE
A4: INDICATEUR | B4: AN1 | C4: % CA | D4: AN2 | E4: % CA | F4: AN3 | G4: % CA
A5: EXPLOITATION SARL
A6: CA TOTAL EXPLOITATION | B6: ='③ Exploitation CR'!O11 -> 3129984 | D6: ='③ Exploitation CR'!AC11 -> 4014024 | F6: ='③ Exploitation CR'!AQ11 -> 4132789
A7: CA Hébergement | B7: ='③ Exploitation CR'!O6 -> 2845440 | C7: =IFERROR(B7/B6,0) -> 0.90909091 | D7: ='③ Exploitation CR'!AC6 -> 2973352 | E7: =IFERROR(D7/D6,0) -> 0.74074096 | F7: ='③ Exploitation CR'!AQ6 -> 3061326 | G7: =IFERROR(F7/F6,0) -> 0.74074094
A8: CA Restauration | B8: ='③ Exploitation CR'!O7 -> 284544 | C8: =IFERROR(B8/B6,0) -> 0.090909091 | D8: ='③ Exploitation CR'!AC7 -> 297335 | E8: =IFERROR(D8/D6,0) -> 0.074074046 | F8: ='③ Exploitation CR'!AQ7 -> 306132 | G8: =IFERROR(F8/F6,0) -> 0.074073949
A9: CA Spa & Hammam | B9: ='③ Exploitation CR'!O8 -> 0 | C9: =IFERROR(B9/B6,0) -> 0 | D9: ='③ Exploitation CR'!AC8 -> 297335 | E9: =IFERROR(D9/D6,0) -> 0.074074046 | F9: ='③ Exploitation CR'!AQ8 -> 306132 | G9: =IFERROR(F9/F6,0) -> 0.074073949
A10: CA Activités & Excursions | B10: ='③ Exploitation CR'!O9 -> 0 | C10: 0 | D10: ='③ Exploitation CR'!AC9 -> 446002 | E10: 0 | F10: ='③ Exploitation CR'!AQ9 -> 459199 | G10: 0
A11: Charges externes (dont loyer Holding) | B11: ='③ Exploitation CR'!O24 -> 1577220 | C11: =IFERROR(B11/B6,0) -> 0.50390673 | D11: ='③ Exploitation CR'!AC24 -> 1612605 | E11: =IFERROR(D11/D6,0) -> 0.40174274 | F11: ='③ Exploitation CR'!AQ24 -> 1640207 | G11: =IFERROR(F11/F6,0) -> 0.39687654
A12: = dont Loyer Holding | B12: ='③ Exploitation CR'!O15 -> 333132 | C12: =IFERROR(B12/B6,0) -> 0.10643249 | D12: ='③ Exploitation CR'!AC15 -> 333132 | E12: =IFERROR(D12/D6,0) -> 0.08299203 | F12: ='③ Exploitation CR'!AQ15 -> 333132 | G12: =IFERROR(F12/F6,0) -> 0.080607067
A13: Rémunérations & charges sociales | B13: ='③ Exploitation CR'!O30 -> 374650 | C13: =IFERROR(B13/B6,0) -> 0.1196971 | D13: ='③ Exploitation CR'!AC30 -> 466344 | E13: =IFERROR(D13/D6,0) -> 0.11617868 | F13: ='③ Exploitation CR'!AQ30 -> 475668 | G13: =IFERROR(F13/F6,0) -> 0.11509613
A14: MARGE BRUTE | B14: ='③ Exploitation CR'!O34 -> 2533135 | C14: =IFERROR(B14/B6,0) -> 0.80931244 | D14: ='③ Exploitation CR'!AC34 -> 3419355 | E14: =IFERROR(D14/D6,0) -> 0.85185216 | F14: ='③ Exploitation CR'!AQ34 -> 3520526 | G14: =IFERROR(F14/F6,0) -> 0.85185234
A15: EXCÉDENT BRUT D'EXPLOITATION (EBE) | B15: ='③ Exploitation CR'!O35 -> 1178114 | C15: =IFERROR(B15/B6,0) -> 0.37639617 | D15: ='③ Exploitation CR'!AC35 -> 1935075 | E15: =IFERROR(D15/D6,0) -> 0.48207858 | F15: ='③ Exploitation CR'!AQ35 -> 2016914 | G15: =IFERROR(F15/F6,0) -> 0.48802733
A16: Dotations aux amortissements SARL | B16: ='③ Exploitation CR'!O32 -> 58692 | C16: =IFERROR(B16/B6,0) -> 0.018751534 | D16: ='③ Exploitation CR'!AC32 -> 58692 | E16: =IFERROR(D16/D6,0) -> 0.014621736 | F16: ='③ Exploitation CR'!AQ32 -> 58692 | G16: =IFERROR(F16/F6,0) -> 0.014201548
A17: RÉSULTAT D'EXPLOITATION (REX) | B17: ='③ Exploitation CR'!O36 -> 1119422 | C17: =IFERROR(B17/B6,0) -> 0.35764464 | D17: ='③ Exploitation CR'!AC36 -> 1876383 | E17: =IFERROR(D17/D6,0) -> 0.46745685 | F17: ='③ Exploitation CR'!AQ36 -> 1958222 | G17: =IFERROR(F17/F6,0) -> 0.47382579
A18: RÉSULTAT NET EXPLOITATION (avant IS) | B18: ='③ Exploitation CR'!O37 -> 1119422 | C18: =IFERROR(B18/B6,0) -> 0.35764464 | D18: ='③ Exploitation CR'!AC37 -> 1876383 | E18: =IFERROR(D18/D6,0) -> 0.46745685 | F18: ='③ Exploitation CR'!AQ37 -> 1958222 | G18: =IFERROR(F18/F6,0) -> 0.47382579
A20: HOLDING Compte de résultat synthétique
A21: Loyers perçus (produits Holding) | B21: ='② Holding CR'!O6 -> 333132 | D21: ='② Holding CR'!AC6 -> 333132 | F21: ='② Holding CR'!AQ6 -> 333132
A22: Mensualité emprunt décaissée | B22: ='② Holding CR'!O9 -> 266508 | D22: ='② Holding CR'!AC9 -> 266508 | F22: ='② Holding CR'!AQ9 -> 266508
A23: Surplus trésorerie Holding (loyer−mensualité) | B23: ='② Holding CR'!O14 -> 24624 | D23: ='② Holding CR'!AC14 -> 23784 | F23: ='② Holding CR'!AQ14 -> 22944
A24: Amortissement murs (gros œuvre) | B24: ='② Holding CR'!O11 -> 309996 | D24: ='② Holding CR'!AC11 -> 309996 | F24: ='② Holding CR'!AQ11 -> 309996
A25: RÉSULTAT NET HOLDING (comptable) | B25: ='② Holding CR'!O15 -> -285372 | D25: ='② Holding CR'!AC15 -> -286212 | F25: ='② Holding CR'!AQ15 -> -287052
A28: Loyer Holding : couvre 100% mensualité emprunt (6% / 20 ans) + marge sécurité 15%
